Workbook

Sheet Instructions & Method
B1: Instructions, principles and formulas
B2: 1. What this workbook answers
B3: A borrower can fund itself with a bond or with an amortising loan of the same amount. Loans are routinely priced by reading the borrower's own bond curve at the loan's weighted average life (WAL) — the 'shortcut'. That shortcut is biased: on an upward-sloping curve it UNDER-charges, so the borrower saves. This workbook measures that saving precisely, for (a) a FLOATING loan priced off the bond Z-spread curve and (b) a FIXED loan priced off the bond YTM curve.
B4: The saving is NET: before the WAL date the loan's exposure is short-dated and genuinely cheaper than the WAL point, so the borrower OVERPAYS there (loss phase); after the WAL the exposure is long-dated and dearer, so the borrower UNDERPAYS (benefit phase). The workbook reports both phases and the net — exactly, not as an approximation (see §4.6).
B5: 2. How to use it (5 minutes)
B6: 1) Tab 'Inputs', rows 4–10: currency (USD/EUR), amount, drawdown years x, repayment years y, and the over/under adjustment X in bp for each loan type (0 = loan priced exactly at the curve point equal to the WAL).
B7: 2) Tab 'Inputs', rows 28–57: paste the bond Z-spread curve (bp), the bond YTM curve (%) and the swap par curve (%) at 1Y…30Y. Leave cells BLANK where you have no point — the model linearly interpolates between known points and holds flat beyond the ends (flagged). You need at least one point per curve; in practice give at least 1Y, 2Y, 3Y, 5Y, 7Y, 10Y and every bond point you have. Credit curve to 20Y is enough for loans up to 20Y; for longer loans see the warning on Results.
B8: 3) Tab 'Inputs', rows 13–19: additional market inputs — recovery rate (default 40%), EUR swap basis, optional 6M fixing. Defaults are correct for standard cases; overrides are optional. Rows 22–24: optional fees/new-issue premium (default 0).
B9: 4) Read tab 'Results'. Green = borrower saves, red = borrower overpays. Check the 'Integrity checks' block reads OK and read the 'Warnings' block.
B10: 5) Nothing else to run: there is NO Goal Seek, Solver or macro. The credit-curve bootstrap is solved in closed form (§4.3), so everything recalculates live.
B11: 3. Principles (why the WAL shortcut is wrong)
B12: P1 — Quoted curves are SPOT averages. A 10Y Z-spread already averages credit risk over years 0–10. Money outstanding in year 15 costs the FORWARD (marginal) credit cost of year 15, not the 15Y spot spread. The model therefore converts each curve into piecewise-constant forward hazard rates λ (one per year) before pricing. Exposure-weighting the spot curve instead double-counts the early years and typically gets even the SIGN wrong.
... B54: Differences from the reference spec, all deliberate for precision: annual (not 5/10/20/30Y) hazard buckets; simple forwards DF(t−1)/DF(t) − 1 instead of ln(DF ratio), so a riskless floater prices exactly at par; swap-curve bootstrap with the correct fixed-leg day count; drawdown period; shortcut read on the curve at the exact WAL (not rounded); exact (not indicative) decomposition.

Sheet Inputs
B1: Loan vs Bond: WAL-pricing wedge calculator — INPUTS
B2: Edit only the yellow cells (blue text). Everything else recalculates live. Example values are ILLUSTRATIVE (a EUR BBB-type issuer) — replace them with today's market data.
B3: 1. Transaction (required)
B4: Currency | C4: EUR | F4: USD or EUR. Drives the default swap/YTM conventions and the money labels.
B5: Loan amount = bond amount | C5: 5000000000 | F5: Same amount for the loan and the bond alternative.
B6: Disbursement (drawdown) period x (years) | C6: 1 | F6: Linear: equal drawdowns every 6 months starting at signing (t = 0). 0 = fully drawn at signing. Multiples of 0.5.
B7: Repayment period y (years) | C7: 23 | F7: Starts after the drawdown period. Equal semi-annual instalments, first one 6m after the last drawdown period ends. Multiples of 0.5, > 0.
B8: FLOATING loan: margin vs Z-spread at WAL (bps) | C8: 0 | F8: 0 = loan margin exactly equals the bond Z-spread read at the loan's WAL. +10 = 10bp above; −10 = 10bp below.
B9: FIXED loan: rate vs YTM at WAL (bps) | C9: 0 | F9: 0 = loan fixed rate exactly equals the bond YTM read at the loan's WAL. +/− as above.
B10: Valuation / pricing date | C10: 46321 | F10: Date the market data below was observed. Informational.
B12: 2. Additional market inputs (needed for the precise calculation — see tab 'Data Sourcing')
B13: Recovery rate on default (R) | C13: 0.4 | F13: Senior unsecured market standard 40%. Result is very insensitive to R (λ scales by 1/(1−R), cost by (1−R)).
B14: EUR swap curve basis (EUR only) | C14: EURIBOR6M | F14: EURIBOR6M = EUR swaps vs 6M Euribor (annual 30/360 fixed leg). ESTR = €STR OIS (annual ACT/360). Use the curve your Z-spreads are quoted against. Ignored for USD (SOFR OIS).
B15: Swap fixed-leg accrual factor — override (blank = default) | F15: Leave blank. Default: USD SOFR OIS ACT/360 = 365.25/360; EUR vs 6M Euribor 30/360 = 1; EUR €STR ACT/360 = 365.25/360.
B16: Swap fixed-leg accrual factor USED | C16: =IF(C15<>"",C15,IF(C4="USD",365.25/360,IF(C14="ESTR",365.25/360,1))) -> 1 | F16: Formula — do not edit.
B17: Bond YTM compounding frequency — override (blank = default) | F17: Leave blank. Default: EUR bonds annual coupons = 1; USD bonds semi-annual = 2.
B18: Bond YTM compounding frequency USED | C18: =IF(C17<>"",C17,IF(C4="USD",2,1)) -> 1 | F18: Formula — do not edit.
B19: 6M floating-rate fixing (optional, %) | C19: 0.03019 | F19: Optional. USD: 6M Term SOFR; EUR: 6M EURIBOR (or 6M €STR OIS if basis = ESTR). Pins the 6-month discount factor. Blank = log-linear from 1Y swap.
B21: 3. Optional all-in cost adjustments (default 0 — the headline hazard wedge ignores them)
B22: Loan upfront / arrangement fee (bps flat, paid at signing) | C22: 0 | F22: Cost to the borrower of the loan route.
B23: Bond issuance costs (bps flat: fees, legal, rating, listing) | C23: 0 | F23: Cost to the borrower of the bond route.
B24: Bond new-issue premium (bps running) | C24: 0 | F24: Concession over the secondary curve a new bond would pay.
B26: 4. Curves — one row per year. Leave a cell BLANK where no data: the model interpolates linearly (flat beyond the ends, flagged).
B27: Tenor | C27: Bond Z-spread (bp) [floating calc] | D27: Bond YTM (%) [fixed calc] | E27: Swap par rate (%) [risk-free curve] | F27: Notes
B28: 1Y | C28: -19 | D28: 0.03032 | E28: 0.0327 | F28: Z-spread: bp over the swap curve in column E. YTM: % in the bond's own compounding (row 18). Swap: par rates, %.
B29: 2Y | C29: -15 | D29: 0.03242 | E29: 0.0342 | F29: Swap curve should reach the loan's final maturity (tenors up to 30Y available).
B30: 3Y | C30: -14 | D30: 0.03349 | E30: 0.0345
B31: 4Y | C31: -2 | D31: 0.03431 | E31: 0.0344
B32: 5Y | C32: 6 | D32: 0.03522 | E32: 0.0344
B33: 6Y | C33: 13 | D33: 0.03597 | E33: 0.0344
B34: 7Y | C34: 24 | D34: 0.03726 | E34: 0.0344
B35: 8Y | C35: 30 | D35: 0.03804 | E35: 0.0345
B36: 9Y | C36: 37 | D36: 0.03888
B37: 10Y | C37: 42 | D37: 0.03942 | E37: 0.0347
B38: 11Y | C38: 46 | D38: 0.03995
B39: 12Y
B40: 13Y
B41: 14Y | C41: 61 | D41: 0.04198
B42: 15Y | C42: 65 | D42: 0.04256 | E42: 0.0351
B43: 16Y
B44: 17Y
B45: 18Y | C45: 74 | D45: 0.0432
B46: 19Y
B47: 20Y | C47: 78 | D47: 0.04349 | E47: 0.0347
B48: 21Y | F48: 21Y–30Y credit points are optional. Beyond the last bond point the last forward hazard rate is extended (flagged on Results).
B49: 22Y
B50: 23Y
B51: 24Y
B52: 25Y | C52: 89 | D52: 0.04349
B53: 26Y
B54: 27Y
B55: 28Y | C55: 92 | D55: 0.04376
B56: 29Y
B57: 30Y | E57: 0.0329

Sheet Results
B1: RESULTS — what the borrower saves (or overpays) by taking the loan priced off the bond curve at the WAL
B2: ="Currency: "&Inputs!C4&" | Amount: "&TEXT(Inputs!C5,"#,##0")&" | Drawdown "&TEXT(Inputs!C6,"0.0")&"y + repayment "&TEXT(Inputs!C7,"0.0")&"y | Market data as of "&TEXT(Inputs!C10,"dd-mmm-yyyy") -> Currency: EUR | Amount: 5000000000,0 | Drawdown 01y + repayment 23y | Market data as of 26-Oct-2026
B3: Sign convention: POSITIVE = borrower SAVES vs. the bond-equivalent (fair) cost of the same profile; NEGATIVE = borrower pays in excess.
B5: Metric | C5: FLOATING loan vs Z-spread curve | D5: FIXED loan vs YTM curve | F5: How to read it
B6: Loan profile
B7: Final maturity (years) | C7: =Calc_Floating!$E$26 -> 24 | D7: =Calc_Fixed!$E$26 -> 24
B8: Weighted average life, WAL (years) | C8: =Calc_Floating!$E$4 -> 12.5 | D8: =Calc_Fixed!$E$4 -> 12.5 | F8: Σ outstanding × time / amount, measured from signing (includes drawdown period).
B9: Risky annuity (PV of 1bp p.a. on the profile, in years) | C9: =Calc_Floating!$E$5 -> 9.0024448 | D9: =Calc_Fixed!$E$5 -> 8.9433309 | F9: Converts bp running into PV: PV = bp/10,000 × amount × annuity.
B10: Pricing
B11: Bond curve read at the WAL (Z-spread bp | YTM quoted basis) | C11: =Calc_Floating!$E$6 -> 53.5 | D11: =Calc_Fixed!$E$6 -> 0.040965 | F11: The market shortcut: linear interpolation of your curve at the exact WAL.
B12: Loan spread / rate CHARGED (shortcut + X) [fixed: s.a. equiv.] | C12: =Calc_Floating!$E$9 -> 0.00535 | D12: =Calc_Fixed!$E$9 -> 0.040553846 | F12: Floating: margin over the reference rate. Fixed: all-in fixed coupon, semi-annual equivalent.
B13: FAIR spread / rate for this exact profile (bond-equivalent cost) | C13: =Calc_Floating!$E$10 -> 0.0062322004 | D13: =Calc_Fixed!$E$10 -> 0.04135539 | F13: What it would cost to fund this exact drawdown/amortisation profile on the issuer's own bond curve (forward hazard rates, survival, recovery on outstanding balance).
B14: Headline: net saving
B15: NET saving, bp p.a. (fair − charged) | C15: =Calc_Floating!$E$11*10000 -> 8.8220045 | D15: =Calc_Fixed!$E$11*10000 -> 8.0154395 | F15: Net of the loss before WAL and the benefit after WAL (split below).
B16: Net saving as % of the bond-equivalent spread / rate | C16: =IFERROR(Calc_Floating!$E$11/Calc_Floating!$E$10,0) -> 0.14155521 | D16: =IFERROR(Calc_Fixed!$E$11/Calc_Fixed!$E$10,0) -> 0.019381849 | F16: Floating: relative to the fair credit spread. Fixed: relative to the fair all-in fixed rate.
B17: Bond-equivalent ALL-IN rate (annualised, s.a.) | C17: =Calc_Floating!$E$12+Calc_Floating!$E$10 -> 0.040708471 | D17: =Calc_Fixed!$E$10 -> 0.04135539 | F17: Floating: exposure-weighted forward reference rate + fair spread. Fixed: fair fixed rate.
B18: Loan ALL-IN rate (annualised, s.a.) | C18: =Calc_Floating!$E$12+Calc_Floating!$E$9 -> 0.039826271 | D18: =Calc_Fixed!$E$9 -> 0.040553846
B19: Net saving as % of the bond all-in rate | C19: =IFERROR(Calc_Floating!$E$11/(Calc_Floating!$E$12+Calc_Floating!$E$10),0) -> 0.021671176 | D19: =IFERROR(Calc_Fixed!$E$11/Calc_Fixed!$E$10,0) -> 0.019381849
B20: Total saving over the life, nominal (undiscounted) | C20: =Calc_Floating!$E$11*Inputs!$C$5*Calc_Floating!$E$4 -> 55137528 | D20: =Calc_Fixed!$E$11*Inputs!$C$5*Calc_Fixed!$E$4 -> 50096497 | E20: =Inputs!$C$4 -> EUR | F20: bp × amount × WAL (= bp × principal-years).
B21: Total saving over the life, PRESENT VALUE | C21: =Calc_Floating!$E$13*Inputs!$C$5 -> 39709804 | D21: =Calc_Fixed!$E$13*Inputs!$C$5 -> 35842364 | E21: =Inputs!$C$4 -> EUR | F21: Exact: survival-weighted and discounted. This is the economic value transferred to the borrower today.
B22: Average saving per year of loan life (nominal) | C22: =IFERROR(Calc_Floating!$E$11*Inputs!$C$5*Calc_Floating!$E$4/Calc_Floating!$E$26,0) -> 2297397 | D22: =IFERROR(Calc_Fixed!$E$11*Inputs!$C$5*Calc_Fixed!$E$4/Calc_Fixed!$E$26,0) -> 2087354 | E22: =Inputs!$C$4 -> EUR
B23: Decomposition: loss before WAL vs benefit after WAL (EXACT — sums to the net)
B24: LOSS phase (start → WAL): PV, money | C24: =Calc_Floating!$E$15*Inputs!$C$5 -> -26278306 | D24: =Calc_Fixed!$E$15*Inputs!$C$5 -> -27401522 | E24: =Inputs!$C$4 -> EUR | F24: Usually negative: early exposure is cheaper than the WAL point, so the borrower overpays here.
B25: BENEFIT phase (WAL → maturity): PV, money | C25: =Calc_Floating!$E$14*Inputs!$C$5 -> 65988110 | D25: =Calc_Fixed!$E$14*Inputs!$C$5 -> 63243886 | E25: =Inputs!$C$4 -> EUR | F25: Usually positive: late exposure is dearer than the WAL point, so the borrower underpays here.
B26: NET (= loss + benefit) | C26: =C24+C25 -> 39709804 | D26: =D24+D25 -> 35842364 | E26: =Inputs!$C$4 -> EUR | F26: Equals the PV total above.
B27: LOSS phase, contribution to net (bp p.a.) | C27: =Calc_Floating!$E$15/Calc_Floating!$E$5*10000 -> -5.8380377 | D27: =Calc_Fixed!$E$15/Calc_Fixed!$E$5*10000 -> -6.1278112
B28: BENEFIT phase, contribution to net (bp p.a.) | C28: =Calc_Floating!$E$14/Calc_Floating!$E$5*10000 -> 14.660042 | D28: =Calc_Fixed!$E$14/Calc_Fixed!$E$5*10000 -> 14.143251
B29: Principal-years before WAL | C29: =Calc_Floating!$E$17 -> 9.5 | D29: =Calc_Fixed!$E$17 -> 9.5
B30: Principal-years after WAL | C30: =Calc_Floating!$E$16 -> 3 | D30: =Calc_Fixed!$E$16 -> 3 | F30: WAL equalises the QUANTITY of principal-years; it does not put them at the same point in time as a bullet.
B31: Avg fair spread / rate on exposure BEFORE WAL | C31: =Calc_Floating!$E$20 -> 0.0046612849 | D31: =Calc_Fixed!$E$20 -> 0.039833198
B32: Avg fair spread / rate on exposure AFTER WAL | C32: =Calc_Floating!$E$19 -> 0.01497393 | D32: =Calc_Fixed!$E$19 -> 0.050002788
B33: Fixed loan only: where the fixed-rate saving comes from
B34: Risk-free curve effect (bp): profile-weighted fwd − rf par yield at WAL | C34: ="n/a" -> n/a | D34: =(Calc_Fixed!$E$12-Calc_Fixed!$E$25)*10000 -> -1.2327166 | F34: Reading a fixed rate at the WAL also misprices the risk-free term structure. This part is not credit.
B35: Credit / hazard effect (bp) = net − risk-free effect | C35: ="n/a" -> n/a | D35: =Calc_Fixed!$E$11*10000-D34 -> 9.2481561 | F35: The pure net hazard-cost saving inside the fixed-rate wedge.
B36: Optional: all-in incl. fees / new-issue premium (Inputs rows 22–24)
B37: Loan upfront fee, running equivalent (bp p.a.) | C37: =Inputs!$C$22/Calc_Floating!$E$5 -> 0 | D37: =Inputs!$C$22/Calc_Fixed!$E$5 -> 0
B38: Bond issuance costs, running equivalent (bp p.a.) | C38: =Inputs!$C$23/Calc_Floating!$E$5 -> 0 | D38: =Inputs!$C$23/Calc_Fixed!$E$5 -> 0
B39: Bond new-issue premium (bp p.a.) | C39: =Inputs!$C$24 -> 0 | D39: =Inputs!$C$24 -> 0
B40: NET saving incl. costs (bp p.a.) | C40: =Calc_Floating!$E$11*10000-C37+C38+C39 -> 8.8220045 | D40: =Calc_Fixed!$E$11*10000-D37+D38+D39 -> 8.0154395
B41: NET saving incl. costs, PV money | C41: =C40/10000*Inputs!$C$5*Calc_Floating!$E$5 -> 39709804 | D41: =D40/10000*Inputs!$C$5*Calc_Fixed!$E$5 -> 35842364 | E41: =Inputs!$C$4 -> EUR
B42: Integrity checks (should all read OK)
B43: Calibration: every quoted bond reprices to its input (max error, bp) | C43: =Calc_Floating!$E$22 -> 1.5677563e-12 | D43: =Calc_Fixed!$E$22 -> 1.2490009e-12
B44: PV identity: decomposition total vs direct loan PV (difference) | C44: =(Calc_Floating!$E$13-Calc_Floating!$E$21)*Inputs!$C$5 -> -5.8113236e-07 | D44: =(Calc_Fixed!$E$13-Calc_Fixed!$E$21)*Inputs!$C$5 -> -2.0686577e-06
B45: WAL cross-check (two formulas) difference | C45: =Calc_Floating!$E$4-Calc_Floating!$E$24 -> 0 | D45: =Calc_Fixed!$E$4-Calc_Fixed!$E$24 -> 0
B46: Status | C46: =IF(AND(C43<0.0001,ABS(C44)<1,ABS(C45)<0.000001),"OK","CHECK") -> OK | D46: =IF(AND(D43<0.0001,ABS(D44)<1,ABS(D45)<0.000001),"OK","CHECK") -> OK
B47: Warnings
B48: Loan maturity beyond last quoted bond tenor? | C48: =IF(Calc_Floating!$E$26>Curves!E37,"YES — last forward hazard extended "&TEXT(Calc_Floating!$E$26-Curves!E37,"0.0")&"y","no") -> no | D48: =IF(Calc_Fixed!$E$26>Curves!E38,"YES — last forward hazard extended "&TEXT(Calc_Fixed!$E$26-Curves!E38,"0.0")&"y","no") -> no | F48: Beyond the last bond point the model extends the last forward hazard (not the spot spread). Treat as an assumption.
B49: WAL beyond last quoted bond tenor (shortcut read on flat extrapolation)? | C49: =IF(Calc_Floating!$E$4>Curves!E37,"YES","no") -> no | D49: =IF(Calc_Fixed!$E$4>Curves!E38,"YES","no") -> no
B50: Loan maturity beyond last quoted swap tenor? | C50: =IF(Calc_Floating!$E$26>Curves!E39,"YES — swap rate held flat","no") -> no | D50: =IF(Calc_Fixed!$E$26>Curves!E39,"YES — swap rate held flat","no") -> no
B51: Bond curve non-monotonic (allowed, but check data)? | C51: =IF(Curves!E43=1,"YES","no") -> no | D51: =IF(Curves!E44=1,"YES","no") -> no
B52: Negative forward hazard (curve inverts too steeply)? | C52: =IF(Calc_Floating!$E$23<0,"YES — check data","no") -> YES — check data | D52: =IF(Calc_Fixed!$E$23<0,"YES — check data","no") -> YES — check data
B53: Input validity (x, y multiples of 0.5; y>0; x+y ≤ 30; ≥1 point per curve) | C53: =IF(AND(Inputs!C6>=0,MOD(Inputs!C6*2,1)=0,Inputs!C7>0,MOD(Inputs!C7*2,1)=0,Inputs!C6+Inputs!C7<=30,Curves!E40>0,Curves!E42>0),"OK","INVALID INPUTS") -> OK | D53: =IF(AND(Inputs!C6>=0,MOD(Inputs!C6*2,1)=0,Inputs!C7>0,MOD(Inputs!C7*2,1)=0,Inputs!C6+Inputs!C7<=30,Curves!E41>0,Curves!E42>0),"OK","INVALID INPUTS") -> OK

Sheet Data Sourcing
B1: Data Sourcing — how to obtain the inputs (by currency)
B2: Bottom line: the swap curve can be obtained free and reliably from the open internet. The BOND curves (Z-spread and YTM by tenor for a specific issuer) are NOT reliably available free — use Bloomberg (or your bank's pricing). Recovery rate: use 40% unless you have a reason not to.
B3: A. Inputs you must supply and why
B4: 1 Bond Z-spread curve 1Y–20Y (bp) → floating calculation. The issuer's own senior unsecured curve, same currency as the loan. 2 Bond YTM curve 1Y–20Y (%) → fixed calculation. Same issuer/seniority/currency. 3 Swap par curve 1Y–30Y (%) → ADDITIONAL INPUT: risk-free discount factors and forward reference rates. 4 Recovery rate → ADDITIONAL INPUT: default 40% senior unsecured. 5 6M fixing (optional) → ADDITIONAL INPUT: pins the first 6 months of the curve. Forward rates are NOT an input: the workbook derives them from the swap curve.
B5: B. Swap curve — USD (SOFR OIS, annual/annual, ACT/360)
B6: Free / open internet: • Chatham Financial — US market rates page, 'SOFR swap rate (annual/annual)' table, 1Y–30Y, mid-market, end of day: https://www.chathamfinancial.com/technology/us-market-rates (a free login gives hourly-refreshed rates and history). • ICE Benchmark Administration — USD SOFR ICE Swap Rate, published daily around 11:15 New York time, tenors 1Y–30Y: https://www.ice.com/iba/ice-swap-rate (access terms apply; widely redistributed by data vendors). • 6M fixing: CME Term SOFR 6M (cmegroup.com, Term SOFR page; free with registration).
B7: Bloomberg: • Tickers USOSFR1 Curncy … USOSFR10, USOSFR12, USOSFR15, USOSFR20, USOSFR25, USOSFR30 Curncy (USD SOFR OIS par swaps). Quickest: type USOSFR10 Curncy <GO>, or open curve S490 in ICVS <GO> / SWDF <GO> and export the par rates. • 6M fixing: TSFR6M Index. • IMPORTANT: in YAS on your bonds, check which curve the Z-spread is computed against (the curve shown next to Z-spread) — use that same curve here.
B8: Settings for USD: Currency = USD (row 4) sets accrual 365.25/360 and YTM compounding 2 automatically.
B9: C. Swap curve — EUR
B10: Which EUR curve? Use the curve your Z-spreads are measured against. Bloomberg's default for EUR corporate bonds is typically the EUR swap curve vs 6M EURIBOR; if your Z-spreads are vs €STR, set row 14 to ESTR.
B11: Free / open internet: • Chatham Financial — European market rates (EURIBOR swap rates): https://www.chathamfinancial.com/technology/european-market-rates • ICE Benchmark Administration — EUR EURIBOR ICE Swap Rate (published ~11:15 CET) and EUR €STR ICE Swap Rate, 1Y–30Y: https://www.ice.com/iba/ice-swap-rate • 6M EURIBOR fixing: EMMI (euribor-rates.eu / emmi-benchmarks.eu; free with a 24h delay). €STR daily rate: ECB website (ecb.europa.eu) — note this is overnight, not a swap curve.
B12: Bloomberg: • vs 6M EURIBOR (annual 30/360 fixed): EUSA1 Curncy … EUSA10, EUSA12, EUSA15, EUSA20, EUSA25, EUSA30 Curncy; 6M fixing EUR006M Index. Curve in ICVS: S45. • vs €STR (annual ACT/360): EESWE1 Curncy … EESWE30 Curncy; curve in ICVS: S514. Set row 14 = ESTR. Settings for EUR: Currency = EUR sets YTM compounding 1 (annual coupons) and accrual 1 (vs Euribor) or 365.25/360 (€STR).
... B19: ☐ Same date for swap and bond data ☐ Z-spreads measured against the swap curve you entered ☐ Bonds: same issuer, seniority, currency as the loan ☐ Mid quotes throughout ☐ Results → Integrity checks = OK ☐ Results → Warnings reviewed (maturity beyond last bond point?)

Sheet Curves
A1: Curve preparation: gap-filling, YTM conversion, swap bootstrap, semi-annual risk-free grid
A2: Calculation sheet — no inputs here.
A4: Year k | B4: Z raw (bp) | C4: prev idx | D4: next idx | E4: Z filled (bp) | F4: Z status | G4: YTM raw | H4: prev idx | I4: next idx | J4: YTM filled (quoted basis) | K4: YTM s.a.-equivalent | L4: YTM status | M4: Swap raw | N4: prev idx | O4: next idx | P4: Swap filled | Q4: Annual DF | R4: Σ DF (annuity) | S4: Swap status | U4: i | V4: t (y) | W4: DF(t) | X4: f·a = DF(i−1)/DF(i) − 1 | Y4: Σ DF (s.a.) | Z4: Risk-free par yield s.a. (bullet to t)
A5: 1 | B5: =IF(Inputs!C28="","",Inputs!C28) -> -19 | C5: =IF(B5<>"",A5,0) -> 1 | D5: =IF(B5<>"",A5,D6) -> 1 | E5: =IF(B5<>"",B5,IF(AND(C5>0,D5>0),INDEX($B$5:$B$34,C5)+(INDEX($B$5:$B$34,D5)-INDEX($B$5:$B$34,C5))*(A5-C5)/(D5-C5),IF(C5>0,INDEX($B$5:$B$34,C5),IF(D5>0,INDEX($B$5:$B$34,D5),NA())))) -> -19 | F5: =IF(B5<>"","quoted",IF(AND(C5>0,D5>0),"interpolated","flat extrapolation")) -> quoted | G5: =IF(Inputs!D28="","",Inputs!D28) -> 0.03032 | H5: =IF(G5<>"",A5,0) -> 1 | I5: =IF(G5<>"",A5,I6) -> 1 | J5: =IF(G5<>"",G5,IF(AND(H5>0,I5>0),INDEX($G$5:$G$34,H5)+(INDEX($G$5:$G$34,I5)-INDEX($G$5:$G$34,H5))*(A5-H5)/(I5-H5),IF(H5>0,INDEX($G$5:$G$34,H5),IF(I5>0,INDEX($G$5:$G$34,I5),NA())))) -> 0.03032 | K5: =2*((1+J5/Inputs!$C$18)^(Inputs!$C$18/2)-1) -> 0.030093594 | L5: =IF(G5<>"","quoted",IF(AND(H5>0,I5>0),"interpolated","flat extrapolation")) -> quoted | M5: =IF(Inputs!E28="","",Inputs!E28) -> 0.0327 | N5: =IF(M5<>"",A5,0) -> 1 | O5: =IF(M5<>"",A5,O6) -> 1 | P5: =IF(M5<>"",M5,IF(AND(N5>0,O5>0),INDEX($M$5:$M$34,N5)+(INDEX($M$5:$M$34,O5)-INDEX($M$5:$M$34,N5))*(A5-N5)/(O5-N5),IF(N5>0,INDEX($M$5:$M$34,N5),IF(O5>0,INDEX($M$5:$M$34,O5),NA())))) -> 0.0327 | Q5: =1/(1+P5*Inputs!$C$16) -> 0.96833543 | R5: =Q5 -> 0.96833543 | S5: =IF(M5<>"","quoted",IF(AND(N5>0,O5>0),"interpolated","flat extrapolation")) -> quoted | U5: 0 | V5: =U5/2 -> 0 | W5: 1 | Y5: 0
A6: 2 | B6: =IF(Inputs!C29="","",Inputs!C29) -> -15 | C6: =IF(B6<>"",A6,C5) -> 2 | D6: =IF(B6<>"",A6,D7) -> 2 | E6: =IF(B6<>"",B6,IF(AND(C6>0,D6>0),INDEX($B$5:$B$34,C6)+(INDEX($B$5:$B$34,D6)-INDEX($B$5:$B$34,C6))*(A6-C6)/(D6-C6),IF(C6>0,INDEX($B$5:$B$34,C6),IF(D6>0,INDEX($B$5:$B$34,D6),NA())))) -> -15 | F6: =IF(B6<>"","quoted",IF(AND(C6>0,D6>0),"interpolated","flat extrapolation")) -> quoted | G6: =IF(Inputs!D29="","",Inputs!D29) -> 0.03242 | H6: =IF(G6<>"",A6,H5) -> 2 | I6: =IF(G6<>"",A6,I7) -> 2 | J6: =IF(G6<>"",G6,IF(AND(H6>0,I6>0),INDEX($G$5:$G$34,H6)+(INDEX($G$5:$G$34,I6)-INDEX($G$5:$G$34,H6))*(A6-H6)/(I6-H6),IF(H6>0,INDEX($G$5:$G$34,H6),IF(I6>0,INDEX($G$5:$G$34,I6),NA())))) -> 0.03242 | K6: =2*((1+J6/Inputs!$C$18)^(Inputs!$C$18/2)-1) -> 0.032161411 | L6: =IF(G6<>"","quoted",IF(AND(H6>0,I6>0),"interpolated","flat extrapolation")) -> quoted | M6: =IF(Inputs!E29="","",Inputs!E29) -> 0.0342 | N6: =IF(M6<>"",A6,N5) -> 2 | O6: =IF(M6<>"",A6,O7) -> 2 | P6: =IF(M6<>"",M6,IF(AND(N6>0,O6>0),INDEX($M$5:$M$34,N6)+(INDEX($M$5:$M$34,O6)-INDEX($M$5:$M$34,N6))*(A6-N6)/(O6-N6),IF(N6>0,INDEX($M$5:$M$34,N6),IF(O6>0,INDEX($M$5:$M$34,O6),NA())))) -> 0.0342 | Q6: =(1-P6*Inputs!$C$16*R5)/(1+P6*Inputs!$C$16) -> 0.93490904 | R6: =R5+Q6 -> 1.9032445 | S6: =IF(M6<>"","quoted",IF(AND(N6>0,O6>0),"interpolated","flat extrapolation")) -> quoted | U6: 1 | V6: =U6/2 -> 0.5 | W6: =IF(Inputs!$C$19<>"",1/(1+Inputs!$C$19*182.5/360),SQRT(1*INDEX($Q$5:$Q$34,1))) -> 0.98492605 | X6: =W5/W6-1 -> 0.015304653 | Y6: =Y5+W6 -> 0.98492605 | Z6: =(1-W6)/(0.5*Y6) -> 0.030609306
A7: 3 | B7: =IF(Inputs!C30="","",Inputs!C30) -> -14 | C7: =IF(B7<>"",A7,C6) -> 3 | D7: =IF(B7<>"",A7,D8) -> 3 | E7: =IF(B7<>"",B7,IF(AND(C7>0,D7>0),INDEX($B$5:$B$34,C7)+(INDEX($B$5:$B$34,D7)-INDEX($B$5:$B$34,C7))*(A7-C7)/(D7-C7),IF(C7>0,INDEX($B$5:$B$34,C7),IF(D7>0,INDEX($B$5:$B$34,D7),NA())))) -> -14 | F7: =IF(B7<>"","quoted",IF(AND(C7>0,D7>0),"interpolated","flat extrapolation")) -> quoted | G7: =IF(Inputs!D30="","",Inputs!D30) -> 0.03349 | H7: =IF(G7<>"",A7,H6) -> 3 | I7: =IF(G7<>"",A7,I8) -> 3 | J7: =IF(G7<>"",G7,IF(AND(H7>0,I7>0),INDEX($G$5:$G$34,H7)+(INDEX($G$5:$G$34,I7)-INDEX($G$5:$G$34,H7))*(A7-H7)/(I7-H7),IF(H7>0,INDEX($G$5:$G$34,H7),IF(I7>0,INDEX($G$5:$G$34,I7),NA())))) -> 0.03349 | K7: =2*((1+J7/Inputs!$C$18)^(Inputs!$C$18/2)-1) -> 0.033214204 | L7: =IF(G7<>"","quoted",IF(AND(H7>0,I7>0),"interpolated","flat extrapolation")) -> quoted | M7: =IF(Inputs!E30="","",Inputs!E30) -> 0.0345 | N7: =IF(M7<>"",A7,N6) -> 3 | O7: =IF(M7<>"",A7,O8) -> 3 | P7: =IF(M7<>"",M7,IF(AND(N7>0,O7>0),INDEX($M$5:$M$34,N7)+(INDEX($M$5:$M$34,O7)-INDEX($M$5:$M$34,N7))*(A7-N7)/(O7-N7),IF(N7>0,INDEX($M$5:$M$34,N7),IF(O7>0,INDEX($M$5:$M$34,O7),NA())))) -> 0.0345 | Q7: =(1-P7*Inputs!$C$16*R6)/(1+P7*Inputs!$C$16) -> 0.90317841 | R7: =R6+Q7 -> 2.8064229 | S7: =IF(M7<>"","quoted",IF(AND(N7>0,O7>0),"interpolated","flat extrapolation")) -> quoted | U7: 2 | V7: =U7/2 -> 1 | W7: =INDEX($Q$5:$Q$34,1) -> 0.96833543 | X7: =W6/W7-1 -> 0.017133131 | Y7: =Y6+W7 -> 1.9532615 | Z7: =(1-W7)/(0.5*Y7) -> 0.032422253
A8: 4 | B8: =IF(Inputs!C31="","",Inputs!C31) -> -2 | C8: =IF(B8<>"",A8,C7) -> 4 | D8: =IF(B8<>"",A8,D9) -> 4 | E8: =IF(B8<>"",B8,IF(AND(C8>0,D8>0),INDEX($B$5:$B$34,C8)+(INDEX($B$5:$B$34,D8)-INDEX($B$5:$B$34,C8))*(A8-C8)/(D8-C8),IF(C8>0,INDEX($B$5:$B$34,C8),IF(D8>0,INDEX($B$5:$B$34,D8),NA())))) -> -2 | F8: =IF(B8<>"","quoted",IF(AND(C8>0,D8>0),"interpolated","flat extrapolation")) -> quoted | G8: =IF(Inputs!D31="","",Inputs!D31) -> 0.03431 | H8: =IF(G8<>"",A8,H7) -> 4 | I8: =IF(G8<>"",A8,I9) -> 4 | J8: =IF(G8<>"",G8,IF(AND(H8>0,I8>0),INDEX($G$5:$G$34,H8)+(INDEX($G$5:$G$34,I8)-INDEX($G$5:$G$34,H8))*(A8-H8)/(I8-H8),IF(H8>0,INDEX($G$5:$G$34,H8),IF(I8>0,INDEX($G$5:$G$34,I8),NA())))) -> 0.03431 | K8: =2*((1+J8/Inputs!$C$18)^(Inputs!$C$18/2)-1) -> 0.034020649 | L8: =IF(G8<>"","quoted",IF(AND(H8>0,I8>0),"interpolated","flat extrapolation")) -> quoted | M8: =IF(Inputs!E31="","",Inputs!E31) -> 0.0344 | N8: =IF(M8<>"",A8,N7) -> 4 | O8: =IF(M8<>"",A8,O9) -> 4 | P8: =IF(M8<>"",M8,IF(AND(N8>0,O8>0),INDEX($M$5:$M$34,N8)+(INDEX($M$5:$M$34,O8)-INDEX($M$5:$M$34,N8))*(A8-N8)/(O8-N8),IF(N8>0,INDEX($M$5:$M$34,N8),IF(O8>0,INDEX($M$5:$M$34,O8),NA())))) -> 0.0344 | Q8: =(1-P8*Inputs!$C$16*R7)/(1+P8*Inputs!$C$16) -> 0.87341362 | R8: =R7+Q8 -> 3.6798365 | S8: =IF(M8<>"","quoted",IF(AND(N8>0,O8>0),"interpolated","flat extrapolation")) -> quoted | U8: 3 | V8: =U8/2 -> 1.5 | W8: =SQRT(INDEX($Q$5:$Q$34,1)*INDEX($Q$5:$Q$34,2)) -> 0.95147546 | X8: =W7/W8-1 -> 0.017719819 | Y8: =Y7+W8 -> 2.9047369 | Z8: =(1-W8)/(0.5*Y8) -> 0.033410627
A9: 5 | B9: =IF(Inputs!C32="","",Inputs!C32) -> 6 | C9: =IF(B9<>"",A9,C8) -> 5 | D9: =IF(B9<>"",A9,D10) -> 5 | E9: =IF(B9<>"",B9,IF(AND(C9>0,D9>0),INDEX($B$5:$B$34,C9)+(INDEX($B$5:$B$34,D9)-INDEX($B$5:$B$34,C9))*(A9-C9)/(D9-C9),IF(C9>0,INDEX($B$5:$B$34,C9),IF(D9>0,INDEX($B$5:$B$34,D9),NA())))) -> 6 | F9: =IF(B9<>"","quoted",IF(AND(C9>0,D9>0),"interpolated","flat extrapolation")) -> quoted | G9: =IF(Inputs!D32="","",Inputs!D32) -> 0.03522 | H9: =IF(G9<>"",A9,H8) -> 5 | I9: =IF(G9<>"",A9,I10) -> 5 | J9: =IF(G9<>"",G9,IF(AND(H9>0,I9>0),INDEX($G$5:$G$34,H9)+(INDEX($G$5:$G$34,I9)-INDEX($G$5:$G$34,H9))*(A9-H9)/(I9-H9),IF(H9>0,INDEX($G$5:$G$34,H9),IF(I9>0,INDEX($G$5:$G$34,I9),NA())))) -> 0.03522 | K9: =2*((1+J9/Inputs!$C$18)^(Inputs!$C$18/2)-1) -> 0.034915232 | L9: =IF(G9<>"","quoted",IF(AND(H9>0,I9>0),"interpolated","flat extrapolation")) -> quoted | M9: =IF(Inputs!E32="","",Inputs!E32) -> 0.0344 | N9: =IF(M9<>"",A9,N8) -> 5 | O9: =IF(M9<>"",A9,O10) -> 5 | P9: =IF(M9<>"",M9,IF(AND(N9>0,O9>0),INDEX($M$5:$M$34,N9)+(INDEX($M$5:$M$34,O9)-INDEX($M$5:$M$34,N9))*(A9-N9)/(O9-N9),IF(N9>0,INDEX($M$5:$M$34,N9),IF(O9>0,INDEX($M$5:$M$34,O9),NA())))) -> 0.0344 | Q9: =(1-P9*Inputs!$C$16*R8)/(1+P9*Inputs!$C$16) -> 0.84436739 | R9: =R8+Q9 -> 4.5242039 | S9: =IF(M9<>"","quoted",IF(AND(N9>0,O9>0),"interpolated","flat extrapolation")) -> quoted | U9: 4 | V9: =U9/2 -> 2 | W9: =INDEX($Q$5:$Q$34,2) -> 0.93490904 | X9: =W8/W9-1 -> 0.017719819 | Y9: =Y8+W9 -> 3.839646 | Z9: =(1-W9)/(0.5*Y9) -> 0.033904668
A10: 6 | B10: =IF(Inputs!C33="","",Inputs!C33) -> 13 | C10: =IF(B10<>"",A10,C9) -> 6 | D10: =IF(B10<>"",A10,D11) -> 6 | E10: =IF(B10<>"",B10,IF(AND(C10>0,D10>0),INDEX($B$5:$B$34,C10)+(INDEX($B$5:$B$34,D10)-INDEX($B$5:$B$34,C10))*(A10-C10)/(D10-C10),IF(C10>0,INDEX($B$5:$B$34,C10),IF(D10>0,INDEX($B$5:$B$34,D10),NA())))) -> 13 | F10: =IF(B10<>"","quoted",IF(AND(C10>0,D10>0),"interpolated","flat extrapolation")) -> quoted | G10: =IF(Inputs!D33="","",Inputs!D33) -> 0.03597 | H10: =IF(G10<>"",A10,H9) -> 6 | I10: =IF(G10<>"",A10,I11) -> 6 | J10: =IF(G10<>"",G10,IF(AND(H10>0,I10>0),INDEX($G$5:$G$34,H10)+(INDEX($G$5:$G$34,I10)-INDEX($G$5:$G$34,H10))*(A10-H10)/(I10-H10),IF(H10>0,INDEX($G$5:$G$34,H10),IF(I10>0,INDEX($G$5:$G$34,I10),NA())))) -> 0.03597 | K10: =2*((1+J10/Inputs!$C$18)^(Inputs!$C$18/2)-1) -> 0.03565223 | L10: =IF(G10<>"","quoted",IF(AND(H10>0,I10>0),"interpolated","flat extrapolation")) -> quoted | M10: =IF(Inputs!E33="","",Inputs!E33) -> 0.0344 | N10: =IF(M10<>"",A10,N9) -> 6 | O10: =IF(M10<>"",A10,O11) -> 6 | P10: =IF(M10<>"",M10,IF(AND(N10>0,O10>0),INDEX($M$5:$M$34,N10)+(INDEX($M$5:$M$34,O10)-INDEX($M$5:$M$34,N10))*(A10-N10)/(O10-N10),IF(N10>0,INDEX($M$5:$M$34,N10),IF(O10>0,INDEX($M$5:$M$34,O10),NA())))) -> 0.0344 | Q10: =(1-P10*Inputs!$C$16*R9)/(1+P10*Inputs!$C$16) -> 0.81628711 | R10: =R9+Q10 -> 5.340491 | S10: =IF(M10<>"","quoted",IF(AND(N10>0,O10>0),"interpolated","flat extrapolation")) -> quoted | U10: 5 | V10: =U10/2 -> 2.5 | W10: =SQRT(INDEX($Q$5:$Q$34,2)*INDEX($Q$5:$Q$34,3)) -> 0.91890677 | X10: =W9/W10-1 -> 0.017414459 | Y10: =Y9+W10 -> 4.7585528 | Z10: =(1-W10)/(0.5*Y10) -> 0.034083147
A11: 7 | B11: =IF(Inputs!C34="","",Inputs!C34) -> 24 | C11: =IF(B11<>"",A11,C10) -> 7 | D11: =IF(B11<>"",A11,D12) -> 7 | E11: =IF(B11<>"",B11,IF(AND(C11>0,D11>0),INDEX($B$5:$B$34,C11)+(INDEX($B$5:$B$34,D11)-INDEX($B$5:$B$34,C11))*(A11-C11)/(D11-C11),IF(C11>0,INDEX($B$5:$B$34,C11),IF(D11>0,INDEX($B$5:$B$34,D11),NA())))) -> 24 | F11: =IF(B11<>"","quoted",IF(AND(C11>0,D11>0),"interpolated","flat extrapolation")) -> quoted | G11: =IF(Inputs!D34="","",Inputs!D34) -> 0.03726 | H11: =IF(G11<>"",A11,H10) -> 7 | I11: =IF(G11<>"",A11,I12) -> 7 | J11: =IF(G11<>"",G11,IF(AND(H11>0,I11>0),INDEX($G$5:$G$34,H11)+(INDEX($G$5:$G$34,I11)-INDEX($G$5:$G$34,H11))*(A11-H11)/(I11-H11),IF(H11>0,INDEX($G$5:$G$34,H11),IF(I11>0,INDEX($G$5:$G$34,I11),NA())))) -> 0.03726 | K11: =2*((1+J11/Inputs!$C$18)^(Inputs!$C$18/2)-1) -> 0.036919242 | L11: =IF(G11<>"","quoted",IF(AND(H11>0,I11>0),"interpolated","flat extrapolation")) -> quoted | M11: =IF(Inputs!E34="","",Inputs!E34) -> 0.0344 | N11: =IF(M11<>"",A11,N10) -> 7 | O11: =IF(M11<>"",A11,O12) -> 7 | P11: =IF(M11<>"",M11,IF(AND(N11>0,O11>0),INDEX($M$5:$M$34,N11)+(INDEX($M$5:$M$34,O11)-INDEX($M$5:$M$34,N11))*(A11-N11)/(O11-N11),IF(N11>0,INDEX($M$5:$M$34,N11),IF(O11>0,INDEX($M$5:$M$34,O11),NA())))) -> 0.0344 | Q11: =(1-P11*Inputs!$C$16*R10)/(1+P11*Inputs!$C$16) -> 0.78914067 | R11: =R10+Q11 -> 6.1296317 | S11: =IF(M11<>"","quoted",IF(AND(N11>0,O11>0),"interpolated","flat extrapolation")) -> quoted | U11: 6 | V11: =U11/2 -> 3 | W11: =INDEX($Q$5:$Q$34,3) -> 0.90317841 | X11: =W10/W11-1 -> 0.017414459 | Y11: =Y10+W11 -> 5.6617312 | Z11: =(1-W11)/(0.5*Y11) -> 0.034202115
A12: 8 | B12: =IF(Inputs!C35="","",Inputs!C35) -> 30 | C12: =IF(B12<>"",A12,C11) -> 8 | D12: =IF(B12<>"",A12,D13) -> 8 | E12: =IF(B12<>"",B12,IF(AND(C12>0,D12>0),INDEX($B$5:$B$34,C12)+(INDEX($B$5:$B$34,D12)-INDEX($B$5:$B$34,C12))*(A12-C12)/(D12-C12),IF(C12>0,INDEX($B$5:$B$34,C12),IF(D12>0,INDEX($B$5:$B$34,D12),NA())))) -> 30 | F12: =IF(B12<>"","quoted",IF(AND(C12>0,D12>0),"interpolated","flat extrapolation")) -> quoted | G12: =IF(Inputs!D35="","",Inputs!D35) -> 0.03804 | H12: =IF(G12<>"",A12,H11) -> 8 | I12: =IF(G12<>"",A12,I13) -> 8 | J12: =IF(G12<>"",G12,IF(AND(H12>0,I12>0),INDEX($G$5:$G$34,H12)+(INDEX($G$5:$G$34,I12)-INDEX($G$5:$G$34,H12))*(A12-H12)/(I12-H12),IF(H12>0,INDEX($G$5:$G$34,H12),IF(I12>0,INDEX($G$5:$G$34,I12),NA())))) -> 0.03804 | K12: =2*((1+J12/Inputs!$C$18)^(Inputs!$C$18/2)-1) -> 0.037684961 | L12: =IF(G12<>"","quoted",IF(AND(H12>0,I12>0),"interpolated","flat extrapolation")) -> quoted | M12: =IF(Inputs!E35="","",Inputs!E35) -> 0.0345 | N12: =IF(M12<>"",A12,N11) -> 8 | O12: =IF(M12<>"",A12,O13) -> 8 | P12: =IF(M12<>"",M12,IF(AND(N12>0,O12>0),INDEX($M$5:$M$34,N12)+(INDEX($M$5:$M$34,O12)-INDEX($M$5:$M$34,N12))*(A12-N12)/(O12-N12),IF(N12>0,INDEX($M$5:$M$34,N12),IF(O12>0,INDEX($M$5:$M$34,O12),NA())))) -> 0.0345 | Q12: =(1-P12*Inputs!$C$16*R11)/(1+P12*Inputs!$C$16) -> 0.76223075 | R12: =R11+Q12 -> 6.8918624 | S12: =IF(M12<>"","quoted",IF(AND(N12>0,O12>0),"interpolated","flat extrapolation")) -> quoted | U12: 7 | V12: =U12/2 -> 3.5 | W12: =SQRT(INDEX($Q$5:$Q$34,3)*INDEX($Q$5:$Q$34,4)) -> 0.88817134 | X12: =W11/W12-1 -> 0.016896594 | Y12: =Y11+W12 -> 6.5499025 | Z12: =(1-W12)/(0.5*Y12) -> 0.034146664
A13: 9 | B13: =IF(Inputs!C36="","",Inputs!C36) -> 37 | C13: =IF(B13<>"",A13,C12) -> 9 | D13: =IF(B13<>"",A13,D14) -> 9 | E13: =IF(B13<>"",B13,IF(AND(C13>0,D13>0),INDEX($B$5:$B$34,C13)+(INDEX($B$5:$B$34,D13)-INDEX($B$5:$B$34,C13))*(A13-C13)/(D13-C13),IF(C13>0,INDEX($B$5:$B$34,C13),IF(D13>0,INDEX($B$5:$B$34,D13),NA())))) -> 37 | F13: =IF(B13<>"","quoted",IF(AND(C13>0,D13>0),"interpolated","flat extrapolation")) -> quoted | G13: =IF(Inputs!D36="","",Inputs!D36) -> 0.03888 | H13: =IF(G13<>"",A13,H12) -> 9 | I13: =IF(G13<>"",A13,I14) -> 9 | J13: =IF(G13<>"",G13,IF(AND(H13>0,I13>0),INDEX($G$5:$G$34,H13)+(INDEX($G$5:$G$34,I13)-INDEX($G$5:$G$34,H13))*(A13-H13)/(I13-H13),IF(H13>0,INDEX($G$5:$G$34,H13),IF(I13>0,INDEX($G$5:$G$34,I13),NA())))) -> 0.03888 | K13: =2*((1+J13/Inputs!$C$18)^(Inputs!$C$18/2)-1) -> 0.038509259 | L13: =IF(G13<>"","quoted",IF(AND(H13>0,I13>0),"interpolated","flat extrapolation")) -> quoted | M13: =IF(Inputs!E36="","",Inputs!E36) | N13: =IF(M13<>"",A13,N12) -> 8 | O13: =IF(M13<>"",A13,O14) -> 10 | P13: =IF(M13<>"",M13,IF(AND(N13>0,O13>0),INDEX($M$5:$M$34,N13)+(INDEX($M$5:$M$34,O13)-INDEX($M$5:$M$34,N13))*(A13-N13)/(O13-N13),IF(N13>0,INDEX($M$5:$M$34,N13),IF(O13>0,INDEX($M$5:$M$34,O13),NA())))) -> 0.0346 | Q13: =(1-P13*Inputs!$C$16*R12)/(1+P13*Inputs!$C$16) -> 0.73607342 | R13: =R12+Q13 -> 7.6279358 | S13: =IF(M13<>"","quoted",IF(AND(N13>0,O13>0),"interpolated","flat extrapolation")) -> interpolated | U13: 8 | V13: =U13/2 -> 4 | W13: =INDEX($Q$5:$Q$34,4) -> 0.87341362 | X13: =W12/W13-1 -> 0.016896594 | Y13: =Y12+W13 -> 7.4233161 | Z13: =(1-W13)/(0.5*Y13) -> 0.034105075
A14: 10 | B14: =IF(Inputs!C37="","",Inputs!C37) -> 42 | C14: =IF(B14<>"",A14,C13) -> 10 | D14: =IF(B14<>"",A14,D15) -> 10 | E14: =IF(B14<>"",B14,IF(AND(C14>0,D14>0),INDEX($B$5:$B$34,C14)+(INDEX($B$5:$B$34,D14)-INDEX($B$5:$B$34,C14))*(A14-C14)/(D14-C14),IF(C14>0,INDEX($B$5:$B$34,C14),IF(D14>0,INDEX($B$5:$B$34,D14),NA())))) -> 42 | F14: =IF(B14<>"","quoted",IF(AND(C14>0,D14>0),"interpolated","flat extrapolation")) -> quoted | G14: =IF(Inputs!D37="","",Inputs!D37) -> 0.03942 | H14: =IF(G14<>"",A14,H13) -> 10 | I14: =IF(G14<>"",A14,I15) -> 10 | J14: =IF(G14<>"",G14,IF(AND(H14>0,I14>0),INDEX($G$5:$G$34,H14)+(INDEX($G$5:$G$34,I14)-INDEX($G$5:$G$34,H14))*(A14-H14)/(I14-H14),IF(H14>0,INDEX($G$5:$G$34,H14),IF(I14>0,INDEX($G$5:$G$34,I14),NA())))) -> 0.03942 | K14: =2*((1+J14/Inputs!$C$18)^(Inputs!$C$18/2)-1) -> 0.039038989 | L14: =IF(G14<>"","quoted",IF(AND(H14>0,I14>0),"interpolated","flat extrapolation")) -> quoted | M14: =IF(Inputs!E37="","",Inputs!E37) -> 0.0347 | N14: =IF(M14<>"",A14,N13) -> 10 | O14: =IF(M14<>"",A14,O15) -> 10 | P14: =IF(M14<>"",M14,IF(AND(N14>0,O14>0),INDEX($M$5:$M$34,N14)+(INDEX($M$5:$M$34,O14)-INDEX($M$5:$M$34,N14))*(A14-N14)/(O14-N14),IF(N14>0,INDEX($M$5:$M$34,N14),IF(O14>0,INDEX($M$5:$M$34,O14),NA())))) -> 0.0347 | Q14: =(1-P14*Inputs!$C$16*R13)/(1+P14*Inputs!$C$16) -> 0.71065104 | R14: =R13+Q14 -> 8.3385869 | S14: =IF(M14<>"","quoted",IF(AND(N14>0,O14>0),"interpolated","flat extrapolation")) -> quoted | U14: 9 | V14: =U14/2 -> 4.5 | W14: =SQRT(INDEX($Q$5:$Q$34,4)*INDEX($Q$5:$Q$34,5)) -> 0.85876771 | X14: =W13/W14-1 -> 0.017054571 | Y14: =Y13+W14 -> 8.2820838 | Z14: =(1-W14)/(0.5*Y14) -> 0.034105496
A15: 11 | B15: =IF(Inputs!C38="","",Inputs!C38) -> 46 | C15: =IF(B15<>"",A15,C14) -> 11 | D15: =IF(B15<>"",A15,D16) -> 11 | E15: =IF(B15<>"",B15,IF(AND(C15>0,D15>0),INDEX($B$5:$B$34,C15)+(INDEX($B$5:$B$34,D15)-INDEX($B$5:$B$34,C15))*(A15-C15)/(D15-C15),IF(C15>0,INDEX($B$5:$B$34,C15),IF(D15>0,INDEX($B$5:$B$34,D15),NA())))) -> 46 | F15: =IF(B15<>"","quoted",IF(AND(C15>0,D15>0),"interpolated","flat extrapolation")) -> quoted | G15: =IF(Inputs!D38="","",Inputs!D38) -> 0.03995 | H15: =IF(G15<>"",A15,H14) -> 11 | I15: =IF(G15<>"",A15,I16) -> 11 | J15: =IF(G15<>"",G15,IF(AND(H15>0,I15>0),INDEX($G$5:$G$34,H15)+(INDEX($G$5:$G$34,I15)-INDEX($G$5:$G$34,H15))*(A15-H15)/(I15-H15),IF(H15>0,INDEX($G$5:$G$34,H15),IF(I15>0,INDEX($G$5:$G$34,I15),NA())))) -> 0.03995 | K15: =2*((1+J15/Inputs!$C$18)^(Inputs!$C$18/2)-1) -> 0.039558776 | L15: =IF(G15<>"","quoted",IF(AND(H15>0,I15>0),"interpolated","flat extrapolation")) -> quoted | M15: =IF(Inputs!E38="","",Inputs!E38) | N15: =IF(M15<>"",A15,N14) -> 10 | O15: =IF(M15<>"",A15,O16) -> 15 | P15: =IF(M15<>"",M15,IF(AND(N15>0,O15>0),INDEX($M$5:$M$34,N15)+(INDEX($M$5:$M$34,O15)-INDEX($M$5:$M$34,N15))*(A15-N15)/(O15-N15),IF(N15>0,INDEX($M$5:$M$34,N15),IF(O15>0,INDEX($M$5:$M$34,O15),NA())))) -> 0.03478 | Q15: =(1-P15*Inputs!$C$16*R14)/(1+P15*Inputs!$C$16) -> 0.68612067 | R15: =R14+Q15 -> 9.0247075 | S15: =IF(M15<>"","quoted",IF(AND(N15>0,O15>0),"interpolated","flat extrapolation")) -> interpolated | U15: 10 | V15: =U15/2 -> 5 | W15: =INDEX($Q$5:$Q$34,5) -> 0.84436739 | X15: =W14/W15-1 -> 0.017054571 | Y15: =Y14+W15 -> 9.1264512 | Z15: =(1-W15)/(0.5*Y15) -> 0.034105834
A16: 12 | B16: =IF(Inputs!C39="","",Inputs!C39) | C16: =IF(B16<>"",A16,C15) -> 11 | D16: =IF(B16<>"",A16,D17) -> 14 | E16: =IF(B16<>"",B16,IF(AND(C16>0,D16>0),INDEX($B$5:$B$34,C16)+(INDEX($B$5:$B$34,D16)-INDEX($B$5:$B$34,C16))*(A16-C16)/(D16-C16),IF(C16>0,INDEX($B$5:$B$34,C16),IF(D16>0,INDEX($B$5:$B$34,D16),NA())))) -> 51 | F16: =IF(B16<>"","quoted",IF(AND(C16>0,D16>0),"interpolated","flat extrapolation")) -> interpolated | G16: =IF(Inputs!D39="","",Inputs!D39) | H16: =IF(G16<>"",A16,H15) -> 11 | I16: =IF(G16<>"",A16,I17) -> 14 | J16: =IF(G16<>"",G16,IF(AND(H16>0,I16>0),INDEX($G$5:$G$34,H16)+(INDEX($G$5:$G$34,I16)-INDEX($G$5:$G$34,H16))*(A16-H16)/(I16-H16),IF(H16>0,INDEX($G$5:$G$34,H16),IF(I16>0,INDEX($G$5:$G$34,I16),NA())))) -> 0.040626667 | K16: =2*((1+J16/Inputs!$C$18)^(Inputs!$C$18/2)-1) -> 0.04022221 | L16: =IF(G16<>"","quoted",IF(AND(H16>0,I16>0),"interpolated","flat extrapolation")) -> interpolated | M16: =IF(Inputs!E39="","",Inputs!E39) | N16: =IF(M16<>"",A16,N15) -> 10 | O16: =IF(M16<>"",A16,O17) -> 15 | P16: =IF(M16<>"",M16,IF(AND(N16>0,O16>0),INDEX($M$5:$M$34,N16)+(INDEX($M$5:$M$34,O16)-INDEX($M$5:$M$34,N16))*(A16-N16)/(O16-N16),IF(N16>0,INDEX($M$5:$M$34,N16),IF(O16>0,INDEX($M$5:$M$34,O16),NA())))) -> 0.03486 | Q16: =(1-P16*Inputs!$C$16*R15)/(1+P16*Inputs!$C$16) -> 0.66231055 | R16: =R15+Q16 -> 9.6870181 | S16: =IF(M16<>"","quoted",IF(AND(N16>0,O16>0),"interpolated","flat extrapolation")) -> interpolated | U16: 11 | V16: =U16/2 -> 5.5 | W16: =SQRT(INDEX($Q$5:$Q$34,5)*INDEX($Q$5:$Q$34,6)) -> 0.83020854 | X16: =W15/W16-1 -> 0.017054571 | Y16: =Y15+W16 -> 9.9566598 | Z16: =(1-W16)/(0.5*Y16) -> 0.03410611
A17: 13 | B17: =IF(Inputs!C40="","",Inputs!C40) | C17: =IF(B17<>"",A17,C16) -> 11 | D17: =IF(B17<>"",A17,D18) -> 14 | E17: =IF(B17<>"",B17,IF(AND(C17>0,D17>0),INDEX($B$5:$B$34,C17)+(INDEX($B$5:$B$34,D17)-INDEX($B$5:$B$34,C17))*(A17-C17)/(D17-C17),IF(C17>0,INDEX($B$5:$B$34,C17),IF(D17>0,INDEX($B$5:$B$34,D17),NA())))) -> 56 | F17: =IF(B17<>"","quoted",IF(AND(C17>0,D17>0),"interpolated","flat extrapolation")) -> interpolated | G17: =IF(Inputs!D40="","",Inputs!D40) | H17: =IF(G17<>"",A17,H16) -> 11 | I17: =IF(G17<>"",A17,I18) -> 14 | J17: =IF(G17<>"",G17,IF(AND(H17>0,I17>0),INDEX($G$5:$G$34,H17)+(INDEX($G$5:$G$34,I17)-INDEX($G$5:$G$34,H17))*(A17-H17)/(I17-H17),IF(H17>0,INDEX($G$5:$G$34,H17),IF(I17>0,INDEX($G$5:$G$34,I17),NA())))) -> 0.041303333 | K17: =2*((1+J17/Inputs!$C$18)^(Inputs!$C$18/2)-1) -> 0.040885429 | L17: =IF(G17<>"","quoted",IF(AND(H17>0,I17>0),"interpolated","flat extrapolation")) -> interpolated | M17: =IF(Inputs!E40="","",Inputs!E40) | N17: =IF(M17<>"",A17,N16) -> 10 | O17: =IF(M17<>"",A17,O18) -> 15 | P17: =IF(M17<>"",M17,IF(AND(N17>0,O17>0),INDEX($M$5:$M$34,N17)+(INDEX($M$5:$M$34,O17)-INDEX($M$5:$M$34,N17))*(A17-N17)/(O17-N17),IF(N17>0,INDEX($M$5:$M$34,N17),IF(O17>0,INDEX($M$5:$M$34,O17),NA())))) -> 0.03494 | Q17: =(1-P17*Inputs!$C$16*R16)/(1+P17*Inputs!$C$16) -> 0.63920187 | R17: =R16+Q17 -> 10.32622 | S17: =IF(M17<>"","quoted",IF(AND(N17>0,O17>0),"interpolated","flat extrapolation")) -> interpolated | U17: 12 | V17: =U17/2 -> 6 | W17: =INDEX($Q$5:$Q$34,6) -> 0.81628711 | X17: =W16/W17-1 -> 0.017054571 | Y17: =Y16+W17 -> 10.772947 | Z17: =(1-W17)/(0.5*Y17) -> 0.034106339
A18: 14 | B18: =IF(Inputs!C41="","",Inputs!C41) -> 61 | C18: =IF(B18<>"",A18,C17) -> 14 | D18: =IF(B18<>"",A18,D19) -> 14 | E18: =IF(B18<>"",B18,IF(AND(C18>0,D18>0),INDEX($B$5:$B$34,C18)+(INDEX($B$5:$B$34,D18)-INDEX($B$5:$B$34,C18))*(A18-C18)/(D18-C18),IF(C18>0,INDEX($B$5:$B$34,C18),IF(D18>0,INDEX($B$5:$B$34,D18),NA())))) -> 61 | F18: =IF(B18<>"","quoted",IF(AND(C18>0,D18>0),"interpolated","flat extrapolation")) -> quoted | G18: =IF(Inputs!D41="","",Inputs!D41) -> 0.04198 | H18: =IF(G18<>"",A18,H17) -> 14 | I18: =IF(G18<>"",A18,I19) -> 14 | J18: =IF(G18<>"",G18,IF(AND(H18>0,I18>0),INDEX($G$5:$G$34,H18)+(INDEX($G$5:$G$34,I18)-INDEX($G$5:$G$34,H18))*(A18-H18)/(I18-H18),IF(H18>0,INDEX($G$5:$G$34,H18),IF(I18>0,INDEX($G$5:$G$34,I18),NA())))) -> 0.04198 | K18: =2*((1+J18/Inputs!$C$18)^(Inputs!$C$18/2)-1) -> 0.041548432 | L18: =IF(G18<>"","quoted",IF(AND(H18>0,I18>0),"interpolated","flat extrapolation")) -> quoted | M18: =IF(Inputs!E41="","",Inputs!E41) | N18: =IF(M18<>"",A18,N17) -> 10 | O18: =IF(M18<>"",A18,O19) -> 15 | P18: =IF(M18<>"",M18,IF(AND(N18>0,O18>0),INDEX($M$5:$M$34,N18)+(INDEX($M$5:$M$34,O18)-INDEX($M$5:$M$34,N18))*(A18-N18)/(O18-N18),IF(N18>0,INDEX($M$5:$M$34,N18),IF(O18>0,INDEX($M$5:$M$34,O18),NA())))) -> 0.03502 | Q18: =(1-P18*Inputs!$C$16*R17)/(1+P18*Inputs!$C$16) -> 0.61677627 | R18: =R17+Q18 -> 10.942996 | S18: =IF(M18<>"","quoted",IF(AND(N18>0,O18>0),"interpolated","flat extrapolation")) -> interpolated | U18: 13 | V18: =U18/2 -> 6.5 | W18: =SQRT(INDEX($Q$5:$Q$34,6)*INDEX($Q$5:$Q$34,7)) -> 0.80259913 | X18: =W17/W18-1 -> 0.017054571 | Y18: =Y17+W18 -> 11.575546 | Z18: =(1-W18)/(0.5*Y18) -> 0.034106534
A19: 15 | B19: =IF(Inputs!C42="","",Inputs!C42) -> 65 | C19: =IF(B19<>"",A19,C18) -> 15 | D19: =IF(B19<>"",A19,D20) -> 15 | E19: =IF(B19<>"",B19,IF(AND(C19>0,D19>0),INDEX($B$5:$B$34,C19)+(INDEX($B$5:$B$34,D19)-INDEX($B$5:$B$34,C19))*(A19-C19)/(D19-C19),IF(C19>0,INDEX($B$5:$B$34,C19),IF(D19>0,INDEX($B$5:$B$34,D19),NA())))) -> 65 | F19: =IF(B19<>"","quoted",IF(AND(C19>0,D19>0),"interpolated","flat extrapolation")) -> quoted | G19: =IF(Inputs!D42="","",Inputs!D42) -> 0.04256 | H19: =IF(G19<>"",A19,H18) -> 15 | I19: =IF(G19<>"",A19,I20) -> 15 | J19: =IF(G19<>"",G19,IF(AND(H19>0,I19>0),INDEX($G$5:$G$34,H19)+(INDEX($G$5:$G$34,I19)-INDEX($G$5:$G$34,H19))*(A19-H19)/(I19-H19),IF(H19>0,INDEX($G$5:$G$34,H19),IF(I19>0,INDEX($G$5:$G$34,I19),NA())))) -> 0.04256 | K19: =2*((1+J19/Inputs!$C$18)^(Inputs!$C$18/2)-1) -> 0.042116549 | L19: =IF(G19<>"","quoted",IF(AND(H19>0,I19>0),"interpolated","flat extrapolation")) -> quoted | M19: =IF(Inputs!E42="","",Inputs!E42) -> 0.0351 | N19: =IF(M19<>"",A19,N18) -> 15 | O19: =IF(M19<>"",A19,O20) -> 15 | P19: =IF(M19<>"",M19,IF(AND(N19>0,O19>0),INDEX($M$5:$M$34,N19)+(INDEX($M$5:$M$34,O19)-INDEX($M$5:$M$34,N19))*(A19-N19)/(O19-N19),IF(N19>0,INDEX($M$5:$M$34,N19),IF(O19>0,INDEX($M$5:$M$34,O19),NA())))) -> 0.0351 | Q19: =(1-P19*Inputs!$C$16*R18)/(1+P19*Inputs!$C$16) -> 0.59501578 | R19: =R18+Q19 -> 11.538012 | S19: =IF(M19<>"","quoted",IF(AND(N19>0,O19>0),"interpolated","flat extrapolation")) -> quoted | U19: 14 | V19: =U19/2 -> 7 | W19: =INDEX($Q$5:$Q$34,7) -> 0.78914067 | X19: =W18/W19-1 -> 0.017054571 | Y19: =Y18+W19 -> 12.364687 | Z19: =(1-W19)/(0.5*Y19) -> 0.0341067
A20: 16 | B20: =IF(Inputs!C43="","",Inputs!C43) | C20: =IF(B20<>"",A20,C19) -> 15 | D20: =IF(B20<>"",A20,D21) -> 18 | E20: =IF(B20<>"",B20,IF(AND(C20>0,D20>0),INDEX($B$5:$B$34,C20)+(INDEX($B$5:$B$34,D20)-INDEX($B$5:$B$34,C20))*(A20-C20)/(D20-C20),IF(C20>0,INDEX($B$5:$B$34,C20),IF(D20>0,INDEX($B$5:$B$34,D20),NA())))) -> 68 | F20: =IF(B20<>"","quoted",IF(AND(C20>0,D20>0),"interpolated","flat extrapolation")) -> interpolated | G20: =IF(Inputs!D43="","",Inputs!D43) | H20: =IF(G20<>"",A20,H19) -> 15 | I20: =IF(G20<>"",A20,I21) -> 18 | J20: =IF(G20<>"",G20,IF(AND(H20>0,I20>0),INDEX($G$5:$G$34,H20)+(INDEX($G$5:$G$34,I20)-INDEX($G$5:$G$34,H20))*(A20-H20)/(I20-H20),IF(H20>0,INDEX($G$5:$G$34,H20),IF(I20>0,INDEX($G$5:$G$34,I20),NA())))) -> 0.042773333 | K20: =2*((1+J20/Inputs!$C$18)^(Inputs!$C$18/2)-1) -> 0.042325472 | L20: =IF(G20<>"","quoted",IF(AND(H20>0,I20>0),"interpolated","flat extrapolation")) -> interpolated | M20: =IF(Inputs!E43="","",Inputs!E43) | N20: =IF(M20<>"",A20,N19) -> 15 | O20: =IF(M20<>"",A20,O21) -> 20 | P20: =IF(M20<>"",M20,IF(AND(N20>0,O20>0),INDEX($M$5:$M$34,N20)+(INDEX($M$5:$M$34,O20)-INDEX($M$5:$M$34,N20))*(A20-N20)/(O20-N20),IF(N20>0,INDEX($M$5:$M$34,N20),IF(O20>0,INDEX($M$5:$M$34,O20),NA())))) -> 0.03502 | Q20: =(1-P20*Inputs!$C$16*R19)/(1+P20*Inputs!$C$16) -> 0.57577517 | R20: =R19+Q20 -> 12.113787 | S20: =IF(M20<>"","quoted",IF(AND(N20>0,O20>0),"interpolated","flat extrapolation")) -> interpolated | U20: 15 | V20: =U20/2 -> 7.5 | W20: =SQRT(INDEX($Q$5:$Q$34,7)*INDEX($Q$5:$Q$34,8)) -> 0.77556901 | X20: =W19/W20-1 -> 0.017498978 | Y20: =Y19+W20 -> 13.140256 | Z20: =(1-W20)/(0.5*Y20) -> 0.034159304
A21: 17 | B21: =IF(Inputs!C44="","",Inputs!C44) | C21: =IF(B21<>"",A21,C20) -> 15 | D21: =IF(B21<>"",A21,D22) -> 18 | E21: =IF(B21<>"",B21,IF(AND(C21>0,D21>0),INDEX($B$5:$B$34,C21)+(INDEX($B$5:$B$34,D21)-INDEX($B$5:$B$34,C21))*(A21-C21)/(D21-C21),IF(C21>0,INDEX($B$5:$B$34,C21),IF(D21>0,INDEX($B$5:$B$34,D21),NA())))) -> 71 | F21: =IF(B21<>"","quoted",IF(AND(C21>0,D21>0),"interpolated","flat extrapolation")) -> interpolated | G21: =IF(Inputs!D44="","",Inputs!D44) | H21: =IF(G21<>"",A21,H20) -> 15 | I21: =IF(G21<>"",A21,I22) -> 18 | J21: =IF(G21<>"",G21,IF(AND(H21>0,I21>0),INDEX($G$5:$G$34,H21)+(INDEX($G$5:$G$34,I21)-INDEX($G$5:$G$34,H21))*(A21-H21)/(I21-H21),IF(H21>0,INDEX($G$5:$G$34,H21),IF(I21>0,INDEX($G$5:$G$34,I21),NA())))) -> 0.042986667 | K21: =2*((1+J21/Inputs!$C$18)^(Inputs!$C$18/2)-1) -> 0.042534373 | L21: =IF(G21<>"","quoted",IF(AND(H21>0,I21>0),"interpolated","flat extrapolation")) -> interpolated | M21: =IF(Inputs!E44="","",Inputs!E44) | N21: =IF(M21<>"",A21,N20) -> 15 | O21: =IF(M21<>"",A21,O22) -> 20 | P21: =IF(M21<>"",M21,IF(AND(N21>0,O21>0),INDEX($M$5:$M$34,N21)+(INDEX($M$5:$M$34,O21)-INDEX($M$5:$M$34,N21))*(A21-N21)/(O21-N21),IF(N21>0,INDEX($M$5:$M$34,N21),IF(O21>0,INDEX($M$5:$M$34,O21),NA())))) -> 0.03494 | Q21: =(1-P21*Inputs!$C$16*R20)/(1+P21*Inputs!$C$16) -> 0.55727315 | R21: =R20+Q21 -> 12.67106 | S21: =IF(M21<>"","quoted",IF(AND(N21>0,O21>0),"interpolated","flat extrapolation")) -> interpolated | U21: 16 | V21: =U21/2 -> 8 | W21: =INDEX($Q$5:$Q$34,8) -> 0.76223075 | X21: =W20/W21-1 -> 0.017498978 | Y21: =Y20+W21 -> 13.902486 | Z21: =(1-W21)/(0.5*Y21) -> 0.034205285
A22: 18 | B22: =IF(Inputs!C45="","",Inputs!C45) -> 74 | C22: =IF(B22<>"",A22,C21) -> 18 | D22: =IF(B22<>"",A22,D23) -> 18 | E22: =IF(B22<>"",B22,IF(AND(C22>0,D22>0),INDEX($B$5:$B$34,C22)+(INDEX($B$5:$B$34,D22)-INDEX($B$5:$B$34,C22))*(A22-C22)/(D22-C22),IF(C22>0,INDEX($B$5:$B$34,C22),IF(D22>0,INDEX($B$5:$B$34,D22),NA())))) -> 74 | F22: =IF(B22<>"","quoted",IF(AND(C22>0,D22>0),"interpolated","flat extrapolation")) -> quoted | G22: =IF(Inputs!D45="","",Inputs!D45) -> 0.0432 | H22: =IF(G22<>"",A22,H21) -> 18 | I22: =IF(G22<>"",A22,I23) -> 18 | J22: =IF(G22<>"",G22,IF(AND(H22>0,I22>0),INDEX($G$5:$G$34,H22)+(INDEX($G$5:$G$34,I22)-INDEX($G$5:$G$34,H22))*(A22-H22)/(I22-H22),IF(H22>0,INDEX($G$5:$G$34,H22),IF(I22>0,INDEX($G$5:$G$34,I22),NA())))) -> 0.0432 | K22: =2*((1+J22/Inputs!$C$18)^(Inputs!$C$18/2)-1) -> 0.042743254 | L22: =IF(G22<>"","quoted",IF(AND(H22>0,I22>0),"interpolated","flat extrapolation")) -> quoted | M22: =IF(Inputs!E45="","",Inputs!E45) | N22: =IF(M22<>"",A22,N21) -> 15 | O22: =IF(M22<>"",A22,O23) -> 20 | P22: =IF(M22<>"",M22,IF(AND(N22>0,O22>0),INDEX($M$5:$M$34,N22)+(INDEX($M$5:$M$34,O22)-INDEX($M$5:$M$34,N22))*(A22-N22)/(O22-N22),IF(N22>0,INDEX($M$5:$M$34,N22),IF(O22>0,INDEX($M$5:$M$34,O22),NA())))) -> 0.03486 | Q22: =(1-P22*Inputs!$C$16*R21)/(1+P22*Inputs!$C$16) -> 0.53948054 | R22: =R21+Q22 -> 13.210541 | S22: =IF(M22<>"","quoted",IF(AND(N22>0,O22>0),"interpolated","flat extrapolation")) -> interpolated | U22: 17 | V22: =U22/2 -> 8.5 | W22: =SQRT(INDEX($Q$5:$Q$34,8)*INDEX($Q$5:$Q$34,9)) -> 0.74903791 | X22: =W21/W22-1 -> 0.017613041 | Y22: =Y21+W22 -> 14.651524 | Z22: =(1-W22)/(0.5*Y22) -> 0.034257472
A23: 19 | B23: =IF(Inputs!C46="","",Inputs!C46) | C23: =IF(B23<>"",A23,C22) -> 18 | D23: =IF(B23<>"",A23,D24) -> 20 | E23: =IF(B23<>"",B23,IF(AND(C23>0,D23>0),INDEX($B$5:$B$34,C23)+(INDEX($B$5:$B$34,D23)-INDEX($B$5:$B$34,C23))*(A23-C23)/(D23-C23),IF(C23>0,INDEX($B$5:$B$34,C23),IF(D23>0,INDEX($B$5:$B$34,D23),NA())))) -> 76 | F23: =IF(B23<>"","quoted",IF(AND(C23>0,D23>0),"interpolated","flat extrapolation")) -> interpolated | G23: =IF(Inputs!D46="","",Inputs!D46) | H23: =IF(G23<>"",A23,H22) -> 18 | I23: =IF(G23<>"",A23,I24) -> 20 | J23: =IF(G23<>"",G23,IF(AND(H23>0,I23>0),INDEX($G$5:$G$34,H23)+(INDEX($G$5:$G$34,I23)-INDEX($G$5:$G$34,H23))*(A23-H23)/(I23-H23),IF(H23>0,INDEX($G$5:$G$34,H23),IF(I23>0,INDEX($G$5:$G$34,I23),NA())))) -> 0.043345 | K23: =2*((1+J23/Inputs!$C$18)^(Inputs!$C$18/2)-1) -> 0.042885215 | L23: =IF(G23<>"","quoted",IF(AND(H23>0,I23>0),"interpolated","flat extrapolation")) -> interpolated | M23: =IF(Inputs!E46="","",Inputs!E46) | N23: =IF(M23<>"",A23,N22) -> 15 | O23: =IF(M23<>"",A23,O24) -> 20 | P23: =IF(M23<>"",M23,IF(AND(N23>0,O23>0),INDEX($M$5:$M$34,N23)+(INDEX($M$5:$M$34,O23)-INDEX($M$5:$M$34,N23))*(A23-N23)/(O23-N23),IF(N23>0,INDEX($M$5:$M$34,N23),IF(O23>0,INDEX($M$5:$M$34,O23),NA())))) -> 0.03478 | Q23: =(1-P23*Inputs!$C$16*R22)/(1+P23*Inputs!$C$16) -> 0.52236938 | R23: =R22+Q23 -> 13.73291 | S23: =IF(M23<>"","quoted",IF(AND(N23>0,O23>0),"interpolated","flat extrapolation")) -> interpolated | U23: 18 | V23: =U23/2 -> 9 | W23: =INDEX($Q$5:$Q$34,9) -> 0.73607342 | X23: =W22/W23-1 -> 0.017613041 | Y23: =Y22+W23 -> 15.387598 | Z23: =(1-W23)/(0.5*Y23) -> 0.034303805
A24: 20 | B24: =IF(Inputs!C47="","",Inputs!C47) -> 78 | C24: =IF(B24<>"",A24,C23) -> 20 | D24: =IF(B24<>"",A24,D25) -> 20 | E24: =IF(B24<>"",B24,IF(AND(C24>0,D24>0),INDEX($B$5:$B$34,C24)+(INDEX($B$5:$B$34,D24)-INDEX($B$5:$B$34,C24))*(A24-C24)/(D24-C24),IF(C24>0,INDEX($B$5:$B$34,C24),IF(D24>0,INDEX($B$5:$B$34,D24),NA())))) -> 78 | F24: =IF(B24<>"","quoted",IF(AND(C24>0,D24>0),"interpolated","flat extrapolation")) -> quoted | G24: =IF(Inputs!D47="","",Inputs!D47) -> 0.04349 | H24: =IF(G24<>"",A24,H23) -> 20 | I24: =IF(G24<>"",A24,I25) -> 20 | J24: =IF(G24<>"",G24,IF(AND(H24>0,I24>0),INDEX($G$5:$G$34,H24)+(INDEX($G$5:$G$34,I24)-INDEX($G$5:$G$34,H24))*(A24-H24)/(I24-H24),IF(H24>0,INDEX($G$5:$G$34,H24),IF(I24>0,INDEX($G$5:$G$34,I24),NA())))) -> 0.04349 | K24: =2*((1+J24/Inputs!$C$18)^(Inputs!$C$18/2)-1) -> 0.043027166 | L24: =IF(G24<>"","quoted",IF(AND(H24>0,I24>0),"interpolated","flat extrapolation")) -> quoted | M24: =IF(Inputs!E47="","",Inputs!E47) -> 0.0347 | N24: =IF(M24<>"",A24,N23) -> 20 | O24: =IF(M24<>"",A24,O25) -> 20 | P24: =IF(M24<>"",M24,IF(AND(N24>0,O24>0),INDEX($M$5:$M$34,N24)+(INDEX($M$5:$M$34,O24)-INDEX($M$5:$M$34,N24))*(A24-N24)/(O24-N24),IF(N24>0,INDEX($M$5:$M$34,N24),IF(O24>0,INDEX($M$5:$M$34,O24),NA())))) -> 0.0347 | Q24: =(1-P24*Inputs!$C$16*R23)/(1+P24*Inputs!$C$16) -> 0.50591284 | R24: =R23+Q24 -> 14.238823 | S24: =IF(M24<>"","quoted",IF(AND(N24>0,O24>0),"interpolated","flat extrapolation")) -> quoted | U24: 19 | V24: =U24/2 -> 9.5 | W24: =SQRT(INDEX($Q$5:$Q$34,9)*INDEX($Q$5:$Q$34,10)) -> 0.72325054 | X24: =W23/W24-1 -> 0.017729519 | Y24: =Y23+W24 -> 16.110848 | Z24: =(1-W24)/(0.5*Y24) -> 0.034355666
A25: 21 | B25: =IF(Inputs!C48="","",Inputs!C48) | C25: =IF(B25<>"",A25,C24) -> 20 | D25: =IF(B25<>"",A25,D26) -> 25 | E25: =IF(B25<>"",B25,IF(AND(C25>0,D25>0),INDEX($B$5:$B$34,C25)+(INDEX($B$5:$B$34,D25)-INDEX($B$5:$B$34,C25))*(A25-C25)/(D25-C25),IF(C25>0,INDEX($B$5:$B$34,C25),IF(D25>0,INDEX($B$5:$B$34,D25),NA())))) -> 80.2 | F25: =IF(B25<>"","quoted",IF(AND(C25>0,D25>0),"interpolated","flat extrapolation")) -> interpolated | G25: =IF(Inputs!D48="","",Inputs!D48) | H25: =IF(G25<>"",A25,H24) -> 20 | I25: =IF(G25<>"",A25,I26) -> 25 | J25: =IF(G25<>"",G25,IF(AND(H25>0,I25>0),INDEX($G$5:$G$34,H25)+(INDEX($G$5:$G$34,I25)-INDEX($G$5:$G$34,H25))*(A25-H25)/(I25-H25),IF(H25>0,INDEX($G$5:$G$34,H25),IF(I25>0,INDEX($G$5:$G$34,I25),NA())))) -> 0.04349 | K25: =2*((1+J25/Inputs!$C$18)^(Inputs!$C$18/2)-1) -> 0.043027166 | L25: =IF(G25<>"","quoted",IF(AND(H25>0,I25>0),"interpolated","flat extrapolation")) -> interpolated | M25: =IF(Inputs!E48="","",Inputs!E48) | N25: =IF(M25<>"",A25,N24) -> 20 | O25: =IF(M25<>"",A25,O26) -> 30 | P25: =IF(M25<>"",M25,IF(AND(N25>0,O25>0),INDEX($M$5:$M$34,N25)+(INDEX($M$5:$M$34,O25)-INDEX($M$5:$M$34,N25))*(A25-N25)/(O25-N25),IF(N25>0,INDEX($M$5:$M$34,N25),IF(O25>0,INDEX($M$5:$M$34,O25),NA())))) -> 0.03452 | Q25: =(1-P25*Inputs!$C$16*R24)/(1+P25*Inputs!$C$16) -> 0.49150894 | R25: =R24+Q25 -> 14.730332 | S25: =IF(M25<>"","quoted",IF(AND(N25>0,O25>0),"interpolated","flat extrapolation")) -> interpolated | U25: 20 | V25: =U25/2 -> 10 | W25: =INDEX($Q$5:$Q$34,10) -> 0.71065104 | X25: =W24/W25-1 -> 0.017729519 | Y25: =Y24+W25 -> 16.821499 | Z25: =(1-W25)/(0.5*Y25) -> 0.03440228
A26: 22 | B26: =IF(Inputs!C49="","",Inputs!C49) | C26: =IF(B26<>"",A26,C25) -> 20 | D26: =IF(B26<>"",A26,D27) -> 25 | E26: =IF(B26<>"",B26,IF(AND(C26>0,D26>0),INDEX($B$5:$B$34,C26)+(INDEX($B$5:$B$34,D26)-INDEX($B$5:$B$34,C26))*(A26-C26)/(D26-C26),IF(C26>0,INDEX($B$5:$B$34,C26),IF(D26>0,INDEX($B$5:$B$34,D26),NA())))) -> 82.4 | F26: =IF(B26<>"","quoted",IF(AND(C26>0,D26>0),"interpolated","flat extrapolation")) -> interpolated | G26: =IF(Inputs!D49="","",Inputs!D49) | H26: =IF(G26<>"",A26,H25) -> 20 | I26: =IF(G26<>"",A26,I27) -> 25 | J26: =IF(G26<>"",G26,IF(AND(H26>0,I26>0),INDEX($G$5:$G$34,H26)+(INDEX($G$5:$G$34,I26)-INDEX($G$5:$G$34,H26))*(A26-H26)/(I26-H26),IF(H26>0,INDEX($G$5:$G$34,H26),IF(I26>0,INDEX($G$5:$G$34,I26),NA())))) -> 0.04349 | K26: =2*((1+J26/Inputs!$C$18)^(Inputs!$C$18/2)-1) -> 0.043027166 | L26: =IF(G26<>"","quoted",IF(AND(H26>0,I26>0),"interpolated","flat extrapolation")) -> interpolated | M26: =IF(Inputs!E49="","",Inputs!E49) | N26: =IF(M26<>"",A26,N25) -> 20 | O26: =IF(M26<>"",A26,O27) -> 30 | P26: =IF(M26<>"",M26,IF(AND(N26>0,O26>0),INDEX($M$5:$M$34,N26)+(INDEX($M$5:$M$34,O26)-INDEX($M$5:$M$34,N26))*(A26-N26)/(O26-N26),IF(N26>0,INDEX($M$5:$M$34,N26),IF(O26>0,INDEX($M$5:$M$34,O26),NA())))) -> 0.03434 | Q26: =(1-P26*Inputs!$C$16*R25)/(1+P26*Inputs!$C$16) -> 0.47775431 | R26: =R25+Q26 -> 15.208086 | S26: =IF(M26<>"","quoted",IF(AND(N26>0,O26>0),"interpolated","flat extrapolation")) -> interpolated | U26: 21 | V26: =U26/2 -> 10.5 | W26: =SQRT(INDEX($Q$5:$Q$34,10)*INDEX($Q$5:$Q$34,11)) -> 0.69827814 | X26: =W25/W26-1 -> 0.017719145 | Y26: =Y25+W26 -> 17.519777 | Z26: =(1-W26)/(0.5*Y26) -> 0.034443572
A27: 23 | B27: =IF(Inputs!C50="","",Inputs!C50) | C27: =IF(B27<>"",A27,C26) -> 20 | D27: =IF(B27<>"",A27,D28) -> 25 | E27: =IF(B27<>"",B27,IF(AND(C27>0,D27>0),INDEX($B$5:$B$34,C27)+(INDEX($B$5:$B$34,D27)-INDEX($B$5:$B$34,C27))*(A27-C27)/(D27-C27),IF(C27>0,INDEX($B$5:$B$34,C27),IF(D27>0,INDEX($B$5:$B$34,D27),NA())))) -> 84.6 | F27: =IF(B27<>"","quoted",IF(AND(C27>0,D27>0),"interpolated","flat extrapolation")) -> interpolated | G27: =IF(Inputs!D50="","",Inputs!D50) | H27: =IF(G27<>"",A27,H26) -> 20 | I27: =IF(G27<>"",A27,I28) -> 25 | J27: =IF(G27<>"",G27,IF(AND(H27>0,I27>0),INDEX($G$5:$G$34,H27)+(INDEX($G$5:$G$34,I27)-INDEX($G$5:$G$34,H27))*(A27-H27)/(I27-H27),IF(H27>0,INDEX($G$5:$G$34,H27),IF(I27>0,INDEX($G$5:$G$34,I27),NA())))) -> 0.04349 | K27: =2*((1+J27/Inputs!$C$18)^(Inputs!$C$18/2)-1) -> 0.043027166 | L27: =IF(G27<>"","quoted",IF(AND(H27>0,I27>0),"interpolated","flat extrapolation")) -> interpolated | M27: =IF(Inputs!E50="","",Inputs!E50) | N27: =IF(M27<>"",A27,N26) -> 20 | O27: =IF(M27<>"",A27,O28) -> 30 | P27: =IF(M27<>"",M27,IF(AND(N27>0,O27>0),INDEX($M$5:$M$34,N27)+(INDEX($M$5:$M$34,O27)-INDEX($M$5:$M$34,N27))*(A27-N27)/(O27-N27),IF(N27>0,INDEX($M$5:$M$34,N27),IF(O27>0,INDEX($M$5:$M$34,O27),NA())))) -> 0.03416 | Q27: =(1-P27*Inputs!$C$16*R26)/(1+P27*Inputs!$C$16) -> 0.46462034 | R27: =R26+Q27 -> 15.672707 | S27: =IF(M27<>"","quoted",IF(AND(N27>0,O27>0),"interpolated","flat extrapolation")) -> interpolated | U27: 22 | V27: =U27/2 -> 11 | W27: =INDEX($Q$5:$Q$34,11) -> 0.68612067 | X27: =W26/W27-1 -> 0.017719145 | Y27: =Y26+W27 -> 18.205898 | Z27: =(1-W27)/(0.5*Y27) -> 0.03448106
A28: 24 | B28: =IF(Inputs!C51="","",Inputs!C51) | C28: =IF(B28<>"",A28,C27) -> 20 | D28: =IF(B28<>"",A28,D29) -> 25 | E28: =IF(B28<>"",B28,IF(AND(C28>0,D28>0),INDEX($B$5:$B$34,C28)+(INDEX($B$5:$B$34,D28)-INDEX($B$5:$B$34,C28))*(A28-C28)/(D28-C28),IF(C28>0,INDEX($B$5:$B$34,C28),IF(D28>0,INDEX($B$5:$B$34,D28),NA())))) -> 86.8 | F28: =IF(B28<>"","quoted",IF(AND(C28>0,D28>0),"interpolated","flat extrapolation")) -> interpolated | G28: =IF(Inputs!D51="","",Inputs!D51) | H28: =IF(G28<>"",A28,H27) -> 20 | I28: =IF(G28<>"",A28,I29) -> 25 | J28: =IF(G28<>"",G28,IF(AND(H28>0,I28>0),INDEX($G$5:$G$34,H28)+(INDEX($G$5:$G$34,I28)-INDEX($G$5:$G$34,H28))*(A28-H28)/(I28-H28),IF(H28>0,INDEX($G$5:$G$34,H28),IF(I28>0,INDEX($G$5:$G$34,I28),NA())))) -> 0.04349 | K28: =2*((1+J28/Inputs!$C$18)^(Inputs!$C$18/2)-1) -> 0.043027166 | L28: =IF(G28<>"","quoted",IF(AND(H28>0,I28>0),"interpolated","flat extrapolation")) -> interpolated | M28: =IF(Inputs!E51="","",Inputs!E51) | N28: =IF(M28<>"",A28,N27) -> 20 | O28: =IF(M28<>"",A28,O29) -> 30 | P28: =IF(M28<>"",M28,IF(AND(N28>0,O28>0),INDEX($M$5:$M$34,N28)+(INDEX($M$5:$M$34,O28)-INDEX($M$5:$M$34,N28))*(A28-N28)/(O28-N28),IF(N28>0,INDEX($M$5:$M$34,N28),IF(O28>0,INDEX($M$5:$M$34,O28),NA())))) -> 0.03398 | Q28: =(1-P28*Inputs!$C$16*R27)/(1+P28*Inputs!$C$16) -> 0.45207976 | R28: =R27+Q28 -> 16.124786 | S28: =IF(M28<>"","quoted",IF(AND(N28>0,O28>0),"interpolated","flat extrapolation")) -> interpolated | U28: 23 | V28: =U28/2 -> 11.5 | W28: =SQRT(INDEX($Q$5:$Q$34,11)*INDEX($Q$5:$Q$34,12)) -> 0.67411049 | X28: =W27/W28-1 -> 0.017816333 | Y28: =Y27+W28 -> 18.880009 | Z28: =(1-W28)/(0.5*Y28) -> 0.034522178
A29: 25 | B29: =IF(Inputs!C52="","",Inputs!C52) -> 89 | C29: =IF(B29<>"",A29,C28) -> 25 | D29: =IF(B29<>"",A29,D30) -> 25 | E29: =IF(B29<>"",B29,IF(AND(C29>0,D29>0),INDEX($B$5:$B$34,C29)+(INDEX($B$5:$B$34,D29)-INDEX($B$5:$B$34,C29))*(A29-C29)/(D29-C29),IF(C29>0,INDEX($B$5:$B$34,C29),IF(D29>0,INDEX($B$5:$B$34,D29),NA())))) -> 89 | F29: =IF(B29<>"","quoted",IF(AND(C29>0,D29>0),"interpolated","flat extrapolation")) -> quoted | G29: =IF(Inputs!D52="","",Inputs!D52) -> 0.04349 | H29: =IF(G29<>"",A29,H28) -> 25 | I29: =IF(G29<>"",A29,I30) -> 25 | J29: =IF(G29<>"",G29,IF(AND(H29>0,I29>0),INDEX($G$5:$G$34,H29)+(INDEX($G$5:$G$34,I29)-INDEX($G$5:$G$34,H29))*(A29-H29)/(I29-H29),IF(H29>0,INDEX($G$5:$G$34,H29),IF(I29>0,INDEX($G$5:$G$34,I29),NA())))) -> 0.04349 | K29: =2*((1+J29/Inputs!$C$18)^(Inputs!$C$18/2)-1) -> 0.043027166 | L29: =IF(G29<>"","quoted",IF(AND(H29>0,I29>0),"interpolated","flat extrapolation")) -> quoted | M29: =IF(Inputs!E52="","",Inputs!E52) | N29: =IF(M29<>"",A29,N28) -> 20 | O29: =IF(M29<>"",A29,O30) -> 30 | P29: =IF(M29<>"",M29,IF(AND(N29>0,O29>0),INDEX($M$5:$M$34,N29)+(INDEX($M$5:$M$34,O29)-INDEX($M$5:$M$34,N29))*(A29-N29)/(O29-N29),IF(N29>0,INDEX($M$5:$M$34,N29),IF(O29>0,INDEX($M$5:$M$34,O29),NA())))) -> 0.0338 | Q29: =(1-P29*Inputs!$C$16*R28)/(1+P29*Inputs!$C$16) -> 0.44010661 | R29: =R28+Q29 -> 16.564893 | S29: =IF(M29<>"","quoted",IF(AND(N29>0,O29>0),"interpolated","flat extrapolation")) -> interpolated | U29: 24 | V29: =U29/2 -> 12 | W29: =INDEX($Q$5:$Q$34,12) -> 0.66231055 | X29: =W28/W29-1 -> 0.017816333 | Y29: =Y28+W29 -> 19.542319 | Z29: =(1-W29)/(0.5*Y29) -> 0.034559813
A30: 26 | B30: =IF(Inputs!C53="","",Inputs!C53) | C30: =IF(B30<>"",A30,C29) -> 25 | D30: =IF(B30<>"",A30,D31) -> 28 | E30: =IF(B30<>"",B30,IF(AND(C30>0,D30>0),INDEX($B$5:$B$34,C30)+(INDEX($B$5:$B$34,D30)-INDEX($B$5:$B$34,C30))*(A30-C30)/(D30-C30),IF(C30>0,INDEX($B$5:$B$34,C30),IF(D30>0,INDEX($B$5:$B$34,D30),NA())))) -> 90 | F30: =IF(B30<>"","quoted",IF(AND(C30>0,D30>0),"interpolated","flat extrapolation")) -> interpolated | G30: =IF(Inputs!D53="","",Inputs!D53) | H30: =IF(G30<>"",A30,H29) -> 25 | I30: =IF(G30<>"",A30,I31) -> 28 | J30: =IF(G30<>"",G30,IF(AND(H30>0,I30>0),INDEX($G$5:$G$34,H30)+(INDEX($G$5:$G$34,I30)-INDEX($G$5:$G$34,H30))*(A30-H30)/(I30-H30),IF(H30>0,INDEX($G$5:$G$34,H30),IF(I30>0,INDEX($G$5:$G$34,I30),NA())))) -> 0.04358 | K30: =2*((1+J30/Inputs!$C$18)^(Inputs!$C$18/2)-1) -> 0.043115268 | L30: =IF(G30<>"","quoted",IF(AND(H30>0,I30>0),"interpolated","flat extrapolation")) -> interpolated | M30: =IF(Inputs!E53="","",Inputs!E53) | N30: =IF(M30<>"",A30,N29) -> 20 | O30: =IF(M30<>"",A30,O31) -> 30 | P30: =IF(M30<>"",M30,IF(AND(N30>0,O30>0),INDEX($M$5:$M$34,N30)+(INDEX($M$5:$M$34,O30)-INDEX($M$5:$M$34,N30))*(A30-N30)/(O30-N30),IF(N30>0,INDEX($M$5:$M$34,N30),IF(O30>0,INDEX($M$5:$M$34,O30),NA())))) -> 0.03362 | Q30: =(1-P30*Inputs!$C$16*R29)/(1+P30*Inputs!$C$16) -> 0.4286762 | R30: =R29+Q30 -> 16.993569 | S30: =IF(M30<>"","quoted",IF(AND(N30>0,O30>0),"interpolated","flat extrapolation")) -> interpolated | U30: 25 | V30: =U30/2 -> 12.5 | W30: =SQRT(INDEX($Q$5:$Q$34,12)*INDEX($Q$5:$Q$34,13)) -> 0.65065363 | X30: =W29/W30-1 -> 0.017915708 | Y30: =Y29+W30 -> 20.192973 | Z30: =(1-W30)/(0.5*Y30) -> 0.034600787
A31: 27 | B31: =IF(Inputs!C54="","",Inputs!C54) | C31: =IF(B31<>"",A31,C30) -> 25 | D31: =IF(B31<>"",A31,D32) -> 28 | E31: =IF(B31<>"",B31,IF(AND(C31>0,D31>0),INDEX($B$5:$B$34,C31)+(INDEX($B$5:$B$34,D31)-INDEX($B$5:$B$34,C31))*(A31-C31)/(D31-C31),IF(C31>0,INDEX($B$5:$B$34,C31),IF(D31>0,INDEX($B$5:$B$34,D31),NA())))) -> 91 | F31: =IF(B31<>"","quoted",IF(AND(C31>0,D31>0),"interpolated","flat extrapolation")) -> interpolated | G31: =IF(Inputs!D54="","",Inputs!D54) | H31: =IF(G31<>"",A31,H30) -> 25 | I31: =IF(G31<>"",A31,I32) -> 28 | J31: =IF(G31<>"",G31,IF(AND(H31>0,I31>0),INDEX($G$5:$G$34,H31)+(INDEX($G$5:$G$34,I31)-INDEX($G$5:$G$34,H31))*(A31-H31)/(I31-H31),IF(H31>0,INDEX($G$5:$G$34,H31),IF(I31>0,INDEX($G$5:$G$34,I31),NA())))) -> 0.04367 | K31: =2*((1+J31/Inputs!$C$18)^(Inputs!$C$18/2)-1) -> 0.043203367 | L31: =IF(G31<>"","quoted",IF(AND(H31>0,I31>0),"interpolated","flat extrapolation")) -> interpolated | M31: =IF(Inputs!E54="","",Inputs!E54) | N31: =IF(M31<>"",A31,N30) -> 20 | O31: =IF(M31<>"",A31,O32) -> 30 | P31: =IF(M31<>"",M31,IF(AND(N31>0,O31>0),INDEX($M$5:$M$34,N31)+(INDEX($M$5:$M$34,O31)-INDEX($M$5:$M$34,N31))*(A31-N31)/(O31-N31),IF(N31>0,INDEX($M$5:$M$34,N31),IF(O31>0,INDEX($M$5:$M$34,O31),NA())))) -> 0.03344 | Q31: =(1-P31*Inputs!$C$16*R30)/(1+P31*Inputs!$C$16) -> 0.41776498 | R31: =R30+Q31 -> 17.411334 | S31: =IF(M31<>"","quoted",IF(AND(N31>0,O31>0),"interpolated","flat extrapolation")) -> interpolated | U31: 26 | V31: =U31/2 -> 13 | W31: =INDEX($Q$5:$Q$34,13) -> 0.63920187 | X31: =W30/W31-1 -> 0.017915708 | Y31: =Y30+W31 -> 20.832175 | Z31: =(1-W31)/(0.5*Y31) -> 0.034638547
A32: 28 | B32: =IF(Inputs!C55="","",Inputs!C55) -> 92 | C32: =IF(B32<>"",A32,C31) -> 28 | D32: =IF(B32<>"",A32,D33) -> 28 | E32: =IF(B32<>"",B32,IF(AND(C32>0,D32>0),INDEX($B$5:$B$34,C32)+(INDEX($B$5:$B$34,D32)-INDEX($B$5:$B$34,C32))*(A32-C32)/(D32-C32),IF(C32>0,INDEX($B$5:$B$34,C32),IF(D32>0,INDEX($B$5:$B$34,D32),NA())))) -> 92 | F32: =IF(B32<>"","quoted",IF(AND(C32>0,D32>0),"interpolated","flat extrapolation")) -> quoted | G32: =IF(Inputs!D55="","",Inputs!D55) -> 0.04376 | H32: =IF(G32<>"",A32,H31) -> 28 | I32: =IF(G32<>"",A32,I33) -> 28 | J32: =IF(G32<>"",G32,IF(AND(H32>0,I32>0),INDEX($G$5:$G$34,H32)+(INDEX($G$5:$G$34,I32)-INDEX($G$5:$G$34,H32))*(A32-H32)/(I32-H32),IF(H32>0,INDEX($G$5:$G$34,H32),IF(I32>0,INDEX($G$5:$G$34,I32),NA())))) -> 0.04376 | K32: =2*((1+J32/Inputs!$C$18)^(Inputs!$C$18/2)-1) -> 0.043291462 | L32: =IF(G32<>"","quoted",IF(AND(H32>0,I32>0),"interpolated","flat extrapolation")) -> quoted | M32: =IF(Inputs!E55="","",Inputs!E55) | N32: =IF(M32<>"",A32,N31) -> 20 | O32: =IF(M32<>"",A32,O33) -> 30 | P32: =IF(M32<>"",M32,IF(AND(N32>0,O32>0),INDEX($M$5:$M$34,N32)+(INDEX($M$5:$M$34,O32)-INDEX($M$5:$M$34,N32))*(A32-N32)/(O32-N32),IF(N32>0,INDEX($M$5:$M$34,N32),IF(O32>0,INDEX($M$5:$M$34,O32),NA())))) -> 0.03326 | Q32: =(1-P32*Inputs!$C$16*R31)/(1+P32*Inputs!$C$16) -> 0.40735054 | R32: =R31+Q32 -> 17.818685 | S32: =IF(M32<>"","quoted",IF(AND(N32>0,O32>0),"interpolated","flat extrapolation")) -> interpolated | U32: 27 | V32: =U32/2 -> 13.5 | W32: =SQRT(INDEX($Q$5:$Q$34,13)*INDEX($Q$5:$Q$34,14)) -> 0.62788896 | X32: =W31/W32-1 -> 0.018017377 | Y32: =Y31+W32 -> 21.460064 | Z32: =(1-W32)/(0.5*Y32) -> 0.034679397
A33: 29 | B33: =IF(Inputs!C56="","",Inputs!C56) | C33: =IF(B33<>"",A33,C32) -> 28 | D33: =IF(B33<>"",A33,D34) -> 0 | E33: =IF(B33<>"",B33,IF(AND(C33>0,D33>0),INDEX($B$5:$B$34,C33)+(INDEX($B$5:$B$34,D33)-INDEX($B$5:$B$34,C33))*(A33-C33)/(D33-C33),IF(C33>0,INDEX($B$5:$B$34,C33),IF(D33>0,INDEX($B$5:$B$34,D33),NA())))) -> 92 | F33: =IF(B33<>"","quoted",IF(AND(C33>0,D33>0),"interpolated","flat extrapolation")) -> flat extrapolation | G33: =IF(Inputs!D56="","",Inputs!D56) | H33: =IF(G33<>"",A33,H32) -> 28 | I33: =IF(G33<>"",A33,I34) -> 0 | J33: =IF(G33<>"",G33,IF(AND(H33>0,I33>0),INDEX($G$5:$G$34,H33)+(INDEX($G$5:$G$34,I33)-INDEX($G$5:$G$34,H33))*(A33-H33)/(I33-H33),IF(H33>0,INDEX($G$5:$G$34,H33),IF(I33>0,INDEX($G$5:$G$34,I33),NA())))) -> 0.04376 | K33: =2*((1+J33/Inputs!$C$18)^(Inputs!$C$18/2)-1) -> 0.043291462 | L33: =IF(G33<>"","quoted",IF(AND(H33>0,I33>0),"interpolated","flat extrapolation")) -> flat extrapolation | M33: =IF(Inputs!E56="","",Inputs!E56) | N33: =IF(M33<>"",A33,N32) -> 20 | O33: =IF(M33<>"",A33,O34) -> 30 | P33: =IF(M33<>"",M33,IF(AND(N33>0,O33>0),INDEX($M$5:$M$34,N33)+(INDEX($M$5:$M$34,O33)-INDEX($M$5:$M$34,N33))*(A33-N33)/(O33-N33),IF(N33>0,INDEX($M$5:$M$34,N33),IF(O33>0,INDEX($M$5:$M$34,O33),NA())))) -> 0.03308 | Q33: =(1-P33*Inputs!$C$16*R32)/(1+P33*Inputs!$C$16) -> 0.39741153 | R33: =R32+Q33 -> 18.216096 | S33: =IF(M33<>"","quoted",IF(AND(N33>0,O33>0),"interpolated","flat extrapolation")) -> interpolated | U33: 28 | V33: =U33/2 -> 14 | W33: =INDEX($Q$5:$Q$34,14) -> 0.61677627 | X33: =W32/W33-1 -> 0.018017377 | Y33: =Y32+W33 -> 22.07684 | Z33: =(1-W33)/(0.5*Y33) -> 0.034717263
A34: 30 | B34: =IF(Inputs!C57="","",Inputs!C57) | C34: =IF(B34<>"",A34,C33) -> 28 | D34: =IF(B34<>"",A34,0) -> 0 | E34: =IF(B34<>"",B34,IF(AND(C34>0,D34>0),INDEX($B$5:$B$34,C34)+(INDEX($B$5:$B$34,D34)-INDEX($B$5:$B$34,C34))*(A34-C34)/(D34-C34),IF(C34>0,INDEX($B$5:$B$34,C34),IF(D34>0,INDEX($B$5:$B$34,D34),NA())))) -> 92 | F34: =IF(B34<>"","quoted",IF(AND(C34>0,D34>0),"interpolated","flat extrapolation")) -> flat extrapolation | G34: =IF(Inputs!D57="","",Inputs!D57) | H34: =IF(G34<>"",A34,H33) -> 28 | I34: =IF(G34<>"",A34,0) -> 0 | J34: =IF(G34<>"",G34,IF(AND(H34>0,I34>0),INDEX($G$5:$G$34,H34)+(INDEX($G$5:$G$34,I34)-INDEX($G$5:$G$34,H34))*(A34-H34)/(I34-H34),IF(H34>0,INDEX($G$5:$G$34,H34),IF(I34>0,INDEX($G$5:$G$34,I34),NA())))) -> 0.04376 | K34: =2*((1+J34/Inputs!$C$18)^(Inputs!$C$18/2)-1) -> 0.043291462 | L34: =IF(G34<>"","quoted",IF(AND(H34>0,I34>0),"interpolated","flat extrapolation")) -> flat extrapolation | M34: =IF(Inputs!E57="","",Inputs!E57) -> 0.0329 | N34: =IF(M34<>"",A34,N33) -> 30 | O34: =IF(M34<>"",A34,0) -> 30 | P34: =IF(M34<>"",M34,IF(AND(N34>0,O34>0),INDEX($M$5:$M$34,N34)+(INDEX($M$5:$M$34,O34)-INDEX($M$5:$M$34,N34))*(A34-N34)/(O34-N34),IF(N34>0,INDEX($M$5:$M$34,N34),IF(O34>0,INDEX($M$5:$M$34,O34),NA())))) -> 0.0329 | Q34: =(1-P34*Inputs!$C$16*R33)/(1+P34*Inputs!$C$16) -> 0.38792761 | R34: =R33+Q34 -> 18.604024 | S34: =IF(M34<>"","quoted",IF(AND(N34>0,O34>0),"interpolated","flat extrapolation")) -> quoted | U34: 29 | V34: =U34/2 -> 14.5 | W34: =SQRT(INDEX($Q$5:$Q$34,14)*INDEX($Q$5:$Q$34,15)) -> 0.60579833 | X34: =W33/W34-1 -> 0.018121451 | Y34: =Y33+W34 -> 22.682638 | Z34: =(1-W34)/(0.5*Y34) -> 0.034758009
U35: 30 | V35: =U35/2 -> 15 | W35: =INDEX($Q$5:$Q$34,15) -> 0.59501578 | X35: =W34/W35-1 -> 0.018121451 | Y35: =Y34+W35 -> 23.277654 | Z35: =(1-W35)/(0.5*Y35) -> 0.034795965
U36: 31 | V36: =U36/2 -> 15.5 | W36: =SQRT(INDEX($Q$5:$Q$34,15)*INDEX($Q$5:$Q$34,16)) -> 0.58531642 | X36: =W35/W36-1 -> 0.016571135 | Y36: =Y35+W36 -> 23.86297 | Z36: =(1-W36)/(0.5*Y36) -> 0.034755403
A37: Last quoted Z-spread tenor | E37: =C34 -> 28 | U37: 32 | V37: =U37/2 -> 16 | W37: =INDEX($Q$5:$Q$34,16) -> 0.57577517 | X37: =W36/W37-1 -> 0.016571135 | Y37: =Y36+W37 -> 24.438746 | Z37: =(1-W37)/(0.5*Y37) -> 0.034717398
A38: Last quoted YTM tenor | E38: =H34 -> 28 | U38: 33 | V38: =U38/2 -> 16.5 | W38: =SQRT(INDEX($Q$5:$Q$34,16)*INDEX($Q$5:$Q$34,17)) -> 0.56644863 | X38: =W37/W38-1 -> 0.016464948 | Y38: =Y37+W38 -> 25.005194 | Z38: =(1-W38)/(0.5*Y38) -> 0.034676905
A39: Last quoted swap tenor | E39: =N34 -> 30 | U39: 34 | V39: =U39/2 -> 17 | W39: =INDEX($Q$5:$Q$34,17) -> 0.55727315 | X39: =W38/W39-1 -> 0.016464948 | Y39: =Y38+W39 -> 25.562467 | Z39: =(1-W39)/(0.5*Y39) -> 0.03463882
A40: Count of Z-spread points | E40: =COUNT(B5:B34) -> 17 | U40: 35 | V40: =U40/2 -> 17.5 | W40: =SQRT(INDEX($Q$5:$Q$34,17)*INDEX($Q$5:$Q$34,18)) -> 0.54830468 | X40: =W39/W40-1 -> 0.016356728 | Y40: =Y39+W40 -> 26.110772 | Z40: =(1-W40)/(0.5*Y40) -> 0.034598389
A41: Count of YTM points | E41: =COUNT(G5:G34) -> 17 | U41: 36 | V41: =U41/2 -> 18 | W41: =INDEX($Q$5:$Q$34,18) -> 0.53948054 | X41: =W40/W41-1 -> 0.016356728 | Y41: =Y40+W41 -> 26.650253 | Z41: =(1-W41)/(0.5*Y41) -> 0.034560232
A42: Count of swap points | E42: =COUNT(M5:M34) -> 12 | U42: 37 | V42: =U42/2 -> 18.5 | W42: =SQRT(INDEX($Q$5:$Q$34,18)*INDEX($Q$5:$Q$34,19)) -> 0.53085602 | X42: =W41/W42-1 -> 0.01624644 | Y42: =Y41+W42 -> 27.181109 | Z42: =(1-W42)/(0.5*Y42) -> 0.034519856
A43: Z curve non-monotonic over quoted range? (1 = yes) | E43: =IF(SUMPRODUCT((E6:E34<E5:E33)*1)>0,1,0) -> 0 | U43: 38 | V43: =U43/2 -> 19 | W43: =INDEX($Q$5:$Q$34,19) -> 0.52236938 | X43: =W42/W43-1 -> 0.01624644 | Y43: =Y42+W43 -> 27.703478 | Z43: =(1-W43)/(0.5*Y43) -> 0.034481636
A44: YTM curve non-monotonic? (1 = yes) | E44: =IF(SUMPRODUCT((J6:J34<J5:J33)*1)>0,1,0) -> 0 | U44: 39 | V44: =U44/2 -> 19.5 | W44: =SQRT(INDEX($Q$5:$Q$34,19)*INDEX($Q$5:$Q$34,20)) -> 0.51407526 | X44: =W43/W44-1 -> 0.016134054 | Y44: =Y43+W44 -> 28.217553 | Z44: =(1-W44)/(0.5*Y44) -> 0.034441309
U45: 40 | V45: =U45/2 -> 20 | W45: =INDEX($Q$5:$Q$34,20) -> 0.50591284 | X45: =W44/W45-1 -> 0.016134054 | Y45: =Y44+W45 -> 28.723466 | Z45: =(1-W45)/(0.5*Y45) -> 0.034403032
U46: 41 | V46: =U46/2 -> 20.5 | W46: =SQRT(INDEX($Q$5:$Q$34,20)*INDEX($Q$5:$Q$34,21)) -> 0.49865888 | X46: =W45/W46-1 -> 0.014546928 | Y46: =Y45+W46 -> 29.222125 | Z46: =(1-W46)/(0.5*Y46) -> 0.034312434
U47: 42 | V47: =U47/2 -> 21 | W47: =INDEX($Q$5:$Q$34,21) -> 0.49150894 | X47: =W46/W47-1 -> 0.014546928 | Y47: =Y46+W47 -> 29.713634 | Z47: =(1-W47)/(0.5*Y47) -> 0.034226111
U48: 43 | V48: =U48/2 -> 21.5 | W48: =SQRT(INDEX($Q$5:$Q$34,21)*INDEX($Q$5:$Q$34,22)) -> 0.48458283 | X48: =W47/W48-1 -> 0.014292936 | Y48: =Y47+W48 -> 30.198217 | Z48: =(1-W48)/(0.5*Y48) -> 0.034135603
U49: 44 | V49: =U49/2 -> 22 | W49: =INDEX($Q$5:$Q$34,22) -> 0.47775431 | X49: =W48/W49-1 -> 0.014292936 | Y49: =Y48+W49 -> 30.675971 | Z49: =(1-W49)/(0.5*Y49) -> 0.034049171
U50: 45 | V50: =U50/2 -> 22.5 | W50: =SQRT(INDEX($Q$5:$Q$34,22)*INDEX($Q$5:$Q$34,23)) -> 0.47114156 | X50: =W49/W50-1 -> 0.014035595 | Y50: =Y49+W50 -> 31.147113 | Z50: =(1-W50)/(0.5*Y50) -> 0.033958746
U51: 46 | V51: =U51/2 -> 23 | W51: =INDEX($Q$5:$Q$34,23) -> 0.46462034 | X51: =W50/W51-1 -> 0.014035595 | Y51: =Y50+W51 -> 31.611733 | Z51: =(1-W51)/(0.5*Y51) -> 0.033872212
U52: 47 | V52: =U52/2 -> 23.5 | W52: =SQRT(INDEX($Q$5:$Q$34,23)*INDEX($Q$5:$Q$34,24)) -> 0.45830716 | X52: =W51/W52-1 -> 0.013775004 | Y52: =Y51+W52 -> 32.07004 | Z52: =(1-W52)/(0.5*Y52) -> 0.033781863
U53: 48 | V53: =U53/2 -> 24 | W53: =INDEX($Q$5:$Q$34,24) -> 0.45207976 | X53: =W52/W53-1 -> 0.013775004 | Y53: =Y52+W53 -> 32.52212 | Z53: =(1-W53)/(0.5*Y53) -> 0.033695235
U54: 49 | V54: =U54/2 -> 24.5 | W54: =SQRT(INDEX($Q$5:$Q$34,24)*INDEX($Q$5:$Q$34,25)) -> 0.44605301 | X54: =W53/W54-1 -> 0.01351127 | Y54: =Y53+W54 -> 32.968173 | Z54: =(1-W54)/(0.5*Y54) -> 0.033604955
U55: 50 | V55: =U55/2 -> 25 | W55: =INDEX($Q$5:$Q$34,25) -> 0.44010661 | X55: =W54/W55-1 -> 0.01351127 | Y55: =Y54+W55 -> 33.40828 | Z55: =(1-W55)/(0.5*Y55) -> 0.033518241
U56: 51 | V56: =U56/2 -> 25.5 | W56: =SQRT(INDEX($Q$5:$Q$34,25)*INDEX($Q$5:$Q$34,26)) -> 0.43435381 | X56: =W55/W56-1 -> 0.013244514 | Y56: =Y55+W56 -> 33.842633 | Z56: =(1-W56)/(0.5*Y56) -> 0.033428025
U57: 52 | V57: =U57/2 -> 26 | W57: =INDEX($Q$5:$Q$34,26) -> 0.4286762 | X57: =W56/W57-1 -> 0.013244514 | Y57: =Y56+W57 -> 34.27131 | Z57: =(1-W57)/(0.5*Y57) -> 0.03334123
U58: 53 | V58: =U58/2 -> 26.5 | W58: =SQRT(INDEX($Q$5:$Q$34,26)*INDEX($Q$5:$Q$34,27)) -> 0.42318543 | X58: =W57/W58-1 -> 0.012974866 | Y58: =Y57+W58 -> 34.694495 | Z58: =(1-W58)/(0.5*Y58) -> 0.033251072
U59: 54 | V59: =U59/2 -> 27 | W59: =INDEX($Q$5:$Q$34,27) -> 0.41776498 | X59: =W58/W59-1 -> 0.012974866 | Y59: =Y58+W59 -> 35.11226 | Z59: =(1-W59)/(0.5*Y59) -> 0.033164201
U60: 55 | V60: =U60/2 -> 27.5 | W60: =SQRT(INDEX($Q$5:$Q$34,27)*INDEX($Q$5:$Q$34,28)) -> 0.4125249 | X60: =W59/W60-1 -> 0.012702465 | Y60: =Y59+W60 -> 35.524785 | Z60: =(1-W60)/(0.5*Y60) -> 0.033074098
U61: 56 | V61: =U61/2 -> 28 | W61: =INDEX($Q$5:$Q$34,28) -> 0.40735054 | X61: =W60/W61-1 -> 0.012702465 | Y61: =Y60+W61 -> 35.932135 | Z61: =(1-W61)/(0.5*Y61) -> 0.032987155
U62: 57 | V62: =U62/2 -> 28.5 | W62: =SQRT(INDEX($Q$5:$Q$34,28)*INDEX($Q$5:$Q$34,29)) -> 0.40235035 | X62: =W61/W62-1 -> 0.012427462 | Y62: =Y61+W62 -> 36.334486 | Z62: =(1-W62)/(0.5*Y62) -> 0.032897102
U63: 58 | V63: =U63/2 -> 29 | W63: =INDEX($Q$5:$Q$34,29) -> 0.39741153 | X63: =W62/W63-1 -> 0.012427462 | Y63: =Y62+W63 -> 36.731897 | Z63: =(1-W63)/(0.5*Y63) -> 0.032810092
U64: 59 | V64: =U64/2 -> 29.5 | W64: =SQRT(INDEX($Q$5:$Q$34,29)*INDEX($Q$5:$Q$34,30)) -> 0.39264094 | X64: =W63/W64-1 -> 0.012150017 | Y64: =Y63+W64 -> 37.124538 | Z64: =(1-W64)/(0.5*Y64) -> 0.032720087
U65: 60 | V65: =U65/2 -> 30 | W65: =INDEX($Q$5:$Q$34,30) -> 0.38792761 | X65: =W64/W65-1 -> 0.012150017 | Y65: =Y64+W65 -> 37.512466 | Z65: =(1-W65)/(0.5*Y65) -> 0.032633013

Sheet Calc_Floating
A1: FLOATING loan vs bond Z-spread curve — calibration, loan grid and exact pricing
A2: Calculation sheet — no inputs here. Units: per 1 of notional, rates as decimals.
D3: Pricing results (per 1 notional)
A4: Recovery R | B4: =Inputs!C13 -> 0.4 | D4: WAL = Σ O·a (years) | E4: =SUM($AD$32:$AD$91) -> 12.5
A5: Accrual a (semi-annual) | B5: 0.5 | D5: Risky annuity B = Σ DF·S·a·O | E5: =SUM($U$32:$U$91) -> 9.0024448
A6: Last quoted credit tenor (years) | B6: =Curves!E37 -> 28 | D6: Bond Z-spread at WAL (bp, linear interp.) | E6: =INDEX(Curves!$E$5:$E$34,MAX(1,MIN(29,INT(MIN(30,MAX(1,E4))))))+(INDEX(Curves!$E$5:$E$34,MAX(1,MIN(29,INT(MIN(30,MAX(1,E4)))))+1)-INDEX(Curves!$E$5:$E$34,MAX(1,MIN(29,INT(MIN(30,MAX(1,E4)))))))*(MIN(30,MAX(1,E4))-MAX(1,MIN(29,INT(MIN(30,MAX(1,E4)))))) -> 53.5
A7: Drawdown periods D = 2x | B7: =ROUND(2*Inputs!C6,0) -> 2 | D7: Shortcut spread (decimal) | E7: =E6/10000 -> 0.00535
A8: Repayment instalments = 2y | B8: =ROUND(2*Inputs!C7,0) -> 46 | D8: Adjustment X (decimal) | E8: =Inputs!C8/10000 -> 0
A9: Total periods n | B9: =B7+B8 -> 48 | D9: Loan spread/rate CHARGED = shortcut + X | E9: =E7+E8 -> 0.00535
A10: Number of drawdowns (≥1) | B10: =MAX(B7,1) -> 2 | D10: FAIR (hazard-consistent) spread/rate = Σw·k / Σw | E10: =SUMPRODUCT($U$32:$U$91,$Y$32:$Y$91)/E5 -> 0.0062322004
D11: NET wedge = fair − charged (+ = borrower saves) | E11: =E10-E9 -> 0.00088220045
D12: Exposure-weighted risk-free forward Σw·f / Σw | E12: =SUMPRODUCT($U$32:$U$91,$X$32:$X$91)/E5 -> 0.034476271
D13: PV of saving, per 1 notional = Σ w·(k − charged) | E13: =SUM($Z$32:$Z$91) -> 0.0079419608
D14: of which WAL → maturity (benefit) | E14: =SUM($AB$32:$AB$91) -> 0.013197622
D15: of which start → WAL (loss) | E15: =SUM($AC$32:$AC$91) -> -0.0052556612
D16: Principal-years after WAL | E16: =SUM($AE$32:$AE$91) -> 3
D17: Principal-years before WAL | E17: =E4-E16 -> 9.5
D18: Risky annuity after WAL | E18: =SUMPRODUCT($U$32:$U$91,$AA$32:$AA$91) -> 1.3713339
D19: Avg fair spread/rate after WAL | E19: =IF(E18>0,SUMPRODUCT($U$32:$U$91,$AA$32:$AA$91,$Y$32:$Y$91)/E18,0) -> 0.01497393
D20: Avg fair spread/rate before WAL | E20: =IF(E5-E18>0,(SUMPRODUCT($U$32:$U$91,$Y$32:$Y$91)-SUMPRODUCT($U$32:$U$91,$AA$32:$AA$91,$Y$32:$Y$91))/(E5-E18),0) -> 0.0046612849
D21: CHECK: PV(drawdowns) − PV(loan at charged) — must equal E13 | E21: =SUM($T$32:$T$91)-SUM($AF$32:$AF$91) -> 0.0079419608
D22: CHECK: max bullet repricing error (bp) | E22: =MAX($AH$32:$AH$91) -> 1.5677563e-12
D23: Minimum forward hazard λ | E23: =MIN($L$32:$L$91) -> -0.0030857345
D24: CHECK: WAL via Σt·P − Σt_draw·DD | E24: =SUMPRODUCT($B$32:$B$91,$R$32:$R$91)-SUMPRODUCT($B$32:$B$91-0.5,$AG$32:$AG$91) -> 12.5
D25: Risk-free par yield at WAL (s.a.) | E25: =INDEX(Curves!$Z$6:$Z$65,MAX(1,MIN(59,INT(2*MIN(30,MAX(0.5,E4))))))+(INDEX(Curves!$Z$6:$Z$65,MAX(1,MIN(59,INT(2*MIN(30,MAX(0.5,E4)))))+1)-INDEX(Curves!$Z$6:$Z$65,MAX(1,MIN(59,INT(2*MIN(30,MAX(0.5,E4)))))))*(2*MIN(30,MAX(0.5,E4))-MAX(1,MIN(59,INT(2*MIN(30,MAX(0.5,E4)))))) -> 0.034600787
D26: Final maturity (years) | E26: =B9/2 -> 24
A30: i | B30: t | C30: bucket b | D30: Bullet quote q_b (Z) | E30: quoted node? | F30: DF(t) | G30: f·a | H30: K = C(i−1)+q·Ann(i−1) | I30: quad a2 | J30: quad a1 | K30: quad a0 | L30: λ_b fwd hazard | M30: S(t) | N30: C cumulative | O30: Ann cumulative | P30: Bullet reprices to (b at even i) | Q30: O outstanding in period | R30: P repayment at t | S30: DD at t(i−1) | T30: PV of drawdown | U30: w = DF·S·a·O | V30: p = S(i)/S(i−1) | W30: c = credit break-even margin | X30: f fwd rf rate | Y30: k = fair spread | Z30: PV saving = w·(k − charged) | AA30: fraction of period after WAL | AB30: PV saving after WAL | AC30: PV saving before WAL | AD30: principal-years O·a | AE30: principal-years after WAL | AF30: PV loan cashflows at charged | AG30: DD amount (for WAL check) | AH30: |repricing error| bp
A31: 0 | B31: =A31/2 -> 0 | F31: =Curves!W5 -> 1 | M31: 1 | N31: 0 | O31: 0
A32: 1 | B32: =A32/2 -> 0.5 | C32: =ROUNDUP(A32/2,0) -> 1 | D32: =INDEX(Curves!$E$5:$E$34,C32)/10000 -> -0.0019 | E32: =IF(C32<=$B$6,1,0) -> 1 | F32: =Curves!W6 -> 0.98492605 | G32: =Curves!X6 -> 0.015304653 | H32: =N31+D32*O31 -> 0 | I32: =F33*M31*((G33+D32*$B$5+1)-$B$4) -> 0.59667196 | J32: =M31*(F32*((G32+D32*$B$5)-$B$4)+F33*$B$4) -> 0.0075020245 | K32: =H32+F32*M31*$B$4-1 -> -0.60602958 | L32: =IF(E32=1,-2*LN((-J32+SQRT(J32^2-4*I32*K32))/(2*I32)),0) -> -0.0030857345 | M32: =M31*EXP(-L32*$B$5) -> 1.0015441 | N32: =N31+F32*(M32*G32+$B$4*(M31-M32)) -> 0.014488913 | O32: =O31+F32*M32*$B$5 -> 0.49322342 | Q32: =IF(A32<=$B$9,MIN(A32,$B$10)/$B$10-MAX(0,MIN(A32-1,$B$9)-$B$7)/$B$8,0) -> 0.5 | R32: =IF(AND(A32>$B$7,A32<=$B$9),1/$B$8,0) -> 0 | S32: =IF(A32<=$B$10,1/$B$10,0) -> 0.5 | T32: =F31*M31*S32 -> 0.5 | U32: =F32*M32*$B$5*Q32 -> 0.24661171 | V32: =M32/M31 -> 1.0015441 | W32: =(1-V32)*(1+G32-$B$4)/(V32*$B$5) -> -0.0018972028 | X32: =G32/$B$5 -> 0.030609306 | Y32: =W32 -> -0.0018972028 | Z32: =U32*(Y32-$E$9) -> -0.0017872451 | AA32: =MAX(0,MIN(1,(B32-$E$4)/$B$5)) -> 0 | AB32: =Z32*AA32 -> 0 | AC32: =Z32-AB32 -> -0.0017872451 | AD32: =Q32*$B$5 -> 0.25 | AE32: =AD32*AA32 -> 0 | AF32: =F32*(M32*((G32+$E$9*$B$5)*Q32+R32)+$B$4*(M31-M32)*Q32) -> 0.0085638292 | AG32: =S32 -> 0.5 | AH32: 0
A33: 2 | B33: =A33/2 -> 1 | C33: =ROUNDUP(A33/2,0) -> 1 | D33: =INDEX(Curves!$E$5:$E$34,C33)/10000 -> -0.0019 | E33: =IF(C33<=$B$6,1,0) -> 1 | F33: =Curves!W7 -> 0.96833543 | G33: =Curves!X7 -> 0.017133131 | L33: =L32 -> -0.0030857345 | M33: =M32*EXP(-L33*$B$5) -> 1.0030905 | N33: =N32+F33*(M33*G33+$B$4*(M32-M33)) -> 0.030531814 | O33: =O32+F33*M33*$B$5 -> 0.97888745 | P33: =IF(E33=1,(1-N33-F33*M33)/O33,"") -> -0.0019 | Q33: =IF(A33<=$B$9,MIN(A33,$B$10)/$B$10-MAX(0,MIN(A33-1,$B$9)-$B$7)/$B$8,0) -> 1 | R33: =IF(AND(A33>$B$7,A33<=$B$9),1/$B$8,0) -> 0 | S33: =IF(A33<=$B$10,1/$B$10,0) -> 0.5 | T33: =F32*M32*S33 -> 0.49322342 | U33: =F33*M33*$B$5*Q33 -> 0.48566404 | V33: =M33/M32 -> 1.0015441 | W33: =(1-V33)*(1+G33-$B$4)/(V33*$B$5) -> -0.0019028407 | X33: =G33/$B$5 -> 0.034266261 | Y33: =W33 -> -0.0019028407 | Z33: =U33*(Y33-$E$9) -> -0.0035224439 | AA33: =MAX(0,MIN(1,(B33-$E$4)/$B$5)) -> 0 | AB33: =Z33*AA33 -> 0 | AC33: =Z33-AB33 -> -0.0035224439 | AD33: =Q33*$B$5 -> 0.5 | AE33: =AD33*AA33 -> 0 | AF33: =F33*(M33*((G33+$E$9*$B$5)*Q33+R33)+$B$4*(M32-M33)*Q33) -> 0.018641203 | AG33: =S33 -> 0.5 | AH33: =IF(E33=1,ABS(P33-D33)*10000,0) -> 6.4184769e-13
A34: 3 | B34: =A34/2 -> 1.5 | C34: =ROUNDUP(A34/2,0) -> 2 | D34: =INDEX(Curves!$E$5:$E$34,C34)/10000 -> -0.0015 | E34: =IF(C34<=$B$6,1,0) -> 1 | F34: =Curves!W8 -> 0.95147546 | G34: =Curves!X8 -> 0.017719819 | H34: =N33+D34*O33 -> 0.029063483 | I34: =F35*M33*((G35+D34*$B$5+1)-$B$4) -> 0.57859329 | J34: =M33*(F34*((G34+D34*$B$5)-$B$4)+F35*$B$4) -> 0.0095492198 | K34: =H34+F34*M33*$B$4-1 -> -0.58917012 | L34: =IF(E34=1,-2*LN((-J34+SQRT(J34^2-4*I34*K34))/(2*I34)),L33) -> -0.0017599622 | M34: =M33*EXP(-L34*$B$5) -> 1.0039736 | N34: =N33+F34*(M34*G34+$B$4*(M33-M34)) -> 0.047122687 | O34: =O33+F34*M34*$B$5 -> 1.4565156 | Q34: =IF(A34<=$B$9,MIN(A34,$B$10)/$B$10-MAX(0,MIN(A34-1,$B$9)-$B$7)/$B$8,0) -> 1 | R34: =IF(AND(A34>$B$7,A34<=$B$9),1/$B$8,0) -> 0.02173913 | S34: =IF(A34<=$B$10,1/$B$10,0) -> 0 | T34: =F33*M33*S34 -> 0 | U34: =F34*M34*$B$5*Q34 -> 0.47762812 | V34: =M34/M33 -> 1.0008804 | W34: =(1-V34)*(1+G34-$B$4)/(V34*$B$5) -> -0.0010866854 | X34: =G34/$B$5 -> 0.035439638 | Y34: =W34 -> -0.0010866854 | Z34: =U34*(Y34-$E$9) -> -0.0030743419 | AA34: =MAX(0,MIN(1,(B34-$E$4)/$B$5)) -> 0 | AB34: =Z34*AA34 -> 0 | AC34: =Z34-AB34 -> -0.0030743419 | AD34: =Q34*$B$5 -> 0.5 | AE34: =AD34*AA34 -> 0 | AF34: =F34*(M34*((G34+$E$9*$B$5)*Q34+R34)+$B$4*(M33-M34)*Q34) -> 0.039912623 | AG34: =S34 -> 0 | AH34: 0
A35: 4 | B35: =A35/2 -> 2 | C35: =ROUNDUP(A35/2,0) -> 2 | D35: =INDEX(Curves!$E$5:$E$34,C35)/10000 -> -0.0015 | E35: =IF(C35<=$B$6,1,0) -> 1 | F35: =Curves!W9 -> 0.93490904 | G35: =Curves!X9 -> 0.017719819 | L35: =L34 -> -0.0017599622 | M35: =M34*EXP(-L35*$B$5) -> 1.0048575 | N35: =N34+F35*(M35*G35+$B$4*(M34-M35)) -> 0.063439042 | O35: =O34+F35*M35*$B$5 -> 1.9262407 | P35: =IF(E35=1,(1-N35-F35*M35)/O35,"") -> -0.0015 | Q35: =IF(A35<=$B$9,MIN(A35,$B$10)/$B$10-MAX(0,MIN(A35-1,$B$9)-$B$7)/$B$8,0) -> 0.97826087 | R35: =IF(AND(A35>$B$7,A35<=$B$9),1/$B$8,0) -> 0.02173913 | S35: =IF(A35<=$B$10,1/$B$10,0) -> 0 | T35: =F34*M34*S35 -> 0 | U35: =F35*M35*$B$5*Q35 -> 0.45951374 | V35: =M35/M34 -> 1.0008804 | W35: =(1-V35)*(1+G35-$B$4)/(V35*$B$5) -> -0.0010866854 | X35: =G35/$B$5 -> 0.035439638 | Y35: =W35 -> -0.0010866854 | Z35: =U35*(Y35-$E$9) -> -0.0029577454 | AA35: =MAX(0,MIN(1,(B35-$E$4)/$B$5)) -> 0 | AB35: =Z35*AA35 -> 0 | AC35: =Z35-AB35 -> -0.0029577454 | AD35: =Q35*$B$5 -> 0.48913043 | AE35: =AD35*AA35 -> 0 | AF35: =F35*(M35*((G35+$E$9*$B$5)*Q35+R35)+$B$4*(M34-M35)*Q35) -> 0.038842884 | AG35: =S35 -> 0 | AH35: =IF(E35=1,ABS(P35-D35)*10000,0) -> 1.5677563e-12
A36: 5 | B36: =A36/2 -> 2.5 | C36: =ROUNDUP(A36/2,0) -> 3 | D36: =INDEX(Curves!$E$5:$E$34,C36)/10000 -> -0.0014 | E36: =IF(C36<=$B$6,1,0) -> 1 | F36: =Curves!W10 -> 0.91890677 | G36: =Curves!X10 -> 0.017414459 | H36: =N35+D36*O35 -> 0.060742305 | I36: =F37*M35*((G37+D36*$B$5+1)-$B$4) -> 0.5597088 | J36: =M35*(F36*((G36+D36*$B$5)-$B$4)+F37*$B$4) -> 0.0091117304 | K36: =H36+F36*M35*$B$4-1 -> -0.56990957 | L36: =IF(E36=1,-2*LN((-J36+SQRT(J36^2-4*I36*K36))/(2*I36)),L35) -> -0.0019281479 | M36: =M35*EXP(-L36*$B$5) -> 1.0058267 | N36: =N35+F36*(M36*G36+$B$4*(M35-M36)) -> 0.079178297 | O36: =O35+F36*M36*$B$5 -> 2.3883712 | Q36: =IF(A36<=$B$9,MIN(A36,$B$10)/$B$10-MAX(0,MIN(A36-1,$B$9)-$B$7)/$B$8,0) -> 0.95652174 | R36: =IF(AND(A36>$B$7,A36<=$B$9),1/$B$8,0) -> 0.02173913 | S36: =IF(A36<=$B$10,1/$B$10,0) -> 0 | T36: =F35*M35*S36 -> 0 | U36: =F36*M36*$B$5*Q36 -> 0.44203785 | V36: =M36/M35 -> 1.0009645 | W36: =(1-V36)*(1+G36-$B$4)/(V36*$B$5) -> -0.0011898927 | X36: =G36/$B$5 -> 0.034828919 | Y36: =W36 -> -0.0011898927 | Z36: =U36*(Y36-$E$9) -> -0.0028908801 | AA36: =MAX(0,MIN(1,(B36-$E$4)/$B$5)) -> 0 | AB36: =Z36*AA36 -> 0 | AC36: =Z36-AB36 -> -0.0028908801 | AD36: =Q36*$B$5 -> 0.47826087 | AE36: =AD36*AA36 -> 0 | AF36: =F36*(M36*((G36+$E$9*$B$5)*Q36+R36)+$B$4*(M35-M36)*Q36) -> 0.037512471 | AG36: =S36 -> 0 | AH36: 0
A37: 6 | B37: =A37/2 -> 3 | C37: =ROUNDUP(A37/2,0) -> 3 | D37: =INDEX(Curves!$E$5:$E$34,C37)/10000 -> -0.0014 | E37: =IF(C37<=$B$6,1,0) -> 1 | F37: =Curves!W11 -> 0.90317841 | G37: =Curves!X11 -> 0.017414459 | L37: =L36 -> -0.0019281479 | M37: =M36*EXP(-L37*$B$5) -> 1.0067968 | N37: =N36+F37*(M37*G37+$B$4*(M36-M37)) -> 0.094663073 | O37: =O36+F37*M37*$B$5 -> 2.8430298 | P37: =IF(E37=1,(1-N37-F37*M37)/O37,"") -> -0.0014 | Q37: =IF(A37<=$B$9,MIN(A37,$B$10)/$B$10-MAX(0,MIN(A37-1,$B$9)-$B$7)/$B$8,0) -> 0.93478261 | R37: =IF(AND(A37>$B$7,A37<=$B$9),1/$B$8,0) -> 0.02173913 | S37: =IF(A37<=$B$10,1/$B$10,0) -> 0 | T37: =F36*M36*S37 -> 0 | U37: =F37*M37*$B$5*Q37 -> 0.42500694 | V37: =M37/M36 -> 1.0009645 | W37: =(1-V37)*(1+G37-$B$4)/(V37*$B$5) -> -0.0011898927 | X37: =G37/$B$5 -> 0.034828919 | Y37: =W37 -> -0.0011898927 | Z37: =U37*(Y37-$E$9) -> -0.0027794998 | AA37: =MAX(0,MIN(1,(B37-$E$4)/$B$5)) -> 0 | AB37: =Z37*AA37 -> 0 | AC37: =Z37-AB37 -> -0.0027794998 | AD37: =Q37*$B$5 -> 0.4673913 | AE37: =AD37*AA37 -> 0 | AF37: =F37*(M37*((G37+$E$9*$B$5)*Q37+R37)+$B$4*(M36-M37)*Q37) -> 0.036516451 | AG37: =S37 -> 0 | AH37: =IF(E37=1,ABS(P37-D37)*10000,0) -> 1.1752752e-12
A38: 7 | B38: =A38/2 -> 3.5 | C38: =ROUNDUP(A38/2,0) -> 4 | D38: =INDEX(Curves!$E$5:$E$34,C38)/10000 -> -0.0002 | E38: =IF(C38<=$B$6,1,0) -> 1 | F38: =Curves!W12 -> 0.88817134 | G38: =Curves!X12 -> 0.016896594 | H38: =N37+D38*O37 -> 0.094094467 | I38: =F39*M37*((G39+D38*$B$5+1)-$B$4) -> 0.54238013 | J38: =M37*(F38*((G38+D38*$B$5)-$B$4)+F39*$B$4) -> 0.009076442 | K38: =H38+F38*M37*$B$4-1 -> -0.54822229 | L38: =IF(E38=1,-2*LN((-J38+SQRT(J38^2-4*I38*K38))/(2*I38)),L37) -> 0.0059311247 | M38: =M37*EXP(-L38*$B$5) -> 1.0038155 | N38: =N37+F38*(M38*G38+$B$4*(M37-M38)) -> 0.11078656 | O38: =O37+F38*M38*$B$5 -> 3.2888099 | Q38: =IF(A38<=$B$9,MIN(A38,$B$10)/$B$10-MAX(0,MIN(A38-1,$B$9)-$B$7)/$B$8,0) -> 0.91304348 | R38: =IF(AND(A38>$B$7,A38<=$B$9),1/$B$8,0) -> 0.02173913 | S38: =IF(A38<=$B$10,1/$B$10,0) -> 0 | T38: =F37*M37*S38 -> 0 | U38: =F38*M38*$B$5*Q38 -> 0.40701661 | V38: =M38/M37 -> 0.99703883 | W38: =(1-V38)*(1+G38-$B$4)/(V38*$B$5) -> 0.0036643213 | X38: =G38/$B$5 -> 0.033793189 | Y38: =W38 -> 0.0036643213 | Z38: =U38*(Y38-$E$9) -> -0.00068609922 | AA38: =MAX(0,MIN(1,(B38-$E$4)/$B$5)) -> 0 | AB38: =Z38*AA38 -> 0 | AC38: =Z38-AB38 -> -0.00068609922 | AD38: =Q38*$B$5 -> 0.45652174 | AE38: =AD38*AA38 -> 0 | AF38: =F38*(M38*((G38+$E$9*$B$5)*Q38+R38)+$B$4*(M37-M38)*Q38) -> 0.036280731 | AG38: =S38 -> 0 | AH38: 0
A39: 8 | B39: =A39/2 -> 4 | C39: =ROUNDUP(A39/2,0) -> 4 | D39: =INDEX(Curves!$E$5:$E$34,C39)/10000 -> -0.0002 | E39: =IF(C39<=$B$6,1,0) -> 1 | F39: =Curves!W13 -> 0.87341362 | G39: =Curves!X13 -> 0.016896594 | L39: =L38 -> 0.0059311247 | M39: =M38*EXP(-L39*$B$5) -> 1.0008431 | N39: =N38+F39*(M39*G39+$B$4*(M38-M39)) -> 0.1265952 | O39: =O38+F39*M39*$B$5 -> 3.7258849 | P39: =IF(E39=1,(1-N39-F39*M39)/O39,"") -> -0.0002 | Q39: =IF(A39<=$B$9,MIN(A39,$B$10)/$B$10-MAX(0,MIN(A39-1,$B$9)-$B$7)/$B$8,0) -> 0.89130435 | R39: =IF(AND(A39>$B$7,A39<=$B$9),1/$B$8,0) -> 0.02173913 | S39: =IF(A39<=$B$10,1/$B$10,0) -> 0 | T39: =F38*M38*S39 -> 0 | U39: =F39*M39*$B$5*Q39 -> 0.38956684 | V39: =M39/M38 -> 0.99703883 | W39: =(1-V39)*(1+G39-$B$4)/(V39*$B$5) -> 0.0036643213 | X39: =G39/$B$5 -> 0.033793189 | Y39: =W39 -> 0.0036643213 | Z39: =U39*(Y39-$E$9) -> -0.00065668451 | AA39: =MAX(0,MIN(1,(B39-$E$4)/$B$5)) -> 0 | AB39: =Z39*AA39 -> 0 | AC39: =Z39-AB39 -> -0.00065668451 | AD39: =Q39*$B$5 -> 0.44565217 | AE39: =AD39*AA39 -> 0 | AF39: =F39*(M39*((G39+$E$9*$B$5)*Q39+R39)+$B$4*(M38-M39)*Q39) -> 0.035177748 | AG39: =S39 -> 0 | AH39: =IF(E39=1,ABS(P39-D39)*10000,0) -> 1.6344348e-13
A40: 9 | B40: =A40/2 -> 4.5 | C40: =ROUNDUP(A40/2,0) -> 5 | D40: =INDEX(Curves!$E$5:$E$34,C40)/10000 -> 0.0006 | E40: =IF(C40<=$B$6,1,0) -> 1 | F40: =Curves!W14 -> 0.85876771 | G40: =Curves!X14 -> 0.017054571 | H40: =N39+D40*O39 -> 0.12883073 | I40: =F41*M39*((G41+D40*$B$5+1)-$B$4) -> 0.52171354 | J40: =M39*(F40*((G40+D40*$B$5)-$B$4)+F41*$B$4) -> 0.0091511243 | K40: =H40+F40*M39*$B$4-1 -> -0.52737258 | L40: =IF(E40=1,-2*LN((-J40+SQRT(J40^2-4*I40*K40))/(2*I40)),L39) -> 0.0066573017 | M40: =M39*EXP(-L40*$B$5) -> 0.99751716 | N40: =N39+F40*(M40*G40+$B$4*(M39-M40)) -> 0.14234723 | O40: =O39+F40*M40*$B$5 -> 4.1542026 | Q40: =IF(A40<=$B$9,MIN(A40,$B$10)/$B$10-MAX(0,MIN(A40-1,$B$9)-$B$7)/$B$8,0) -> 0.86956522 | R40: =IF(AND(A40>$B$7,A40<=$B$9),1/$B$8,0) -> 0.02173913 | S40: =IF(A40<=$B$10,1/$B$10,0) -> 0 | T40: =F39*M39*S40 -> 0 | U40: =F40*M40*$B$5*Q40 -> 0.37245023 | V40: =M40/M39 -> 0.99667688 | W40: =(1-V40)*(1+G40-$B$4)/(V40*$B$5) -> 0.0041147629 | X40: =G40/$B$5 -> 0.034109142 | Y40: =W40 -> 0.0041147629 | Z40: =U40*(Y40-$E$9) -> -0.00046006433 | AA40: =MAX(0,MIN(1,(B40-$E$4)/$B$5)) -> 0 | AB40: =Z40*AA40 -> 0 | AC40: =Z40-AB40 -> -0.00046006433 | AD40: =Q40*$B$5 -> 0.43478261 | AE40: =AD40*AA40 -> 0 | AF40: =F40*(M40*((G40+$E$9*$B$5)*Q40+R40)+$B$4*(M39-M40)*Q40) -> 0.034312536 | AG40: =S40 -> 0 | AH40: 0
A41: 10 | B41: =A41/2 -> 5 | C41: =ROUNDUP(A41/2,0) -> 5 | D41: =INDEX(Curves!$E$5:$E$34,C41)/10000 -> 0.0006 | E41: =IF(C41<=$B$6,1,0) -> 1 | F41: =Curves!W15 -> 0.84436739 | G41: =Curves!X15 -> 0.017054571 | L41: =L40 -> 0.0066573017 | M41: =M40*EXP(-L41*$B$5) -> 0.99420229 | N41: =N40+F41*(M41*G41+$B$4*(M40-M41)) -> 0.15778365 | O41: =O40+F41*M41*$B$5 -> 4.5739386 | P41: =IF(E41=1,(1-N41-F41*M41)/O41,"") -> 0.0006 | Q41: =IF(A41<=$B$9,MIN(A41,$B$10)/$B$10-MAX(0,MIN(A41-1,$B$9)-$B$7)/$B$8,0) -> 0.84782609 | R41: =IF(AND(A41>$B$7,A41<=$B$9),1/$B$8,0) -> 0.02173913 | S41: =IF(A41<=$B$10,1/$B$10,0) -> 0 | T41: =F40*M40*S41 -> 0 | U41: =F41*M41*$B$5*Q41 -> 0.35586313 | V41: =M41/M40 -> 0.99667688 | W41: =(1-V41)*(1+G41-$B$4)/(V41*$B$5) -> 0.0041147629 | X41: =G41/$B$5 -> 0.034109142 | Y41: =W41 -> 0.0041147629 | Z41: =U41*(Y41-$E$9) -> -0.00043957533 | AA41: =MAX(0,MIN(1,(B41-$E$4)/$B$5)) -> 0 | AB41: =Z41*AA41 -> 0 | AC41: =Z41-AB41 -> -0.00043957533 | AD41: =Q41*$B$5 -> 0.42391304 | AE41: =AD41*AA41 -> 0 | AF41: =F41*(M41*((G41+$E$9*$B$5)*Q41+R41)+$B$4*(M40-M41)*Q41) -> 0.033240659 | AG41: =S41 -> 0 | AH41: =IF(E41=1,ABS(P41-D41)*10000,0) -> 5.2041704e-14
A42: 11 | B42: =A42/2 -> 5.5 | C42: =ROUNDUP(A42/2,0) -> 6 | D42: =INDEX(Curves!$E$5:$E$34,C42)/10000 -> 0.0013 | E42: =IF(C42<=$B$6,1,0) -> 1 | F42: =Curves!W16 -> 0.83020854 | G42: =Curves!X16 -> 0.017054571 | H42: =N41+D42*O41 -> 0.16372977 | I42: =F43*M41*((G43+D42*$B$5+1)-$B$4) -> 0.50130093 | J42: =M41*(F42*((G42+D42*$B$5)-$B$4)+F43*$B$4) -> 0.0090769827 | K42: =H42+F42*M41*$B$4-1 -> -0.50611214 | L42: =IF(E42=1,-2*LN((-J42+SQRT(J42^2-4*I42*K42))/(2*I42)),L41) -> 0.0084686582 | M42: =M41*EXP(-L42*$B$5) -> 0.99000141 | N42: =N41+F42*(M42*G42+$B$4*(M41-M42)) -> 0.17319597 | O42: =O41+F42*M42*$B$5 -> 4.9848924 | Q42: =IF(A42<=$B$9,MIN(A42,$B$10)/$B$10-MAX(0,MIN(A42-1,$B$9)-$B$7)/$B$8,0) -> 0.82608696 | R42: =IF(AND(A42>$B$7,A42<=$B$9),1/$B$8,0) -> 0.02173913 | S42: =IF(A42<=$B$10,1/$B$10,0) -> 0 | T42: =F41*M41*S42 -> 0 | U42: =F42*M42*$B$5*Q42 -> 0.33948358 | V42: =M42/M41 -> 0.99577462 | W42: =(1-V42)*(1+G42-$B$4)/(V42*$B$5) -> 0.0052367034 | X42: =G42/$B$5 -> 0.034109142 | Y42: =W42 -> 0.0052367034 | Z42: =U42*(Y42-$E$9) -> -3.8462339e-05 | AA42: =MAX(0,MIN(1,(B42-$E$4)/$B$5)) -> 0 | AB42: =Z42*AA42 -> 0 | AC42: =Z42-AB42 -> -3.8462339e-05 | AD42: =Q42*$B$5 -> 0.41304348 | AE42: =AD42*AA42 -> 0 | AF42: =F42*(M42*((G42+$E$9*$B$5)*Q42+R42)+$B$4*(M41-M42)*Q42) -> 0.032415714 | AG42: =S42 -> 0 | AH42: 0
A43: 12 | B43: =A43/2 -> 6 | C43: =ROUNDUP(A43/2,0) -> 6 | D43: =INDEX(Curves!$E$5:$E$34,C43)/10000 -> 0.0013 | E43: =IF(C43<=$B$6,1,0) -> 1 | F43: =Curves!W17 -> 0.81628711 | G43: =Curves!X17 -> 0.017054571 | L43: =L42 -> 0.0084686582 | M43: =M42*EXP(-L43*$B$5) -> 0.98581828 | N43: =N42+F43*(M43*G43+$B$4*(M42-M43)) -> 0.18828582 | O43: =O42+F43*M43*$B$5 -> 5.3872478 | P43: =IF(E43=1,(1-N43-F43*M43)/O43,"") -> 0.0013 | Q43: =IF(A43<=$B$9,MIN(A43,$B$10)/$B$10-MAX(0,MIN(A43-1,$B$9)-$B$7)/$B$8,0) -> 0.80434783 | R43: =IF(AND(A43>$B$7,A43<=$B$9),1/$B$8,0) -> 0.02173913 | S43: =IF(A43<=$B$10,1/$B$10,0) -> 0 | T43: =F42*M42*S43 -> 0 | U43: =F43*M43*$B$5*Q43 -> 0.32363367 | V43: =M43/M42 -> 0.99577462 | W43: =(1-V43)*(1+G43-$B$4)/(V43*$B$5) -> 0.0052367034 | X43: =G43/$B$5 -> 0.034109142 | Y43: =W43 -> 0.0052367034 | Z43: =U43*(Y43-$E$9) -> -3.6666598e-05 | AA43: =MAX(0,MIN(1,(B43-$E$4)/$B$5)) -> 0 | AB43: =Z43*AA43 -> 0 | AC43: =Z43-AB43 -> -3.6666598e-05 | AD43: =Q43*$B$5 -> 0.40217391 | AE43: =AD43*AA43 -> 0 | AF43: =F43*(M43*((G43+$E$9*$B$5)*Q43+R43)+$B$4*(M42-M43)*Q43) -> 0.031362641 | AG43: =S43 -> 0 | AH43: =IF(E43=1,ABS(P43-D43)*10000,0) -> 2.1467203e-13
A44: 13 | B44: =A44/2 -> 6.5 | C44: =ROUNDUP(A44/2,0) -> 7 | D44: =INDEX(Curves!$E$5:$E$34,C44)/10000 -> 0.0024 | E44: =IF(C44<=$B$6,1,0) -> 1 | F44: =Curves!W18 -> 0.80259913 | G44: =Curves!X18 -> 0.017054571 | H44: =N43+D44*O43 -> 0.20121522 | I44: =F45*M43*((G45+D44*$B$5+1)-$B$4) -> 0.48097071 | J44: =M43*(F44*((G44+D44*$B$5)-$B$4)+F45*$B$4) -> 0.0091362882 | K44: =H44+F44*M43*$B$4-1 -> -0.48229803 | L44: =IF(E44=1,-2*LN((-J44+SQRT(J44^2-4*I44*K44))/(2*I44)),L43) -> 0.016213218 | M44: =M43*EXP(-L44*$B$5) -> 0.97785894 | N44: =N43+F44*(M44*G44+$B$4*(M43-M44)) -> 0.204226 | O44: =O43+F44*M44*$B$5 -> 5.7796622 | Q44: =IF(A44<=$B$9,MIN(A44,$B$10)/$B$10-MAX(0,MIN(A44-1,$B$9)-$B$7)/$B$8,0) -> 0.7826087 | R44: =IF(AND(A44>$B$7,A44<=$B$9),1/$B$8,0) -> 0.02173913 | S44: =IF(A44<=$B$10,1/$B$10,0) -> 0 | T44: =F43*M43*S44 -> 0 | U44: =F44*M44*$B$5*Q44 -> 0.3071069 | V44: =M44/M43 -> 0.99192616 | W44: =(1-V44)*(1+G44-$B$4)/(V44*$B$5) -> 0.010045101 | X44: =G44/$B$5 -> 0.034109142 | Y44: =W44 -> 0.010045101 | Z44: =U44*(Y44-$E$9) -> 0.0014418979 | AA44: =MAX(0,MIN(1,(B44-$E$4)/$B$5)) -> 0 | AB44: =Z44*AA44 -> 0 | AC44: =Z44-AB44 -> 0.0014418979 | AD44: =Q44*$B$5 -> 0.39130435 | AE44: =AD44*AA44 -> 0 | AF44: =F44*(M44*((G44+$E$9*$B$5)*Q44+R44)+$B$4*(M43-M44)*Q44) -> 0.03117944 | AG44: =S44 -> 0 | AH44: 0
A45: 14 | B45: =A45/2 -> 7 | C45: =ROUNDUP(A45/2,0) -> 7 | D45: =INDEX(Curves!$E$5:$E$34,C45)/10000 -> 0.0024 | E45: =IF(C45<=$B$6,1,0) -> 1 | F45: =Curves!W19 -> 0.78914067 | G45: =Curves!X19 -> 0.017054571 | L45: =L44 -> 0.016213218 | M45: =M44*EXP(-L45*$B$5) -> 0.96996387 | N45: =N44+F45*(M45*G45+$B$4*(M44-M45)) -> 0.21977235 | O45: =O44+F45*M45*$B$5 -> 6.1623812 | P45: =IF(E45=1,(1-N45-F45*M45)/O45,"") -> 0.0024 | Q45: =IF(A45<=$B$9,MIN(A45,$B$10)/$B$10-MAX(0,MIN(A45-1,$B$9)-$B$7)/$B$8,0) -> 0.76086957 | R45: =IF(AND(A45>$B$7,A45<=$B$9),1/$B$8,0) -> 0.02173913 | S45: =IF(A45<=$B$10,1/$B$10,0) -> 0 | T45: =F44*M44*S45 -> 0 | U45: =F45*M45*$B$5*Q45 -> 0.29119922 | V45: =M45/M44 -> 0.99192616 | W45: =(1-V45)*(1+G45-$B$4)/(V45*$B$5) -> 0.010045101 | X45: =G45/$B$5 -> 0.034109142 | Y45: =W45 -> 0.010045101 | Z45: =U45*(Y45-$E$9) -> 0.0013672097 | AA45: =MAX(0,MIN(1,(B45-$E$4)/$B$5)) -> 0 | AB45: =Z45*AA45 -> 0 | AC45: =Z45-AB45 -> 0.0013672097 | AD45: =Q45*$B$5 -> 0.38043478 | AE45: =AD45*AA45 -> 0 | AF45: =F45*(M45*((G45+$E$9*$B$5)*Q45+R45)+$B$4*(M44-M45)*Q45) -> 0.030026612 | AG45: =S45 -> 0 | AH45: =IF(E45=1,ABS(P45-D45)*10000,0) -> 2.2117724e-13
A46: 15 | B46: =A46/2 -> 7.5 | C46: =ROUNDUP(A46/2,0) -> 8 | D46: =INDEX(Curves!$E$5:$E$34,C46)/10000 -> 0.003 | E46: =IF(C46<=$B$6,1,0) -> 1 | F46: =Curves!W20 -> 0.77556901 | G46: =Curves!X20 -> 0.017498978 | H46: =N45+D46*O45 -> 0.23825949 | I46: =F47*M45*((G47+D46*$B$5+1)-$B$4) -> 0.4576484 | J46: =M45*(F46*((G46+D46*$B$5)-$B$4)+F47*$B$4) -> 0.0091173837 | K46: =H46+F46*M45*$B$4-1 -> -0.46083094 | L46: =IF(E46=1,-2*LN((-J46+SQRT(J46^2-4*I46*K46))/(2*I46)),L45) -> 0.012922961 | M46: =M45*EXP(-L46*$B$5) -> 0.96371667 | N46: =N45+F46*(M46*G46+$B$4*(M45-M46)) -> 0.23478964 | O46: =O45+F46*M46*$B$5 -> 6.5360955 | Q46: =IF(A46<=$B$9,MIN(A46,$B$10)/$B$10-MAX(0,MIN(A46-1,$B$9)-$B$7)/$B$8,0) -> 0.73913043 | R46: =IF(AND(A46>$B$7,A46<=$B$9),1/$B$8,0) -> 0.02173913 | S46: =IF(A46<=$B$10,1/$B$10,0) -> 0 | T46: =F45*M45*S46 -> 0 | U46: =F46*M46*$B$5*Q46 -> 0.27622368 | V46: =M46/M45 -> 0.99355935 | W46: =(1-V46)*(1+G46-$B$4)/(V46*$B$5) -> 0.0080057517 | X46: =G46/$B$5 -> 0.034997956 | Y46: =W46 -> 0.0080057517 | Z46: =U46*(Y46-$E$9) -> 0.0007335815 | AA46: =MAX(0,MIN(1,(B46-$E$4)/$B$5)) -> 0 | AB46: =Z46*AA46 -> 0 | AC46: =Z46-AB46 -> 0.0007335815 | AD46: =Q46*$B$5 -> 0.36956522 | AE46: =AD46*AA46 -> 0 | AF46: =F46*(M46*((G46+$E$9*$B$5)*Q46+R46)+$B$4*(M45-M46)*Q46) -> 0.028825987 | AG46: =S46 -> 0 | AH46: 0
A47: 16 | B47: =A47/2 -> 8 | C47: =ROUNDUP(A47/2,0) -> 8 | D47: =INDEX(Curves!$E$5:$E$34,C47)/10000 -> 0.003 | E47: =IF(C47<=$B$6,1,0) -> 1 | F47: =Curves!W21 -> 0.76223075 | G47: =Curves!X21 -> 0.017498978 | L47: =L46 -> 0.012922961 | M47: =M46*EXP(-L47*$B$5) -> 0.95750971 | N47: =N46+F47*(M47*G47+$B$4*(M46-M47)) -> 0.24945361 | O47: =O46+F47*M47*$B$5 -> 6.9010172 | P47: =IF(E47=1,(1-N47-F47*M47)/O47,"") -> 0.003 | Q47: =IF(A47<=$B$9,MIN(A47,$B$10)/$B$10-MAX(0,MIN(A47-1,$B$9)-$B$7)/$B$8,0) -> 0.7173913 | R47: =IF(AND(A47>$B$7,A47<=$B$9),1/$B$8,0) -> 0.02173913 | S47: =IF(A47<=$B$10,1/$B$10,0) -> 0 | T47: =F46*M46*S47 -> 0 | U47: =F47*M47*$B$5*Q47 -> 0.26179163 | V47: =M47/M46 -> 0.99355935 | W47: =(1-V47)*(1+G47-$B$4)/(V47*$B$5) -> 0.0080057517 | X47: =G47/$B$5 -> 0.034997956 | Y47: =W47 -> 0.0080057517 | Z47: =U47*(Y47-$E$9) -> 0.00069525357 | AA47: =MAX(0,MIN(1,(B47-$E$4)/$B$5)) -> 0 | AB47: =Z47*AA47 -> 0 | AC47: =Z47-AB47 -> 0.00069525357 | AD47: =Q47*$B$5 -> 0.35869565 | AE47: =AD47*AA47 -> 0 | AF47: =F47*(M47*((G47+$E$9*$B$5)*Q47+R47)+$B$4*(M46-M47)*Q47) -> 0.027786547 | AG47: =S47 -> 0 | AH47: =IF(E47=1,ABS(P47-D47)*10000,0) -> 1.474515e-13
A48: 17 | B48: =A48/2 -> 8.5 | C48: =ROUNDUP(A48/2,0) -> 9 | D48: =INDEX(Curves!$E$5:$E$34,C48)/10000 -> 0.0037 | E48: =IF(C48<=$B$6,1,0) -> 1 | F48: =Curves!W22 -> 0.74903791 | G48: =Curves!X22 -> 0.017613041 | H48: =N47+D48*O47 -> 0.27498737 | I48: =F49*M47*((G49+D48*$B$5+1)-$B$4) -> 0.43659597 | J48: =M47*(F48*((G48+D48*$B$5)-$B$4)+F49*$B$4) -> 0.0089936579 | K48: =H48+F48*M47*$B$4-1 -> -0.4381282 | L48: =IF(E48=1,-2*LN((-J48+SQRT(J48^2-4*I48*K48))/(2*I48)),L47) -> 0.017059736 | M48: =M47*EXP(-L48*$B$5) -> 0.94937701 | N48: =N47+F48*(M48*G48+$B$4*(M47-M48)) -> 0.26441526 | O48: =O47+F48*M48*$B$5 -> 7.2565769 | Q48: =IF(A48<=$B$9,MIN(A48,$B$10)/$B$10-MAX(0,MIN(A48-1,$B$9)-$B$7)/$B$8,0) -> 0.69565217 | R48: =IF(AND(A48>$B$7,A48<=$B$9),1/$B$8,0) -> 0.02173913 | S48: =IF(A48<=$B$10,1/$B$10,0) -> 0 | T48: =F47*M47*S48 -> 0 | U48: =F48*M48*$B$5*Q48 -> 0.24734587 | V48: =M48/M47 -> 0.99150641 | W48: =(1-V48)*(1+G48-$B$4)/(V48*$B$5) -> 0.01058138 | X48: =G48/$B$5 -> 0.035226082 | Y48: =W48 -> 0.01058138 | Z48: =U48*(Y48-$E$9) -> 0.0012939602 | AA48: =MAX(0,MIN(1,(B48-$E$4)/$B$5)) -> 0 | AB48: =Z48*AA48 -> 0 | AC48: =Z48-AB48 -> 0.0012939602 | AD48: =Q48*$B$5 -> 0.34782609 | AE48: =AD48*AA48 -> 0 | AF48: =F48*(M48*((G48+$E$9*$B$5)*Q48+R48)+$B$4*(M47-M48)*Q48) -> 0.027190524 | AG48: =S48 -> 0 | AH48: 0
A49: 18 | B49: =A49/2 -> 9 | C49: =ROUNDUP(A49/2,0) -> 9 | D49: =INDEX(Curves!$E$5:$E$34,C49)/10000 -> 0.0037 | E49: =IF(C49<=$B$6,1,0) -> 1 | F49: =Curves!W23 -> 0.73607342 | G49: =Curves!X23 -> 0.017613041 | L49: =L48 -> 0.017059736 | M49: =M48*EXP(-L49*$B$5) -> 0.94131339 | N49: =N48+F49*(M49*G49+$B$4*(M48-M49)) -> 0.27899308 | O49: =O48+F49*M49*$B$5 -> 7.6030148 | P49: =IF(E49=1,(1-N49-F49*M49)/O49,"") -> 0.0037 | Q49: =IF(A49<=$B$9,MIN(A49,$B$10)/$B$10-MAX(0,MIN(A49-1,$B$9)-$B$7)/$B$8,0) -> 0.67391304 | R49: =IF(AND(A49>$B$7,A49<=$B$9),1/$B$8,0) -> 0.02173913 | S49: =IF(A49<=$B$10,1/$B$10,0) -> 0 | T49: =F48*M48*S49 -> 0 | U49: =F49*M49*$B$5*Q49 -> 0.23346901 | V49: =M49/M48 -> 0.99150641 | W49: =(1-V49)*(1+G49-$B$4)/(V49*$B$5) -> 0.01058138 | X49: =G49/$B$5 -> 0.035226082 | Y49: =W49 -> 0.01058138 | Z49: =U49*(Y49-$E$9) -> 0.0012213651 | AA49: =MAX(0,MIN(1,(B49-$E$4)/$B$5)) -> 0 | AB49: =Z49*AA49 -> 0 | AC49: =Z49-AB49 -> 0.0012213651 | AD49: =Q49*$B$5 -> 0.33695652 | AE49: =AD49*AA49 -> 0 | AF49: =F49*(M49*((G49+$E$9*$B$5)*Q49+R49)+$B$4*(M48-M49)*Q49) -> 0.026135756 | AG49: =S49 -> 0 | AH49: =IF(E49=1,ABS(P49-D49)*10000,0) -> 2.3418767e-13
A50: 19 | B50: =A50/2 -> 9.5 | C50: =ROUNDUP(A50/2,0) -> 10 | D50: =INDEX(Curves!$E$5:$E$34,C50)/10000 -> 0.0042 | E50: =IF(C50<=$B$6,1,0) -> 1 | F50: =Curves!W24 -> 0.72325054 | G50: =Curves!X24 -> 0.017729519 | H50: =N49+D50*O49 -> 0.31092574 | I50: =F51*M49*((G51+D50*$B$5+1)-$B$4) -> 0.41463207 | J50: =M49*(F50*((G50+D50*$B$5)-$B$4)+F51*$B$4) -> 0.0087560121 | K50: =H50+F50*M49*$B$4-1 -> -0.41675209 | L50: =IF(E50=1,-2*LN((-J50+SQRT(J50^2-4*I50*K50))/(2*I50)),L49) -> 0.015963369 | M50: =M49*EXP(-L50*$B$5) -> 0.93383003 | N50: =N49+F50*(M50*G50+$B$4*(M49-M50)) -> 0.29313241 | O50: =O49+F50*M50*$B$5 -> 7.9407113 | Q50: =IF(A50<=$B$9,MIN(A50,$B$10)/$B$10-MAX(0,MIN(A50-1,$B$9)-$B$7)/$B$8,0) -> 0.65217391 | R50: =IF(AND(A50>$B$7,A50<=$B$9),1/$B$8,0) -> 0.02173913 | S50: =IF(A50<=$B$10,1/$B$10,0) -> 0 | T50: =F49*M49*S50 -> 0 | U50: =F50*M50*$B$5*Q50 -> 0.22023687 | V50: =M50/M49 -> 0.99205008 | W50: =(1-V50)*(1+G50-$B$4)/(V50*$B$5) -> 0.0099005029 | X50: =G50/$B$5 -> 0.035459037 | Y50: =W50 -> 0.0099005029 | Z50: =U50*(Y50-$E$9) -> 0.0010021885 | AA50: =MAX(0,MIN(1,(B50-$E$4)/$B$5)) -> 0 | AB50: =Z50*AA50 -> 0 | AC50: =Z50-AB50 -> 0.0010021885 | AD50: =Q50*$B$5 -> 0.32608696 | AE50: =AD50*AA50 -> 0 | AF50: =F50*(M50*((G50+$E$9*$B$5)*Q50+R50)+$B$4*(M49-M50)*Q50) -> 0.025082029 | AG50: =S50 -> 0 | AH50: 0
A51: 20 | B51: =A51/2 -> 10 | C51: =ROUNDUP(A51/2,0) -> 10 | D51: =INDEX(Curves!$E$5:$E$34,C51)/10000 -> 0.0042 | E51: =IF(C51<=$B$6,1,0) -> 1 | F51: =Curves!W25 -> 0.71065104 | G51: =Curves!X25 -> 0.017729519 | L51: =L50 -> 0.015963369 | M51: =M50*EXP(-L51*$B$5) -> 0.92640616 | N51: =N50+F51*(M51*G51+$B$4*(M50-M51)) -> 0.30691498 | O51: =O50+F51*M51*$B$5 -> 8.2698871 | P51: =IF(E51=1,(1-N51-F51*M51)/O51,"") -> 0.0042 | Q51: =IF(A51<=$B$9,MIN(A51,$B$10)/$B$10-MAX(0,MIN(A51-1,$B$9)-$B$7)/$B$8,0) -> 0.63043478 | R51: =IF(AND(A51>$B$7,A51<=$B$9),1/$B$8,0) -> 0.02173913 | S51: =IF(A51<=$B$10,1/$B$10,0) -> 0 | T51: =F50*M50*S51 -> 0 | U51: =F51*M51*$B$5*Q51 -> 0.20752384 | V51: =M51/M50 -> 0.99205008 | W51: =(1-V51)*(1+G51-$B$4)/(V51*$B$5) -> 0.0099005029 | X51: =G51/$B$5 -> 0.035459037 | Y51: =W51 -> 0.0099005029 | Z51: =U51*(Y51-$E$9) -> 0.00094433784 | AA51: =MAX(0,MIN(1,(B51-$E$4)/$B$5)) -> 0 | AB51: =Z51*AA51 -> 0 | AC51: =Z51-AB51 -> 0.00094433784 | AD51: =Q51*$B$5 -> 0.31521739 | AE51: =AD51*AA51 -> 0 | AF51: =F51*(M51*((G51+$E$9*$B$5)*Q51+R51)+$B$4*(M50-M51)*Q51) -> 0.024111251 | AG51: =S51 -> 0 | AH51: =IF(E51=1,ABS(P51-D51)*10000,0) -> 1.7347235e-13
A52: 21 | B52: =A52/2 -> 10.5 | C52: =ROUNDUP(A52/2,0) -> 11 | D52: =INDEX(Curves!$E$5:$E$34,C52)/10000 -> 0.0046 | E52: =IF(C52<=$B$6,1,0) -> 1 | F52: =Curves!W26 -> 0.69827814 | G52: =Curves!X26 -> 0.017719145 | H52: =N51+D52*O51 -> 0.34495646 | I52: =F53*M51*((G53+D52*$B$5+1)-$B$4) -> 0.39410055 | J52: =M51*(F52*((G52+D52*$B$5)-$B$4)+F53*$B$4) -> 0.0084450657 | K52: =H52+F52*M51*$B$4-1 -> -0.39628787 | L52: =IF(E52=1,-2*LN((-J52+SQRT(J52^2-4*I52*K52))/(2*I52)),L51) -> 0.015834257 | M52: =M51*EXP(-L52*$B$5) -> 0.91910064 | N52: =N51+F52*(M52*G52+$B$4*(M51-M52)) -> 0.32032742 | O52: =O51+F52*M52*$B$5 -> 8.590781 | Q52: =IF(A52<=$B$9,MIN(A52,$B$10)/$B$10-MAX(0,MIN(A52-1,$B$9)-$B$7)/$B$8,0) -> 0.60869565 | R52: =IF(AND(A52>$B$7,A52<=$B$9),1/$B$8,0) -> 0.02173913 | S52: =IF(A52<=$B$10,1/$B$10,0) -> 0 | T52: =F51*M51*S52 -> 0 | U52: =F52*M52*$B$5*Q52 -> 0.19532675 | V52: =M52/M51 -> 0.99211413 | W52: =(1-V52)*(1+G52-$B$4)/(V52*$B$5) -> 0.0098199454 | X52: =G52/$B$5 -> 0.035438291 | Y52: =W52 -> 0.0098199454 | Z52: =U52*(Y52-$E$9) -> 0.0008730999 | AA52: =MAX(0,MIN(1,(B52-$E$4)/$B$5)) -> 0 | AB52: =Z52*AA52 -> 0 | AC52: =Z52-AB52 -> 0.0008730999 | AD52: =Q52*$B$5 -> 0.30434783 | AE52: =AD52*AA52 -> 0 | AF52: =F52*(M52*((G52+$E$9*$B$5)*Q52+R52)+$B$4*(M51-M52)*Q52) -> 0.023161007 | AG52: =S52 -> 0 | AH52: 0
A53: 22 | B53: =A53/2 -> 11 | C53: =ROUNDUP(A53/2,0) -> 11 | D53: =INDEX(Curves!$E$5:$E$34,C53)/10000 -> 0.0046 | E53: =IF(C53<=$B$6,1,0) -> 1 | F53: =Curves!W27 -> 0.68612067 | G53: =Curves!X27 -> 0.017719145 | L53: =L52 -> 0.015834257 | M53: =M52*EXP(-L53*$B$5) -> 0.91185273 | N53: =N52+F53*(M53*G53+$B$4*(M52-M53)) -> 0.33340242 | O53: =O52+F53*M53*$B$5 -> 8.9036015 | P53: =IF(E53=1,(1-N53-F53*M53)/O53,"") -> 0.0046 | Q53: =IF(A53<=$B$9,MIN(A53,$B$10)/$B$10-MAX(0,MIN(A53-1,$B$9)-$B$7)/$B$8,0) -> 0.58695652 | R53: =IF(AND(A53>$B$7,A53<=$B$9),1/$B$8,0) -> 0.02173913 | S53: =IF(A53<=$B$10,1/$B$10,0) -> 0 | T53: =F52*M52*S53 -> 0 | U53: =F53*M53*$B$5*Q53 -> 0.18361204 | V53: =M53/M52 -> 0.99211413 | W53: =(1-V53)*(1+G53-$B$4)/(V53*$B$5) -> 0.0098199454 | X53: =G53/$B$5 -> 0.035438291 | Y53: =W53 -> 0.0098199454 | Z53: =U53*(Y53-$E$9) -> 0.00082073577 | AA53: =MAX(0,MIN(1,(B53-$E$4)/$B$5)) -> 0 | AB53: =Z53*AA53 -> 0 | AC53: =Z53-AB53 -> 0.00082073577 | AD53: =Q53*$B$5 -> 0.29347826 | AE53: =AD53*AA53 -> 0 | AF53: =F53*(M53*((G53+$E$9*$B$5)*Q53+R53)+$B$4*(M52-M53)*Q53) -> 0.022257672 | AG53: =S53 -> 0 | AH53: =IF(E53=1,ABS(P53-D53)*10000,0) -> 3.469447e-14
A54: 23 | B54: =A54/2 -> 11.5 | C54: =ROUNDUP(A54/2,0) -> 12 | D54: =INDEX(Curves!$E$5:$E$34,C54)/10000 -> 0.0051 | E54: =IF(C54<=$B$6,1,0) -> 1 | F54: =Curves!W28 -> 0.67411049 | G54: =Curves!X28 -> 0.017816333 | H54: =N53+D54*O53 -> 0.37881079 | I54: =F55*M53*((G55+D54*$B$5+1)-$B$4) -> 0.37465764 | J54: =M53*(F54*((G54+D54*$B$5)-$B$4)+F55*$B$4) -> 0.008215046 | K54: =H54+F54*M53*$B$4-1 -> -0.37531341 | L54: =IF(E54=1,-2*LN((-J54+SQRT(J54^2-4*I54*K54))/(2*I54)),L53) -> 0.020158427 | M54: =M53*EXP(-L54*$B$5) -> 0.90270814 | N54: =N53+F54*(M54*G54+$B$4*(M53-M54)) -> 0.3467099 | O54: =O53+F54*M54*$B$5 -> 9.207864 | Q54: =IF(A54<=$B$9,MIN(A54,$B$10)/$B$10-MAX(0,MIN(A54-1,$B$9)-$B$7)/$B$8,0) -> 0.56521739 | R54: =IF(AND(A54>$B$7,A54<=$B$9),1/$B$8,0) -> 0.02173913 | S54: =IF(A54<=$B$10,1/$B$10,0) -> 0 | T54: =F53*M53*S54 -> 0 | U54: =F54*M54*$B$5*Q54 -> 0.17197446 | V54: =M54/M53 -> 0.98997141 | W54: =(1-V54)*(1+G54-$B$4)/(V54*$B$5) -> 0.012517181 | X54: =G54/$B$5 -> 0.035632666 | Y54: =W54 -> 0.012517181 | Z54: =U54*(Y54-$E$9) -> 0.0012325721 | AA54: =MAX(0,MIN(1,(B54-$E$4)/$B$5)) -> 0 | AB54: =Z54*AA54 -> 0 | AC54: =Z54-AB54 -> 0.0012325721 | AD54: =Q54*$B$5 -> 0.2826087 | AE54: =AD54*AA54 -> 0 | AF54: =F54*(M54*((G54+$E$9*$B$5)*Q54+R54)+$B$4*(M53-M54)*Q54) -> 0.021670483 | AG54: =S54 -> 0 | AH54: 0
A55: 24 | B55: =A55/2 -> 12 | C55: =ROUNDUP(A55/2,0) -> 12 | D55: =INDEX(Curves!$E$5:$E$34,C55)/10000 -> 0.0051 | E55: =IF(C55<=$B$6,1,0) -> 1 | F55: =Curves!W29 -> 0.66231055 | G55: =Curves!X29 -> 0.017816333 | L55: =L54 -> 0.020158427 | M55: =M54*EXP(-L55*$B$5) -> 0.89365525 | N55: =N54+F55*(M55*G55+$B$4*(M54-M55)) -> 0.35965331 | O55: =O54+F55*M55*$B$5 -> 9.5038027 | P55: =IF(E55=1,(1-N55-F55*M55)/O55,"") -> 0.0051 | Q55: =IF(A55<=$B$9,MIN(A55,$B$10)/$B$10-MAX(0,MIN(A55-1,$B$9)-$B$7)/$B$8,0) -> 0.54347826 | R55: =IF(AND(A55>$B$7,A55<=$B$9),1/$B$8,0) -> 0.02173913 | S55: =IF(A55<=$B$10,1/$B$10,0) -> 0 | T55: =F54*M54*S55 -> 0 | U55: =F55*M55*$B$5*Q55 -> 0.16083622 | V55: =M55/M54 -> 0.98997141 | W55: =(1-V55)*(1+G55-$B$4)/(V55*$B$5) -> 0.012517181 | X55: =G55/$B$5 -> 0.035632666 | Y55: =W55 -> 0.012517181 | Z55: =U55*(Y55-$E$9) -> 0.0011527423 | AA55: =MAX(0,MIN(1,(B55-$E$4)/$B$5)) -> 0 | AB55: =Z55*AA55 -> 0 | AC55: =Z55-AB55 -> 0.0011527423 | AD55: =Q55*$B$5 -> 0.27173913 | AE55: =AD55*AA55 -> 0 | AF55: =F55*(M55*((G55+$E$9*$B$5)*Q55+R55)+$B$4*(M54-M55)*Q55) -> 0.020761835 | AG55: =S55 -> 0 | AH55: =IF(E55=1,ABS(P55-D55)*10000,0) -> 9.5409791e-14
A56: 25 | B56: =A56/2 -> 12.5 | C56: =ROUNDUP(A56/2,0) -> 13 | D56: =INDEX(Curves!$E$5:$E$34,C56)/10000 -> 0.0056 | E56: =IF(C56<=$B$6,1,0) -> 1 | F56: =Curves!W30 -> 0.65065363 | G56: =Curves!X30 -> 0.017915708 | H56: =N55+D56*O55 -> 0.4128746 | I56: =F57*M55*((G57+D56*$B$5+1)-$B$4) -> 0.35456902 | J56: =M55*(F56*((G56+D56*$B$5)-$B$4)+F57*$B$4) -> 0.0079517882 | K56: =H56+F56*M55*$B$4-1 -> -0.35454138 | L56: =IF(E56=1,-2*LN((-J56+SQRT(J56^2-4*I56*K56))/(2*I56)),L55) -> 0.022504975 | M56: =M55*EXP(-L56*$B$5) -> 0.88365577 | N56: =N55+F56*(M56*G56+$B$4*(M55-M56)) -> 0.37255649 | O56: =O55+F56*M56*$B$5 -> 9.7912796 | Q56: =IF(A56<=$B$9,MIN(A56,$B$10)/$B$10-MAX(0,MIN(A56-1,$B$9)-$B$7)/$B$8,0) -> 0.52173913 | R56: =IF(AND(A56>$B$7,A56<=$B$9),1/$B$8,0) -> 0.02173913 | S56: =IF(A56<=$B$10,1/$B$10,0) -> 0 | T56: =F55*M55*S56 -> 0 | U56: =F56*M56*$B$5*Q56 -> 0.14998796 | V56: =M56/M55 -> 0.98881059 | W56: =(1-V56)*(1+G56-$B$4)/(V56*$B$5) -> 0.013984711 | X56: =G56/$B$5 -> 0.035831417 | Y56: =W56 -> 0.013984711 | Z56: =U56*(Y56-$E$9) -> 0.0012951027 | AA56: =MAX(0,MIN(1,(B56-$E$4)/$B$5)) -> 0 | AB56: =Z56*AA56 -> 0 | AC56: =Z56-AB56 -> 0.0012951027 | AD56: =Q56*$B$5 -> 0.26086957 | AE56: =AD56*AA56 -> 0 | AF56: =F56*(M56*((G56+$E$9*$B$5)*Q56+R56)+$B$4*(M55-M56)*Q56) -> 0.020033528 | AG56: =S56 -> 0 | AH56: 0
A57: 26 | B57: =A57/2 -> 13 | C57: =ROUNDUP(A57/2,0) -> 13 | D57: =INDEX(Curves!$E$5:$E$34,C57)/10000 -> 0.0056 | E57: =IF(C57<=$B$6,1,0) -> 1 | F57: =Curves!W31 -> 0.63920187 | G57: =Curves!X31 -> 0.017915708 | L57: =L56 -> 0.022504975 | M57: =M56*EXP(-L57*$B$5) -> 0.87376818 | N57: =N56+F57*(M57*G57+$B$4*(M56-M57)) -> 0.38509074 | O57: =O56+F57*M57*$B$5 -> 10.070537 | P57: =IF(E57=1,(1-N57-F57*M57)/O57,"") -> 0.0056 | Q57: =IF(A57<=$B$9,MIN(A57,$B$10)/$B$10-MAX(0,MIN(A57-1,$B$9)-$B$7)/$B$8,0) -> 0.5 | R57: =IF(AND(A57>$B$7,A57<=$B$9),1/$B$8,0) -> 0.02173913 | S57: =IF(A57<=$B$10,1/$B$10,0) -> 0 | T57: =F56*M56*S57 -> 0 | U57: =F57*M57*$B$5*Q57 -> 0.13962856 | V57: =M57/M56 -> 0.98881059 | W57: =(1-V57)*(1+G57-$B$4)/(V57*$B$5) -> 0.013984711 | X57: =G57/$B$5 -> 0.035831417 | Y57: =W57 -> 0.013984711 | Z57: =U57*(Y57-$E$9) -> 0.0012056523 | AA57: =MAX(0,MIN(1,(B57-$E$4)/$B$5)) -> 1 | AB57: =Z57*AA57 -> 0.0012056523 | AC57: =Z57-AB57 -> 0 | AD57: =Q57*$B$5 -> 0.25 | AE57: =AD57*AA57 -> 0.25 | AF57: =F57*(M57*((G57+$E$9*$B$5)*Q57+R57)+$B$4*(M56-M57)*Q57) -> 0.01915575 | AG57: =S57 -> 0 | AH57: =IF(E57=1,ABS(P57-D57)*10000,0) -> 6.9388939e-14
A58: 27 | B58: =A58/2 -> 13.5 | C58: =ROUNDUP(A58/2,0) -> 14 | D58: =INDEX(Curves!$E$5:$E$34,C58)/10000 -> 0.0061 | E58: =IF(C58<=$B$6,1,0) -> 1 | F58: =Curves!W32 -> 0.62788896 | G58: =Curves!X32 -> 0.018017377 | H58: =N57+D58*O57 -> 0.44652101 | I58: =F59*M57*((G59+D58*$B$5+1)-$B$4) -> 0.33470531 | J58: =M57*(F58*((G58+D58*$B$5)-$B$4)+F59*$B$4) -> 0.0076742161 | K58: =H58+F58*M57*$B$4-1 -> -0.33402723 | L58: =IF(E58=1,-2*LN((-J58+SQRT(J58^2-4*I58*K58))/(2*I58)),L57) -> 0.024978979 | M58: =M57*EXP(-L58*$B$5) -> 0.86292312 | N58: =N57+F58*(M58*G58+$B$4*(M57-M58)) -> 0.39757671 | O58: =O57+F58*M58*$B$5 -> 10.341447 | Q58: =IF(A58<=$B$9,MIN(A58,$B$10)/$B$10-MAX(0,MIN(A58-1,$B$9)-$B$7)/$B$8,0) -> 0.47826087 | R58: =IF(AND(A58>$B$7,A58<=$B$9),1/$B$8,0) -> 0.02173913 | S58: =IF(A58<=$B$10,1/$B$10,0) -> 0 | T58: =F57*M57*S58 -> 0 | U58: =F58*M58*$B$5*Q58 -> 0.12956563 | V58: =M58/M57 -> 0.98758818 | W58: =(1-V58)*(1+G58-$B$4)/(V58*$B$5) -> 0.015534249 | X58: =G58/$B$5 -> 0.036034754 | Y58: =W58 -> 0.015534249 | Z58: =U58*(Y58-$E$9) -> 0.0013195286 | AA58: =MAX(0,MIN(1,(B58-$E$4)/$B$5)) -> 1 | AB58: =Z58*AA58 -> 0.0013195286 | AC58: =Z58-AB58 -> 0 | AD58: =Q58*$B$5 -> 0.23913043 | AE58: =AD58*AA58 -> 0.23913043 | AF58: =F58*(M58*((G58+$E$9*$B$5)*Q58+R58)+$B$4*(M57-M58)*Q58) -> 0.01844342 | AG58: =S58 -> 0 | AH58: 0
A59: 28 | B59: =A59/2 -> 14 | C59: =ROUNDUP(A59/2,0) -> 14 | D59: =INDEX(Curves!$E$5:$E$34,C59)/10000 -> 0.0061 | E59: =IF(C59<=$B$6,1,0) -> 1 | F59: =Curves!W33 -> 0.61677627 | G59: =Curves!X33 -> 0.018017377 | L59: =L58 -> 0.024978979 | M59: =M58*EXP(-L59*$B$5) -> 0.85221268 | N59: =N58+F59*(M59*G59+$B$4*(M58-M59)) -> 0.40968946 | O59: =O58+F59*M59*$B$5 -> 10.604259 | P59: =IF(E59=1,(1-N59-F59*M59)/O59,"") -> 0.0061 | Q59: =IF(A59<=$B$9,MIN(A59,$B$10)/$B$10-MAX(0,MIN(A59-1,$B$9)-$B$7)/$B$8,0) -> 0.45652174 | R59: =IF(AND(A59>$B$7,A59<=$B$9),1/$B$8,0) -> 0.02173913 | S59: =IF(A59<=$B$10,1/$B$10,0) -> 0 | T59: =F58*M58*S59 -> 0 | U59: =F59*M59*$B$5*Q59 -> 0.11997952 | V59: =M59/M58 -> 0.98758818 | W59: =(1-V59)*(1+G59-$B$4)/(V59*$B$5) -> 0.015534249 | X59: =G59/$B$5 -> 0.036034754 | Y59: =W59 -> 0.015534249 | Z59: =U59*(Y59-$E$9) -> 0.0012219013 | AA59: =MAX(0,MIN(1,(B59-$E$4)/$B$5)) -> 1 | AB59: =Z59*AA59 -> 0.0012219013 | AC59: =Z59-AB59 -> 0 | AD59: =Q59*$B$5 -> 0.22826087 | AE59: =AD59*AA59 -> 0.22826087 | AF59: =F59*(M59*((G59+$E$9*$B$5)*Q59+R59)+$B$4*(M58-M59)*Q59) -> 0.017598247 | AG59: =S59 -> 0 | AH59: =IF(E59=1,ABS(P59-D59)*10000,0) -> 1.5612511e-13
A60: 29 | B60: =A60/2 -> 14.5 | C60: =ROUNDUP(A60/2,0) -> 15 | D60: =INDEX(Curves!$E$5:$E$34,C60)/10000 -> 0.0065 | E60: =IF(C60<=$B$6,1,0) -> 1 | F60: =Curves!W34 -> 0.60579833 | G60: =Curves!X34 -> 0.018121451 | H60: =N59+D60*O59 -> 0.47861715 | I60: =F61*M59*((G61+D60*$B$5+1)-$B$4) -> 0.31508503 | J60: =M59*(F60*((G60+D60*$B$5)-$B$4)+F61*$B$4) -> 0.0073578078 | K60: =H60+F60*M59*$B$4-1 -> -0.31487525 | L60: =IF(E60=1,-2*LN((-J60+SQRT(J60^2-4*I60*K60))/(2*I60)),L59) -> 0.024025073 | M60: =M59*EXP(-L60*$B$5) -> 0.84203668 | N60: =N59+F60*(M60*G60+$B$4*(M59-M60)) -> 0.42139913 | O60: =O59+F60*M60*$B$5 -> 10.859311 | Q60: =IF(A60<=$B$9,MIN(A60,$B$10)/$B$10-MAX(0,MIN(A60-1,$B$9)-$B$7)/$B$8,0) -> 0.43478261 | R60: =IF(AND(A60>$B$7,A60<=$B$9),1/$B$8,0) -> 0.02173913 | S60: =IF(A60<=$B$10,1/$B$10,0) -> 0 | T60: =F59*M59*S60 -> 0 | U60: =F60*M60*$B$5*Q60 -> 0.11089226 | V60: =M60/M59 -> 0.98805933 | W60: =(1-V60)*(1+G60-$B$4)/(V60*$B$5) -> 0.014939967 | X60: =G60/$B$5 -> 0.036242901 | Y60: =W60 -> 0.014939967 | Z60: =U60*(Y60-$E$9) -> 0.0010634532 | AA60: =MAX(0,MIN(1,(B60-$E$4)/$B$5)) -> 1 | AB60: =Z60*AA60 -> 0.0010634532 | AC60: =Z60-AB60 -> 0 | AD60: =Q60*$B$5 -> 0.2173913 | AE60: =AD60*AA60 -> 0.2173913 | AF60: =F60*(M60*((G60+$E$9*$B$5)*Q60+R60)+$B$4*(M59-M60)*Q60) -> 0.016773662 | AG60: =S60 -> 0 | AH60: 0
A61: 30 | B61: =A61/2 -> 15 | C61: =ROUNDUP(A61/2,0) -> 15 | D61: =INDEX(Curves!$E$5:$E$34,C61)/10000 -> 0.0065 | E61: =IF(C61<=$B$6,1,0) -> 1 | F61: =Curves!W35 -> 0.59501578 | G61: =Curves!X35 -> 0.018121451 | L61: =L60 -> 0.024025073 | M61: =M60*EXP(-L61*$B$5) -> 0.8319822 | N61: =N60+F61*(M61*G61+$B$4*(M60-M61)) -> 0.43276305 | O61: =O60+F61*M61*$B$5 -> 11.106832 | P61: =IF(E61=1,(1-N61-F61*M61)/O61,"") -> 0.0065 | Q61: =IF(A61<=$B$9,MIN(A61,$B$10)/$B$10-MAX(0,MIN(A61-1,$B$9)-$B$7)/$B$8,0) -> 0.41304348 | R61: =IF(AND(A61>$B$7,A61<=$B$9),1/$B$8,0) -> 0.02173913 | S61: =IF(A61<=$B$10,1/$B$10,0) -> 0 | T61: =F60*M60*S61 -> 0 | U61: =F61*M61*$B$5*Q61 -> 0.10223705 | V61: =M61/M60 -> 0.98805933 | W61: =(1-V61)*(1+G61-$B$4)/(V61*$B$5) -> 0.014939967 | X61: =G61/$B$5 -> 0.036242901 | Y61: =W61 -> 0.014939967 | Z61: =U61*(Y61-$E$9) -> 0.0009804499 | AA61: =MAX(0,MIN(1,(B61-$E$4)/$B$5)) -> 1 | AB61: =Z61*AA61 -> 0.0009804499 | AC61: =Z61-AB61 -> 0 | AD61: =Q61*$B$5 -> 0.20652174 | AE61: =AD61*AA61 -> 0.20652174 | AF61: =F61*(M61*((G61+$E$9*$B$5)*Q61+R61)+$B$4*(M60-M61)*Q61) -> 0.016002555 | AG61: =S61 -> 0 | AH61: =IF(E61=1,ABS(P61-D61)*10000,0) -> 9.5409791e-14
A62: 31 | B62: =A62/2 -> 15.5 | C62: =ROUNDUP(A62/2,0) -> 16 | D62: =INDEX(Curves!$E$5:$E$34,C62)/10000 -> 0.0068 | E62: =IF(C62<=$B$6,1,0) -> 1 | F62: =Curves!W36 -> 0.58531642 | G62: =Curves!X36 -> 0.016571135 | H62: =N61+D62*O61 -> 0.50828951 | I62: =F63*M61*((G63+D62*$B$5+1)-$B$4) -> 0.29698768 | J62: =M61*(F62*((G62+D62*$B$5)-$B$4)+F63*$B$4) -> 0.006550141 | K62: =H62+F62*M61*$B$4-1 -> -0.29692135 | L62: =IF(E62=1,-2*LN((-J62+SQRT(J62^2-4*I62*K62))/(2*I62)),L61) -> 0.02228066 | M62: =M61*EXP(-L62*$B$5) -> 0.82276508 | N62: =N61+F62*(M62*G62+$B$4*(M61-M62)) -> 0.44290132 | O62: =O61+F62*M62*$B$5 -> 11.347621 | Q62: =IF(A62<=$B$9,MIN(A62,$B$10)/$B$10-MAX(0,MIN(A62-1,$B$9)-$B$7)/$B$8,0) -> 0.39130435 | R62: =IF(AND(A62>$B$7,A62<=$B$9),1/$B$8,0) -> 0.02173913 | S62: =IF(A62<=$B$10,1/$B$10,0) -> 0 | T62: =F61*M61*S62 -> 0 | U62: =F62*M62*$B$5*Q62 -> 0.094221765 | V62: =M62/M61 -> 0.98892149 | W62: =(1-V62)*(1+G62-$B$4)/(V62*$B$5) -> 0.013814418 | X62: =G62/$B$5 -> 0.03314227 | Y62: =W62 -> 0.013814418 | Z62: =U62*(Y62-$E$9) -> 0.00079753236 | AA62: =MAX(0,MIN(1,(B62-$E$4)/$B$5)) -> 1 | AB62: =Z62*AA62 -> 0.00079753236 | AC62: =Z62-AB62 -> 0 | AD62: =Q62*$B$5 -> 0.19565217 | AE62: =AD62*AA62 -> 0.19565217 | AF62: =F62*(M62*((G62+$E$9*$B$5)*Q62+R62)+$B$4*(M61-M62)*Q62) -> 0.014940319 | AG62: =S62 -> 0 | AH62: 0
A63: 32 | B63: =A63/2 -> 16 | C63: =ROUNDUP(A63/2,0) -> 16 | D63: =INDEX(Curves!$E$5:$E$34,C63)/10000 -> 0.0068 | E63: =IF(C63<=$B$6,1,0) -> 1 | F63: =Curves!W37 -> 0.57577517 | G63: =Curves!X37 -> 0.016571135 | L63: =L62 -> 0.02228066 | M63: =M62*EXP(-L63*$B$5) -> 0.81365007 | N63: =N62+F63*(M63*G63+$B$4*(M62-M63)) -> 0.45276383 | O63: =O62+F63*M63*$B$5 -> 11.581861 | P63: =IF(E63=1,(1-N63-F63*M63)/O63,"") -> 0.0068 | Q63: =IF(A63<=$B$9,MIN(A63,$B$10)/$B$10-MAX(0,MIN(A63-1,$B$9)-$B$7)/$B$8,0) -> 0.36956522 | R63: =IF(AND(A63>$B$7,A63<=$B$9),1/$B$8,0) -> 0.02173913 | S63: =IF(A63<=$B$10,1/$B$10,0) -> 0 | T63: =F62*M62*S63 -> 0 | U63: =F63*M63*$B$5*Q63 -> 0.086566866 | V63: =M63/M62 -> 0.98892149 | W63: =(1-V63)*(1+G63-$B$4)/(V63*$B$5) -> 0.013814418 | X63: =G63/$B$5 -> 0.03314227 | Y63: =W63 -> 0.013814418 | Z63: =U63*(Y63-$E$9) -> 0.0007327381 | AA63: =MAX(0,MIN(1,(B63-$E$4)/$B$5)) -> 1 | AB63: =Z63*AA63 -> 0.0007327381 | AC63: =Z63-AB63 -> 0 | AD63: =Q63*$B$5 -> 0.18478261 | AE63: =AD63*AA63 -> 0.18478261 | AF63: =F63*(M63*((G63+$E$9*$B$5)*Q63+R63)+$B$4*(M62-M63)*Q63) -> 0.014292313 | AG63: =S63 -> 0 | AH63: =IF(E63=1,ABS(P63-D63)*10000,0) -> 6.0715322e-14
A64: 33 | B64: =A64/2 -> 16.5 | C64: =ROUNDUP(A64/2,0) -> 17 | D64: =INDEX(Curves!$E$5:$E$34,C64)/10000 -> 0.0071 | E64: =IF(C64<=$B$6,1,0) -> 1 | F64: =Curves!W38 -> 0.56644863 | G64: =Curves!X38 -> 0.016464948 | H64: =N63+D64*O63 -> 0.53499505 | I64: =F65*M63*((G65+D64*$B$5+1)-$B$4) -> 0.28113049 | J64: =M63*(F64*((G64+D64*$B$5)-$B$4)+F65*$B$4) -> 0.0062384589 | K64: =H64+F64*M63*$B$4-1 -> -0.28064857 | L64: =IF(E64=1,-2*LN((-J64+SQRT(J64^2-4*I64*K64))/(2*I64)),L63) -> 0.023924906 | M64: =M63*EXP(-L64*$B$5) -> 0.8039748 | N64: =N63+F64*(M64*G64+$B$4*(M63-M64)) -> 0.46245436 | O64: =O63+F64*M64*$B$5 -> 11.809566 | Q64: =IF(A64<=$B$9,MIN(A64,$B$10)/$B$10-MAX(0,MIN(A64-1,$B$9)-$B$7)/$B$8,0) -> 0.34782609 | R64: =IF(AND(A64>$B$7,A64<=$B$9),1/$B$8,0) -> 0.02173913 | S64: =IF(A64<=$B$10,1/$B$10,0) -> 0 | T64: =F63*M63*S64 -> 0 | U64: =F64*M64*$B$5*Q64 -> 0.079201813 | V64: =M64/M63 -> 0.98810881 | W64: =(1-V64)*(1+G64-$B$4)/(V64*$B$5) -> 0.014837435 | X64: =G64/$B$5 -> 0.032929897 | Y64: =W64 -> 0.014837435 | Z64: =U64*(Y64-$E$9) -> 0.00075142204 | AA64: =MAX(0,MIN(1,(B64-$E$4)/$B$5)) -> 1 | AB64: =Z64*AA64 -> 0.00075142204 | AC64: =Z64-AB64 -> 0 | AD64: =Q64*$B$5 -> 0.17391304 | AE64: =AD64*AA64 -> 0.17391304 | AF64: =F64*(M64*((G64+$E$9*$B$5)*Q64+R64)+$B$4*(M63-M64)*Q64) -> 0.013694574 | AG64: =S64 -> 0 | AH64: 0
A65: 34 | B65: =A65/2 -> 17 | C65: =ROUNDUP(A65/2,0) -> 17 | D65: =INDEX(Curves!$E$5:$E$34,C65)/10000 -> 0.0071 | E65: =IF(C65<=$B$6,1,0) -> 1 | F65: =Curves!W39 -> 0.55727315 | G65: =Curves!X39 -> 0.016464948 | L65: =L64 -> 0.023924906 | M65: =M64*EXP(-L65*$B$5) -> 0.79441459 | N65: =N64+F65*(M65*G65+$B$4*(M64-M65)) -> 0.47187455 | O65: =O64+F65*M65*$B$5 -> 12.030919 | P65: =IF(E65=1,(1-N65-F65*M65)/O65,"") -> 0.0071 | Q65: =IF(A65<=$B$9,MIN(A65,$B$10)/$B$10-MAX(0,MIN(A65-1,$B$9)-$B$7)/$B$8,0) -> 0.32608696 | R65: =IF(AND(A65>$B$7,A65<=$B$9),1/$B$8,0) -> 0.02173913 | S65: =IF(A65<=$B$10,1/$B$10,0) -> 0 | T65: =F64*M64*S65 -> 0 | U65: =F65*M65*$B$5*Q65 -> 0.072180313 | V65: =M65/M64 -> 0.98810881 | W65: =(1-V65)*(1+G65-$B$4)/(V65*$B$5) -> 0.014837435 | X65: =G65/$B$5 -> 0.032929897 | Y65: =W65 -> 0.014837435 | Z65: =U65*(Y65-$E$9) -> 0.00068480602 | AA65: =MAX(0,MIN(1,(B65-$E$4)/$B$5)) -> 1 | AB65: =Z65*AA65 -> 0.00068480602 | AC65: =Z65-AB65 -> 0 | AD65: =Q65*$B$5 -> 0.16304348 | AE65: =AD65*AA65 -> 0.16304348 | AF65: =F65*(M65*((G65+$E$9*$B$5)*Q65+R65)+$B$4*(M64-M65)*Q65) -> 0.013082008 | AG65: =S65 -> 0 | AH65: =IF(E65=1,ABS(P65-D65)*10000,0) -> 3.469447e-14
A66: 35 | B66: =A66/2 -> 17.5 | C66: =ROUNDUP(A66/2,0) -> 18 | D66: =INDEX(Curves!$E$5:$E$34,C66)/10000 -> 0.0074 | E66: =IF(C66<=$B$6,1,0) -> 1 | F66: =Curves!W40 -> 0.54830468 | G66: =Curves!X40 -> 0.016356728 | H66: =N65+D66*O65 -> 0.56090335 | I66: =F67*M65*((G67+D66*$B$5+1)-$B$4) -> 0.26573847 | J66: =M65*(F66*((G66+D66*$B$5)-$B$4)+F67*$B$4) -> 0.0059323253 | K66: =H66+F66*M65*$B$4-1 -> -0.26486415 | L66: =IF(E66=1,-2*LN((-J66+SQRT(J66^2-4*I66*K66))/(2*I66)),L65) -> 0.02565583 | M66: =M65*EXP(-L66*$B$5) -> 0.78428899 | N66: =N65+F66*(M66*G66+$B$4*(M65-M66)) -> 0.48112919 | O66: =O65+F66*M66*$B$5 -> 12.245934 | Q66: =IF(A66<=$B$9,MIN(A66,$B$10)/$B$10-MAX(0,MIN(A66-1,$B$9)-$B$7)/$B$8,0) -> 0.30434783 | R66: =IF(AND(A66>$B$7,A66<=$B$9),1/$B$8,0) -> 0.02173913 | S66: =IF(A66<=$B$10,1/$B$10,0) -> 0 | T66: =F65*M65*S66 -> 0 | U66: =F66*M66*$B$5*Q66 -> 0.065439245 | V66: =M66/M65 -> 0.98725401 | W66: =(1-V66)*(1+G66-$B$4)/(V66*$B$5) -> 0.015915003 | X66: =G66/$B$5 -> 0.032713456 | Y66: =W66 -> 0.015915003 | Z66: =U66*(Y66-$E$9) -> 0.00069136582 | AA66: =MAX(0,MIN(1,(B66-$E$4)/$B$5)) -> 1 | AB66: =Z66*AA66 -> 0.00069136582 | AC66: =Z66-AB66 -> 0 | AD66: =Q66*$B$5 -> 0.15217391 | AE66: =AD66*AA66 -> 0.15217391 | AF66: =F66*(M66*((G66+$E$9*$B$5)*Q66+R66)+$B$4*(M65-M66)*Q66) -> 0.012515192 | AG66: =S66 -> 0 | AH66: 0
A67: 36 | B67: =A67/2 -> 18 | C67: =ROUNDUP(A67/2,0) -> 18 | D67: =INDEX(Curves!$E$5:$E$34,C67)/10000 -> 0.0074 | E67: =IF(C67<=$B$6,1,0) -> 1 | F67: =Curves!W41 -> 0.53948054 | G67: =Curves!X41 -> 0.016356728 | L67: =L66 -> 0.02565583 | M67: =M66*EXP(-L67*$B$5) -> 0.77429245 | N67: =N66+F67*(M67*G67+$B$4*(M66-M67)) -> 0.49011883 | O67: =O66+F67*M67*$B$5 -> 12.454792 | P67: =IF(E67=1,(1-N67-F67*M67)/O67,"") -> 0.0074 | Q67: =IF(A67<=$B$9,MIN(A67,$B$10)/$B$10-MAX(0,MIN(A67-1,$B$9)-$B$7)/$B$8,0) -> 0.2826087 | R67: =IF(AND(A67>$B$7,A67<=$B$9),1/$B$8,0) -> 0.02173913 | S67: =IF(A67<=$B$10,1/$B$10,0) -> 0 | T67: =F66*M66*S67 -> 0 | U67: =F67*M67*$B$5*Q67 -> 0.059025047 | V67: =M67/M66 -> 0.98725401 | W67: =(1-V67)*(1+G67-$B$4)/(V67*$B$5) -> 0.015915003 | X67: =G67/$B$5 -> 0.032713456 | Y67: =W67 -> 0.015915003 | Z67: =U67*(Y67-$E$9) -> 0.0006235998 | AA67: =MAX(0,MIN(1,(B67-$E$4)/$B$5)) -> 1 | AB67: =Z67*AA67 -> 0.0006235998 | AC67: =Z67-AB67 -> 0 | AD67: =Q67*$B$5 -> 0.14130435 | AE67: =AD67*AA67 -> 0.14130435 | AF67: =F67*(M67*((G67+$E$9*$B$5)*Q67+R67)+$B$4*(M66-M67)*Q67) -> 0.01193711 | AG67: =S67 -> 0 | AH67: =IF(E67=1,ABS(P67-D67)*10000,0) -> 1.3010426e-13
A68: 37 | B68: =A68/2 -> 18.5 | C68: =ROUNDUP(A68/2,0) -> 19 | D68: =INDEX(Curves!$E$5:$E$34,C68)/10000 -> 0.0076 | E68: =IF(C68<=$B$6,1,0) -> 1 | F68: =Curves!W42 -> 0.53085602 | G68: =Curves!X42 -> 0.01624644 | H68: =N67+D68*O67 -> 0.58477524 | I68: =F69*M67*((G69+D68*$B$5+1)-$B$4) -> 0.25078812 | J68: =M67*(F68*((G68+D68*$B$5)-$B$4)+F69*$B$4) -> 0.0056113876 | K68: =H68+F68*M67*$B$4-1 -> -0.25080963 | L68: =IF(E68=1,-2*LN((-J68+SQRT(J68^2-4*I68*K68))/(2*I68)),L67) -> 0.022287813 | M68: =M67*EXP(-L68*$B$5) -> 0.76571171 | N68: =N67+F68*(M68*G68+$B$4*(M67-M68)) -> 0.49854478 | O68: =O67+F68*M68*$B$5 -> 12.658033 | Q68: =IF(A68<=$B$9,MIN(A68,$B$10)/$B$10-MAX(0,MIN(A68-1,$B$9)-$B$7)/$B$8,0) -> 0.26086957 | R68: =IF(AND(A68>$B$7,A68<=$B$9),1/$B$8,0) -> 0.02173913 | S68: =IF(A68<=$B$10,1/$B$10,0) -> 0 | T68: =F67*M67*S68 -> 0 | U68: =F68*M68*$B$5*Q68 -> 0.053019479 | V68: =M68/M67 -> 0.98891796 | W68: =(1-V68)*(1+G68-$B$4)/(V68*$B$5) -> 0.0138116 | X68: =G68/$B$5 -> 0.032492881 | Y68: =W68 -> 0.0138116 | Z68: =U68*(Y68-$E$9) -> 0.00044862962 | AA68: =MAX(0,MIN(1,(B68-$E$4)/$B$5)) -> 1 | AB68: =Z68*AA68 -> 0.00044862962 | AC68: =Z68-AB68 -> 0 | AD68: =Q68*$B$5 -> 0.13043478 | AE68: =AD68*AA68 -> 0.13043478 | AF68: =F68*(M68*((G68+$E$9*$B$5)*Q68+R68)+$B$4*(M67-M68)*Q68) -> 0.011318309 | AG68: =S68 -> 0 | AH68: 0
A69: 38 | B69: =A69/2 -> 19 | C69: =ROUNDUP(A69/2,0) -> 19 | D69: =INDEX(Curves!$E$5:$E$34,C69)/10000 -> 0.0076 | E69: =IF(C69<=$B$6,1,0) -> 1 | F69: =Curves!W43 -> 0.52236938 | G69: =Curves!X43 -> 0.01624644 | L69: =L68 -> 0.022287813 | M69: =M68*EXP(-L69*$B$5) -> 0.75722606 | N69: =N68+F69*(M69*G69+$B$4*(M68-M69)) -> 0.50674414 | O69: =O68+F69*M69*$B$5 -> 12.855809 | P69: =IF(E69=1,(1-N69-F69*M69)/O69,"") -> 0.0076 | Q69: =IF(A69<=$B$9,MIN(A69,$B$10)/$B$10-MAX(0,MIN(A69-1,$B$9)-$B$7)/$B$8,0) -> 0.23913043 | R69: =IF(AND(A69>$B$7,A69<=$B$9),1/$B$8,0) -> 0.02173913 | S69: =IF(A69<=$B$10,1/$B$10,0) -> 0 | T69: =F68*M68*S69 -> 0 | U69: =F69*M69*$B$5*Q69 -> 0.047294226 | V69: =M69/M68 -> 0.98891796 | W69: =(1-V69)*(1+G69-$B$4)/(V69*$B$5) -> 0.0138116 | X69: =G69/$B$5 -> 0.032492881 | Y69: =W69 -> 0.0138116 | Z69: =U69*(Y69-$E$9) -> 0.00040018482 | AA69: =MAX(0,MIN(1,(B69-$E$4)/$B$5)) -> 1 | AB69: =Z69*AA69 -> 0.00040018482 | AC69: =Z69-AB69 -> 0 | AD69: =Q69*$B$5 -> 0.11956522 | AE69: =AD69*AA69 -> 0.11956522 | AF69: =F69*(M69*((G69+$E$9*$B$5)*Q69+R69)+$B$4*(M68-M69)*Q69) -> 0.010812692 | AG69: =S69 -> 0 | AH69: =IF(E69=1,ABS(P69-D69)*10000,0) -> 4.3368087e-14
A70: 39 | B70: =A70/2 -> 19.5 | C70: =ROUNDUP(A70/2,0) -> 20 | D70: =INDEX(Curves!$E$5:$E$34,C70)/10000 -> 0.0078 | E70: =IF(C70<=$B$6,1,0) -> 1 | F70: =Curves!W44 -> 0.51407526 | G70: =Curves!X44 -> 0.016134054 | H70: =N69+D70*O69 -> 0.60701945 | I70: =F71*M69*((G71+D70*$B$5+1)-$B$4) -> 0.23752908 | J70: =M69*(F70*((G70+D70*$B$5)-$B$4)+F71*$B$4) -> 0.0053263595 | K70: =H70+F70*M69*$B$4-1 -> -0.23727207 | L70: =IF(E70=1,-2*LN((-J70+SQRT(J70^2-4*I70*K70))/(2*I70)),L69) -> 0.023518313 | M70: =M69*EXP(-L70*$B$5) -> 0.74837387 | N70: =N69+F70*(M70*G70+$B$4*(M69-M70)) -> 0.51477152 | O70: =O69+F70*M70*$B$5 -> 13.048169 | Q70: =IF(A70<=$B$9,MIN(A70,$B$10)/$B$10-MAX(0,MIN(A70-1,$B$9)-$B$7)/$B$8,0) -> 0.2173913 | R70: =IF(AND(A70>$B$7,A70<=$B$9),1/$B$8,0) -> 0.02173913 | S70: =IF(A70<=$B$10,1/$B$10,0) -> 0 | T70: =F69*M69*S70 -> 0 | U70: =F70*M70*$B$5*Q70 -> 0.041817445 | V70: =M70/M69 -> 0.98830971 | W70: =(1-V70)*(1+G70-$B$4)/(V70*$B$5) -> 0.014575966 | X70: =G70/$B$5 -> 0.032268107 | Y70: =W70 -> 0.014575966 | Z70: =U70*(Y70-$E$9) -> 0.00038580632 | AA70: =MAX(0,MIN(1,(B70-$E$4)/$B$5)) -> 1 | AB70: =Z70*AA70 -> 0.00038580632 | AC70: =Z70-AB70 -> 0 | AD70: =Q70*$B$5 -> 0.10869565 | AE70: =AD70*AA70 -> 0.10869565 | AF70: =F70*(M70*((G70+$E$9*$B$5)*Q70+R70)+$B$4*(M69-M70)*Q70) -> 0.010332294 | AG70: =S70 -> 0 | AH70: 0
A71: 40 | B71: =A71/2 -> 20 | C71: =ROUNDUP(A71/2,0) -> 20 | D71: =INDEX(Curves!$E$5:$E$34,C71)/10000 -> 0.0078 | E71: =IF(C71<=$B$6,1,0) -> 1 | F71: =Curves!W45 -> 0.50591284 | G71: =Curves!X45 -> 0.016134054 | L71: =L70 -> 0.023518313 | M71: =M70*EXP(-L71*$B$5) -> 0.73962516 | N71: =N70+F71*(M71*G71+$B$4*(M70-M71)) -> 0.52257909 | O71: =O70+F71*M71*$B$5 -> 13.235262 | P71: =IF(E71=1,(1-N71-F71*M71)/O71,"") -> 0.0078 | Q71: =IF(A71<=$B$9,MIN(A71,$B$10)/$B$10-MAX(0,MIN(A71-1,$B$9)-$B$7)/$B$8,0) -> 0.19565217 | R71: =IF(AND(A71>$B$7,A71<=$B$9),1/$B$8,0) -> 0.02173913 | S71: =IF(A71<=$B$10,1/$B$10,0) -> 0 | T71: =F70*M70*S71 -> 0 | U71: =F71*M71*$B$5*Q71 -> 0.036605139 | V71: =M71/M70 -> 0.98830971 | W71: =(1-V71)*(1+G71-$B$4)/(V71*$B$5) -> 0.014575966 | X71: =G71/$B$5 -> 0.032268107 | Y71: =W71 -> 0.014575966 | Z71: =U71*(Y71-$E$9) -> 0.00033771776 | AA71: =MAX(0,MIN(1,(B71-$E$4)/$B$5)) -> 1 | AB71: =Z71*AA71 -> 0.00033771776 | AC71: =Z71-AB71 -> 0 | AD71: =Q71*$B$5 -> 0.097826087 | AE71: =AD71*AA71 -> 0.097826087 | AF71: =F71*(M71*((G71+$E$9*$B$5)*Q71+R71)+$B$4*(M70-M71)*Q71) -> 0.0098578805 | AG71: =S71 -> 0 | AH71: =IF(E71=1,ABS(P71-D71)*10000,0) -> 0
A72: 41 | B72: =A72/2 -> 20.5 | C72: =ROUNDUP(A72/2,0) -> 21 | D72: =INDEX(Curves!$E$5:$E$34,C72)/10000 -> 0.00802 | E72: =IF(C72<=$B$6,1,0) -> 1 | F72: =Curves!W46 -> 0.49865888 | G72: =Curves!X46 -> 0.014546928 | H72: =N71+D72*O71 -> 0.62872589 | I72: =F73*M71*((G73+D72*$B$5+1)-$B$4) -> 0.22486547 | J72: =M71*(F72*((G72+D72*$B$5)-$B$4)+F73*$B$4) -> 0.0047288668 | K72: =H72+F72*M71*$B$4-1 -> -0.22374585 | L72: =IF(E72=1,-2*LN((-J72+SQRT(J72^2-4*I72*K72))/(2*I72)),L71) -> 0.026073452 | M72: =M71*EXP(-L72*$B$5) -> 0.73004545 | N72: =N71+F72*(M72*G72+$B$4*(M71-M72)) -> 0.52978561 | O72: =O71+F72*M72*$B$5 -> 13.417284 | Q72: =IF(A72<=$B$9,MIN(A72,$B$10)/$B$10-MAX(0,MIN(A72-1,$B$9)-$B$7)/$B$8,0) -> 0.17391304 | R72: =IF(AND(A72>$B$7,A72<=$B$9),1/$B$8,0) -> 0.02173913 | S72: =IF(A72<=$B$10,1/$B$10,0) -> 0 | T72: =F71*M71*S72 -> 0 | U72: =F72*M72*$B$5*Q72 -> 0.03165597 | V72: =M72/M71 -> 0.98704788 | W72: =(1-V72)*(1+G72-$B$4)/(V72*$B$5) -> 0.016128261 | X72: =G72/$B$5 -> 0.029093857 | Y72: =W72 -> 0.016128261 | Z72: =U72*(Y72-$E$9) -> 0.00034119631 | AA72: =MAX(0,MIN(1,(B72-$E$4)/$B$5)) -> 1 | AB72: =Z72*AA72 -> 0.00034119631 | AC72: =Z72-AB72 -> 0 | AD72: =Q72*$B$5 -> 0.086956522 | AE72: =AD72*AA72 -> 0.086956522 | AF72: =F72*(M72*((G72+$E$9*$B$5)*Q72+R72)+$B$4*(M71-M72)*Q72) -> 0.0093366597 | AG72: =S72 -> 0 | AH72: 0
A73: 42 | B73: =A73/2 -> 21 | C73: =ROUNDUP(A73/2,0) -> 21 | D73: =INDEX(Curves!$E$5:$E$34,C73)/10000 -> 0.00802 | E73: =IF(C73<=$B$6,1,0) -> 1 | F73: =Curves!W47 -> 0.49150894 | G73: =Curves!X47 -> 0.014546928 | L73: =L72 -> 0.026073452 | M73: =M72*EXP(-L73*$B$5) -> 0.72058982 | N73: =N72+F73*(M73*G73+$B$4*(M72-M73)) -> 0.5367968 | O73: =O72+F73*M73*$B$5 -> 13.594372 | P73: =IF(E73=1,(1-N73-F73*M73)/O73,"") -> 0.00802 | Q73: =IF(A73<=$B$9,MIN(A73,$B$10)/$B$10-MAX(0,MIN(A73-1,$B$9)-$B$7)/$B$8,0) -> 0.15217391 | R73: =IF(AND(A73>$B$7,A73<=$B$9),1/$B$8,0) -> 0.02173913 | S73: =IF(A73<=$B$10,1/$B$10,0) -> 0 | T73: =F72*M72*S73 -> 0 | U73: =F73*M73*$B$5*Q73 -> 0.0269482 | V73: =M73/M72 -> 0.98704788 | W73: =(1-V73)*(1+G73-$B$4)/(V73*$B$5) -> 0.016128261 | X73: =G73/$B$5 -> 0.029093857 | Y73: =W73 -> 0.016128261 | Z73: =U73*(Y73-$E$9) -> 0.00029045474 | AA73: =MAX(0,MIN(1,(B73-$E$4)/$B$5)) -> 1 | AB73: =Z73*AA73 -> 0.00029045474 | AC73: =Z73-AB73 -> 0 | AD73: =Q73*$B$5 -> 0.076086957 | AE73: =AD73*AA73 -> 0.076086957 | AF73: =F73*(M73*((G73+$E$9*$B$5)*Q73+R73)+$B$4*(M72-M73)*Q73) -> 0.0089105785 | AG73: =S73 -> 0 | AH73: =IF(E73=1,ABS(P73-D73)*10000,0) -> 5.2041704e-14
A74: 43 | B74: =A74/2 -> 21.5 | C74: =ROUNDUP(A74/2,0) -> 22 | D74: =INDEX(Curves!$E$5:$E$34,C74)/10000 -> 0.00824 | E74: =IF(C74<=$B$6,1,0) -> 1 | F74: =Curves!W48 -> 0.48458283 | G74: =Curves!X48 -> 0.014292936 | H74: =N73+D74*O73 -> 0.64881442 | I74: =F75*M73*((G75+D74*$B$5+1)-$B$4) -> 0.21289786 | J74: =M73*(F74*((G74+D74*$B$5)-$B$4)+F75*$B$4) -> 0.004461307 | K74: =H74+F74*M73*$B$4-1 -> -0.21151139 | L74: =IF(E74=1,-2*LN((-J74+SQRT(J74^2-4*I74*K74))/(2*I74)),L73) -> 0.027557004 | M74: =M73*EXP(-L74*$B$5) -> 0.71072926 | N74: =N73+F74*(M74*G74+$B$4*(M73-M74)) -> 0.54363069 | O74: =O73+F74*M74*$B$5 -> 13.766576 | Q74: =IF(A74<=$B$9,MIN(A74,$B$10)/$B$10-MAX(0,MIN(A74-1,$B$9)-$B$7)/$B$8,0) -> 0.13043478 | R74: =IF(AND(A74>$B$7,A74<=$B$9),1/$B$8,0) -> 0.02173913 | S74: =IF(A74<=$B$10,1/$B$10,0) -> 0 | T74: =F73*M73*S74 -> 0 | U74: =F74*M74*$B$5*Q74 -> 0.022461339 | V74: =M74/M73 -> 0.98631599 | W74: =(1-V74)*(1+G74-$B$4)/(V74*$B$5) -> 0.017045232 | X74: =G74/$B$5 -> 0.028585872 | Y74: =W74 -> 0.017045232 | Z74: =U74*(Y74-$E$9) -> 0.00026269057 | AA74: =MAX(0,MIN(1,(B74-$E$4)/$B$5)) -> 1 | AB74: =Z74*AA74 -> 0.00026269057 | AC74: =Z74-AB74 -> 0 | AD74: =Q74*$B$5 -> 0.065217391 | AE74: =AD74*AA74 -> 0.065217391 | AF74: =F74*(M74*((G74+$E$9*$B$5)*Q74+R74)+$B$4*(M73-M74)*Q74) -> 0.0084986585 | AG74: =S74 -> 0 | AH74: 0
A75: 44 | B75: =A75/2 -> 22 | C75: =ROUNDUP(A75/2,0) -> 22 | D75: =INDEX(Curves!$E$5:$E$34,C75)/10000 -> 0.00824 | E75: =IF(C75<=$B$6,1,0) -> 1 | F75: =Curves!W49 -> 0.47775431 | G75: =Curves!X49 -> 0.014292936 | L75: =L74 -> 0.027557004 | M75: =M74*EXP(-L75*$B$5) -> 0.70100363 | N75: =N74+F75*(M75*G75+$B$4*(M74-M75)) -> 0.55027609 | O75: =O74+F75*M75*$B$5 -> 13.93403 | P75: =IF(E75=1,(1-N75-F75*M75)/O75,"") -> 0.00824 | Q75: =IF(A75<=$B$9,MIN(A75,$B$10)/$B$10-MAX(0,MIN(A75-1,$B$9)-$B$7)/$B$8,0) -> 0.10869565 | R75: =IF(AND(A75>$B$7,A75<=$B$9),1/$B$8,0) -> 0.02173913 | S75: =IF(A75<=$B$10,1/$B$10,0) -> 0 | T75: =F74*M74*S75 -> 0 | U75: =F75*M75*$B$5*Q75 -> 0.018201495 | V75: =M75/M74 -> 0.98631599 | W75: =(1-V75)*(1+G75-$B$4)/(V75*$B$5) -> 0.017045232 | X75: =G75/$B$5 -> 0.028585872 | Y75: =W75 -> 0.017045232 | Z75: =U75*(Y75-$E$9) -> 0.00021287071 | AA75: =MAX(0,MIN(1,(B75-$E$4)/$B$5)) -> 1 | AB75: =Z75*AA75 -> 0.00021287071 | AC75: =Z75-AB75 -> 0 | AD75: =Q75*$B$5 -> 0.054347826 | AE75: =AD75*AA75 -> 0.054347826 | AF75: =F75*(M75*((G75+$E$9*$B$5)*Q75+R75)+$B$4*(M74-M75)*Q75) -> 0.0081003017 | AG75: =S75 -> 0 | AH75: =IF(E75=1,ABS(P75-D75)*10000,0) -> 3.469447e-14
A76: 45 | B76: =A76/2 -> 22.5 | C76: =ROUNDUP(A76/2,0) -> 23 | D76: =INDEX(Curves!$E$5:$E$34,C76)/10000 -> 0.00846 | E76: =IF(C76<=$B$6,1,0) -> 1 | F76: =Curves!W50 -> 0.47114156 | G76: =Curves!X50 -> 0.014035595 | H76: =N75+D76*O75 -> 0.66815798 | I76: =F77*M75*((G77+D76*$B$5+1)-$B$4) -> 0.20136944 | J76: =M75*(F76*((G76+D76*$B$5)-$B$4)+F77*$B$4) -> 0.0042040533 | K76: =H76+F76*M75*$B$4-1 -> -0.19973324 | L76: =IF(E76=1,-2*LN((-J76+SQRT(J76^2-4*I76*K76))/(2*I76)),L75) -> 0.029120808 | M76: =M75*EXP(-L76*$B$5) -> 0.69087068 | N76: =N75+F76*(M76*G76+$B$4*(M75-M76)) -> 0.55675427 | O76: =O75+F76*M76*$B$5 -> 14.096778 | Q76: =IF(A76<=$B$9,MIN(A76,$B$10)/$B$10-MAX(0,MIN(A76-1,$B$9)-$B$7)/$B$8,0) -> 0.086956522 | R76: =IF(AND(A76>$B$7,A76<=$B$9),1/$B$8,0) -> 0.02173913 | S76: =IF(A76<=$B$10,1/$B$10,0) -> 0 | T76: =F75*M75*S76 -> 0 | U76: =F76*M76*$B$5*Q76 -> 0.014152082 | V76: =M76/M75 -> 0.98554509 | W76: =(1-V76)*(1+G76-$B$4)/(V76*$B$5) -> 0.018012026 | X76: =G76/$B$5 -> 0.02807119 | Y76: =W76 -> 0.018012026 | Z76: =U76*(Y76-$E$9) -> 0.00017919403 | AA76: =MAX(0,MIN(1,(B76-$E$4)/$B$5)) -> 1 | AB76: =Z76*AA76 -> 0.00017919403 | AC76: =Z76-AB76 -> 0 | AD76: =Q76*$B$5 -> 0.043478261 | AE76: =AD76*AA76 -> 0.043478261 | AF76: =F76*(M76*((G76+$E$9*$B$5)*Q76+R76)+$B$4*(M75-M76)*Q76) -> 0.0077150746 | AG76: =S76 -> 0 | AH76: 0
A77: 46 | B77: =A77/2 -> 23 | C77: =ROUNDUP(A77/2,0) -> 23 | D77: =INDEX(Curves!$E$5:$E$34,C77)/10000 -> 0.00846 | E77: =IF(C77<=$B$6,1,0) -> 1 | F77: =Curves!W51 -> 0.46462034 | G77: =Curves!X51 -> 0.014035595 | L77: =L76 -> 0.029120808 | M77: =M76*EXP(-L77*$B$5) -> 0.68088421 | N77: =N76+F77*(M77*G77+$B$4*(M76-M77)) -> 0.56305043 | O77: =O76+F77*M77*$B$5 -> 14.254955 | P77: =IF(E77=1,(1-N77-F77*M77)/O77,"") -> 0.00846 | Q77: =IF(A77<=$B$9,MIN(A77,$B$10)/$B$10-MAX(0,MIN(A77-1,$B$9)-$B$7)/$B$8,0) -> 0.065217391 | R77: =IF(AND(A77>$B$7,A77<=$B$9),1/$B$8,0) -> 0.02173913 | S77: =IF(A77<=$B$10,1/$B$10,0) -> 0 | T77: =F76*M76*S77 -> 0 | U77: =F77*M77*$B$5*Q77 -> 0.010315847 | V77: =M77/M76 -> 0.98554509 | W77: =(1-V77)*(1+G77-$B$4)/(V77*$B$5) -> 0.018012026 | X77: =G77/$B$5 -> 0.02807119 | Y77: =W77 -> 0.018012026 | Z77: =U77*(Y77-$E$9) -> 0.00013061953 | AA77: =MAX(0,MIN(1,(B77-$E$4)/$B$5)) -> 1 | AB77: =Z77*AA77 -> 0.00013061953 | AC77: =Z77-AB77 -> 0 | AD77: =Q77*$B$5 -> 0.032608696 | AE77: =AD77*AA77 -> 0.032608696 | AF77: =F77*(M77*((G77+$E$9*$B$5)*Q77+R77)+$B$4*(M76-M77)*Q77) -> 0.0073430408 | AG77: =S77 -> 0 | AH77: =IF(E77=1,ABS(P77-D77)*10000,0) -> 0
A78: 47 | B78: =A78/2 -> 23.5 | C78: =ROUNDUP(A78/2,0) -> 24 | D78: =INDEX(Curves!$E$5:$E$34,C78)/10000 -> 0.00868 | E78: =IF(C78<=$B$6,1,0) -> 1 | F78: =Curves!W52 -> 0.45830716 | G78: =Curves!X52 -> 0.013775004 | H78: =N77+D78*O77 -> 0.68678344 | I78: =F79*M77*((G79+D78*$B$5+1)-$B$4) -> 0.19026443 | J78: =M77*(F78*((G78+D78*$B$5)-$B$4)+F79*$B$4) -> 0.0039568058 | K78: =H78+F78*M77*$B$4-1 -> -0.18839492 | L78: =IF(E78=1,-2*LN((-J78+SQRT(J78^2-4*I78*K78))/(2*I78)),L77) -> 0.030773353 | M78: =M77*EXP(-L78*$B$5) -> 0.67048785 | N78: =N77+F78*(M78*G78+$B$4*(M77-M78)) -> 0.56918923 | O78: =O77+F78*M78*$B$5 -> 14.4086 | Q78: =IF(A78<=$B$9,MIN(A78,$B$10)/$B$10-MAX(0,MIN(A78-1,$B$9)-$B$7)/$B$8,0) -> 0.043478261 | R78: =IF(AND(A78>$B$7,A78<=$B$9),1/$B$8,0) -> 0.02173913 | S78: =IF(A78<=$B$10,1/$B$10,0) -> 0 | T78: =F77*M77*S78 -> 0 | U78: =F78*M78*$B$5*Q78 -> 0.0066802039 | V78: =M78/M77 -> 0.98473109 | W78: =(1-V78)*(1+G78-$B$4)/(V78*$B$5) -> 0.019033974 | X78: =G78/$B$5 -> 0.027550007 | Y78: =W78 -> 0.019033974 | Z78: =U78*(Y78-$E$9) -> 9.1411737e-05 | AA78: =MAX(0,MIN(1,(B78-$E$4)/$B$5)) -> 1 | AB78: =Z78*AA78 -> 9.1411737e-05 | AC78: =Z78-AB78 -> 0 | AD78: =Q78*$B$5 -> 0.02173913 | AE78: =AD78*AA78 -> 0.02173913 | AF78: =F78*(M78*((G78+$E$9*$B$5)*Q78+R78)+$B$4*(M77-M78)*Q78) -> 0.0069828475 | AG78: =S78 -> 0 | AH78: 0
A79: 48 | B79: =A79/2 -> 24 | C79: =ROUNDUP(A79/2,0) -> 24 | D79: =INDEX(Curves!$E$5:$E$34,C79)/10000 -> 0.00868 | E79: =IF(C79<=$B$6,1,0) -> 1 | F79: =Curves!W53 -> 0.45207976 | G79: =Curves!X53 -> 0.013775004 | L79: =L78 -> 0.030773353 | M79: =M78*EXP(-L79*$B$5) -> 0.66025023 | N79: =N78+F79*(M79*G79+$B$4*(M78-M79)) -> 0.57515216 | O79: =O78+F79*M79*$B$5 -> 14.557842 | P79: =IF(E79=1,(1-N79-F79*M79)/O79,"") -> 0.00868 | Q79: =IF(A79<=$B$9,MIN(A79,$B$10)/$B$10-MAX(0,MIN(A79-1,$B$9)-$B$7)/$B$8,0) -> 0.02173913 | R79: =IF(AND(A79>$B$7,A79<=$B$9),1/$B$8,0) -> 0.02173913 | S79: =IF(A79<=$B$10,1/$B$10,0) -> 0 | T79: =F78*M78*S79 -> 0 | U79: =F79*M79*$B$5*Q79 -> 0.0032444105 | V79: =M79/M78 -> 0.98473109 | W79: =(1-V79)*(1+G79-$B$4)/(V79*$B$5) -> 0.019033974 | X79: =G79/$B$5 -> 0.027550007 | Y79: =W79 -> 0.019033974 | Z79: =U79*(Y79-$E$9) -> 4.4396429e-05 | AA79: =MAX(0,MIN(1,(B79-$E$4)/$B$5)) -> 1 | AB79: =Z79*AA79 -> 4.4396429e-05 | AC79: =Z79-AB79 -> 0 | AD79: =Q79*$B$5 -> 0.010869565 | AE79: =AD79*AA79 -> 0.010869565 | AF79: =F79*(M79*((G79+$E$9*$B$5)*Q79+R79)+$B$4*(M78-M79)*Q79) -> 0.0066358075 | AG79: =S79 -> 0 | AH79: =IF(E79=1,ABS(P79-D79)*10000,0) -> 1.7347235e-14
A80: 49 | B80: =A80/2 -> 24.5 | C80: =ROUNDUP(A80/2,0) -> 25 | D80: =INDEX(Curves!$E$5:$E$34,C80)/10000 -> 0.0089 | E80: =IF(C80<=$B$6,1,0) -> 1 | F80: =Curves!W54 -> 0.44605301 | G80: =Curves!X54 -> 0.01351127 | H80: =N79+D80*O79 -> 0.70471696 | I80: =F81*M79*((G81+D80*$B$5+1)-$B$4) -> 0.17956749 | J80: =M79*(F80*((G80+D80*$B$5)-$B$4)+F81*$B$4) -> 0.0037192681 | K80: =H80+F80*M79*$B$4-1 -> -0.1774804 | L80: =IF(E80=1,-2*LN((-J80+SQRT(J80^2-4*I80*K80))/(2*I80)),L79) -> 0.032524393 | M80: =M79*EXP(-L80*$B$5) -> 0.64959995 | N80: =N79+F80*(M80*G80+$B$4*(M79-M80)) -> 0.58096737 | O80: =O79+F80*M80*$B$5 -> 14.70272 | Q80: =IF(A80<=$B$9,MIN(A80,$B$10)/$B$10-MAX(0,MIN(A80-1,$B$9)-$B$7)/$B$8,0) -> 0 | R80: =IF(AND(A80>$B$7,A80<=$B$9),1/$B$8,0) -> 0 | S80: =IF(A80<=$B$10,1/$B$10,0) -> 0 | T80: =F79*M79*S80 -> 0 | U80: =F80*M80*$B$5*Q80 -> 0 | V80: =M80/M79 -> 0.98386932 | W80: =(1-V80)*(1+G80-$B$4)/(V80*$B$5) -> 0.020117214 | X80: =G80/$B$5 -> 0.02702254 | Y80: =W80 -> 0.020117214 | Z80: =U80*(Y80-$E$9) -> 0 | AA80: =MAX(0,MIN(1,(B80-$E$4)/$B$5)) -> 1 | AB80: =Z80*AA80 -> 0 | AC80: =Z80-AB80 -> 0 | AD80: =Q80*$B$5 -> 0 | AE80: =AD80*AA80 -> 0 | AF80: =F80*(M80*((G80+$E$9*$B$5)*Q80+R80)+$B$4*(M79-M80)*Q80) -> 0 | AG80: =S80 -> 0 | AH80: 0
A81: 50 | B81: =A81/2 -> 25 | C81: =ROUNDUP(A81/2,0) -> 25 | D81: =INDEX(Curves!$E$5:$E$34,C81)/10000 -> 0.0089 | E81: =IF(C81<=$B$6,1,0) -> 1 | F81: =Curves!W55 -> 0.44010661 | G81: =Curves!X55 -> 0.01351127 | L81: =L80 -> 0.032524393 | M81: =M80*EXP(-L81*$B$5) -> 0.63912146 | N81: =N80+F81*(M81*G81+$B$4*(M80-M81)) -> 0.5866125 | O81: =O80+F81*M81*$B$5 -> 14.843361 | P81: =IF(E81=1,(1-N81-F81*M81)/O81,"") -> 0.0089 | Q81: =IF(A81<=$B$9,MIN(A81,$B$10)/$B$10-MAX(0,MIN(A81-1,$B$9)-$B$7)/$B$8,0) -> 0 | R81: =IF(AND(A81>$B$7,A81<=$B$9),1/$B$8,0) -> 0 | S81: =IF(A81<=$B$10,1/$B$10,0) -> 0 | T81: =F80*M80*S81 -> 0 | U81: =F81*M81*$B$5*Q81 -> 0 | V81: =M81/M80 -> 0.98386932 | W81: =(1-V81)*(1+G81-$B$4)/(V81*$B$5) -> 0.020117214 | X81: =G81/$B$5 -> 0.02702254 | Y81: =W81 -> 0.020117214 | Z81: =U81*(Y81-$E$9) -> 0 | AA81: =MAX(0,MIN(1,(B81-$E$4)/$B$5)) -> 1 | AB81: =Z81*AA81 -> 0 | AC81: =Z81-AB81 -> 0 | AD81: =Q81*$B$5 -> 0 | AE81: =AD81*AA81 -> 0 | AF81: =F81*(M81*((G81+$E$9*$B$5)*Q81+R81)+$B$4*(M80-M81)*Q81) -> 0 | AG81: =S81 -> 0 | AH81: =IF(E81=1,ABS(P81-D81)*10000,0) -> 1.7347235e-14
A82: 51 | B82: =A82/2 -> 25.5 | C82: =ROUNDUP(A82/2,0) -> 26 | D82: =INDEX(Curves!$E$5:$E$34,C82)/10000 -> 0.009 | E82: =IF(C82<=$B$6,1,0) -> 1 | F82: =Curves!W56 -> 0.43435381 | G82: =Curves!X56 -> 0.013244514 | H82: =N81+D82*O81 -> 0.72020275 | I82: =F83*M81*((G83+D82*$B$5+1)-$B$4) -> 0.16924727 | J82: =M81*(F82*((G82+D82*$B$5)-$B$4)+F83*$B$4) -> 0.0034744906 | K82: =H82+F82*M81*$B$4-1 -> -0.16875531 | L82: =IF(E82=1,-2*LN((-J82+SQRT(J82^2-4*I82*K82))/(2*I82)),L81) -> 0.023469605 | M82: =M81*EXP(-L82*$B$5) -> 0.63166533 | N82: =N81+F82*(M82*G82+$B$4*(M81-M82)) -> 0.59154179 | O82: =O81+F82*M82*$B$5 -> 14.980544 | Q82: =IF(A82<=$B$9,MIN(A82,$B$10)/$B$10-MAX(0,MIN(A82-1,$B$9)-$B$7)/$B$8,0) -> 0 | R82: =IF(AND(A82>$B$7,A82<=$B$9),1/$B$8,0) -> 0 | S82: =IF(A82<=$B$10,1/$B$10,0) -> 0 | T82: =F81*M81*S82 -> 0 | U82: =F82*M82*$B$5*Q82 -> 0 | V82: =M82/M81 -> 0.98833378 | W82: =(1-V82)*(1+G82-$B$4)/(V82*$B$5) -> 0.014477385 | X82: =G82/$B$5 -> 0.026489028 | Y82: =W82 -> 0.014477385 | Z82: =U82*(Y82-$E$9) -> 0 | AA82: =MAX(0,MIN(1,(B82-$E$4)/$B$5)) -> 1 | AB82: =Z82*AA82 -> 0 | AC82: =Z82-AB82 -> 0 | AD82: =Q82*$B$5 -> 0 | AE82: =AD82*AA82 -> 0 | AF82: =F82*(M82*((G82+$E$9*$B$5)*Q82+R82)+$B$4*(M81-M82)*Q82) -> 0 | AG82: =S82 -> 0 | AH82: 0
A83: 52 | B83: =A83/2 -> 26 | C83: =ROUNDUP(A83/2,0) -> 26 | D83: =INDEX(Curves!$E$5:$E$34,C83)/10000 -> 0.009 | E83: =IF(C83<=$B$6,1,0) -> 1 | F83: =Curves!W57 -> 0.4286762 | G83: =Curves!X57 -> 0.013244514 | L83: =L82 -> 0.023469605 | M83: =M82*EXP(-L83*$B$5) -> 0.62429618 | N83: =N82+F83*(M83*G83+$B$4*(M82-M83)) -> 0.59634989 | O83: =O82+F83*M83*$B$5 -> 15.114355 | P83: =IF(E83=1,(1-N83-F83*M83)/O83,"") -> 0.009 | Q83: =IF(A83<=$B$9,MIN(A83,$B$10)/$B$10-MAX(0,MIN(A83-1,$B$9)-$B$7)/$B$8,0) -> 0 | R83: =IF(AND(A83>$B$7,A83<=$B$9),1/$B$8,0) -> 0 | S83: =IF(A83<=$B$10,1/$B$10,0) -> 0 | T83: =F82*M82*S83 -> 0 | U83: =F83*M83*$B$5*Q83 -> 0 | V83: =M83/M82 -> 0.98833378 | W83: =(1-V83)*(1+G83-$B$4)/(V83*$B$5) -> 0.014477385 | X83: =G83/$B$5 -> 0.026489028 | Y83: =W83 -> 0.014477385 | Z83: =U83*(Y83-$E$9) -> 0 | AA83: =MAX(0,MIN(1,(B83-$E$4)/$B$5)) -> 1 | AB83: =Z83*AA83 -> 0 | AC83: =Z83-AB83 -> 0 | AD83: =Q83*$B$5 -> 0 | AE83: =AD83*AA83 -> 0 | AF83: =F83*(M83*((G83+$E$9*$B$5)*Q83+R83)+$B$4*(M82-M83)*Q83) -> 0 | AG83: =S83 -> 0 | AH83: =IF(E83=1,ABS(P83-D83)*10000,0) -> 8.6736174e-14
A84: 53 | B84: =A84/2 -> 26.5 | C84: =ROUNDUP(A84/2,0) -> 27 | D84: =INDEX(Curves!$E$5:$E$34,C84)/10000 -> 0.0091 | E84: =IF(C84<=$B$6,1,0) -> 1 | F84: =Curves!W58 -> 0.42318543 | G84: =Curves!X58 -> 0.012974866 | H84: =N83+D84*O83 -> 0.73389052 | I84: =F85*M83*((G85+D84*$B$5+1)-$B$4) -> 0.16105609 | J84: =M83*(F84*((G84+D84*$B$5)-$B$4)+F85*$B$4) -> 0.0032763625 | K84: =H84+F84*M83*$B$4-1 -> -0.16043226 | L84: =IF(E84=1,-2*LN((-J84+SQRT(J84^2-4*I84*K84))/(2*I84)),L83) -> 0.024263059 | M84: =M83*EXP(-L84*$B$5) -> 0.61676827 | N84: =N83+F84*(M84*G84+$B$4*(M83-M84)) -> 0.60101071 | O84: =O83+F84*M84*$B$5 -> 15.244858 | Q84: =IF(A84<=$B$9,MIN(A84,$B$10)/$B$10-MAX(0,MIN(A84-1,$B$9)-$B$7)/$B$8,0) -> 0 | R84: =IF(AND(A84>$B$7,A84<=$B$9),1/$B$8,0) -> 0 | S84: =IF(A84<=$B$10,1/$B$10,0) -> 0 | T84: =F83*M83*S84 -> 0 | U84: =F84*M84*$B$5*Q84 -> 0 | V84: =M84/M83 -> 0.98794176 | W84: =(1-V84)*(1+G84-$B$4)/(V84*$B$5) -> 0.014963225 | X84: =G84/$B$5 -> 0.025949731 | Y84: =W84 -> 0.014963225 | Z84: =U84*(Y84-$E$9) -> 0 | AA84: =MAX(0,MIN(1,(B84-$E$4)/$B$5)) -> 1 | AB84: =Z84*AA84 -> 0 | AC84: =Z84-AB84 -> 0 | AD84: =Q84*$B$5 -> 0 | AE84: =AD84*AA84 -> 0 | AF84: =F84*(M84*((G84+$E$9*$B$5)*Q84+R84)+$B$4*(M83-M84)*Q84) -> 0 | AG84: =S84 -> 0 | AH84: 0
A85: 54 | B85: =A85/2 -> 27 | C85: =ROUNDUP(A85/2,0) -> 27 | D85: =INDEX(Curves!$E$5:$E$34,C85)/10000 -> 0.0091 | E85: =IF(C85<=$B$6,1,0) -> 1 | F85: =Curves!W59 -> 0.41776498 | G85: =Curves!X59 -> 0.012974866 | L85: =L84 -> 0.024263059 | M85: =M84*EXP(-L85*$B$5) -> 0.60933113 | N85: =N84+F85*(M85*G85+$B$4*(M84-M85)) -> 0.60555634 | O85: =O84+F85*M85*$B$5 -> 15.372137 | P85: =IF(E85=1,(1-N85-F85*M85)/O85,"") -> 0.0091 | Q85: =IF(A85<=$B$9,MIN(A85,$B$10)/$B$10-MAX(0,MIN(A85-1,$B$9)-$B$7)/$B$8,0) -> 0 | R85: =IF(AND(A85>$B$7,A85<=$B$9),1/$B$8,0) -> 0 | S85: =IF(A85<=$B$10,1/$B$10,0) -> 0 | T85: =F84*M84*S85 -> 0 | U85: =F85*M85*$B$5*Q85 -> 0 | V85: =M85/M84 -> 0.98794176 | W85: =(1-V85)*(1+G85-$B$4)/(V85*$B$5) -> 0.014963225 | X85: =G85/$B$5 -> 0.025949731 | Y85: =W85 -> 0.014963225 | Z85: =U85*(Y85-$E$9) -> 0 | AA85: =MAX(0,MIN(1,(B85-$E$4)/$B$5)) -> 1 | AB85: =Z85*AA85 -> 0 | AC85: =Z85-AB85 -> 0 | AD85: =Q85*$B$5 -> 0 | AE85: =AD85*AA85 -> 0 | AF85: =F85*(M85*((G85+$E$9*$B$5)*Q85+R85)+$B$4*(M84-M85)*Q85) -> 0 | AG85: =S85 -> 0 | AH85: =IF(E85=1,ABS(P85-D85)*10000,0) -> 1.7347235e-14
A86: 55 | B86: =A86/2 -> 27.5 | C86: =ROUNDUP(A86/2,0) -> 28 | D86: =INDEX(Curves!$E$5:$E$34,C86)/10000 -> 0.0092 | E86: =IF(C86<=$B$6,1,0) -> 1 | F86: =Curves!W60 -> 0.4125249 | G86: =Curves!X60 -> 0.012702465 | H86: =N85+D86*O85 -> 0.74698 | I86: =F87*M85*((G87+D86*$B$5+1)-$B$4) -> 0.15322149 | J86: =M85*(F86*((G86+D86*$B$5)-$B$4)+F87*$B$4) -> 0.0030880629 | K86: =H86+F86*M85*$B$4-1 -> -0.15247429 | L86: =IF(E86=1,-2*LN((-J86+SQRT(J86^2-4*I86*K86))/(2*I86)),L85) -> 0.025091742 | M86: =M85*EXP(-L86*$B$5) -> 0.6017343 | N86: =N85+F86*(M86*G86+$B$4*(M85-M86)) -> 0.60996303 | O86: =O85+F86*M86*$B$5 -> 15.496252 | Q86: =IF(A86<=$B$9,MIN(A86,$B$10)/$B$10-MAX(0,MIN(A86-1,$B$9)-$B$7)/$B$8,0) -> 0 | R86: =IF(AND(A86>$B$7,A86<=$B$9),1/$B$8,0) -> 0 | S86: =IF(A86<=$B$10,1/$B$10,0) -> 0 | T86: =F85*M85*S86 -> 0 | U86: =F86*M86*$B$5*Q86 -> 0 | V86: =M86/M85 -> 0.9875325 | W86: =(1-V86)*(1+G86-$B$4)/(V86*$B$5) -> 0.015470615 | X86: =G86/$B$5 -> 0.025404929 | Y86: =W86 -> 0.015470615 | Z86: =U86*(Y86-$E$9) -> 0 | AA86: =MAX(0,MIN(1,(B86-$E$4)/$B$5)) -> 1 | AB86: =Z86*AA86 -> 0 | AC86: =Z86-AB86 -> 0 | AD86: =Q86*$B$5 -> 0 | AE86: =AD86*AA86 -> 0 | AF86: =F86*(M86*((G86+$E$9*$B$5)*Q86+R86)+$B$4*(M85-M86)*Q86) -> 0 | AG86: =S86 -> 0 | AH86: 0
A87: 56 | B87: =A87/2 -> 28 | C87: =ROUNDUP(A87/2,0) -> 28 | D87: =INDEX(Curves!$E$5:$E$34,C87)/10000 -> 0.0092 | E87: =IF(C87<=$B$6,1,0) -> 1 | F87: =Curves!W61 -> 0.40735054 | G87: =Curves!X61 -> 0.012702465 | L87: =L86 -> 0.025091742 | M87: =M86*EXP(-L87*$B$5) -> 0.59423217 | N87: =N86+F87*(M87*G87+$B$4*(M86-M87)) -> 0.6142602 | O87: =O86+F87*M87*$B$5 -> 15.617283 | P87: =IF(E87=1,(1-N87-F87*M87)/O87,"") -> 0.0092 | Q87: =IF(A87<=$B$9,MIN(A87,$B$10)/$B$10-MAX(0,MIN(A87-1,$B$9)-$B$7)/$B$8,0) -> 0 | R87: =IF(AND(A87>$B$7,A87<=$B$9),1/$B$8,0) -> 0 | S87: =IF(A87<=$B$10,1/$B$10,0) -> 0 | T87: =F86*M86*S87 -> 0 | U87: =F87*M87*$B$5*Q87 -> 0 | V87: =M87/M86 -> 0.9875325 | W87: =(1-V87)*(1+G87-$B$4)/(V87*$B$5) -> 0.015470615 | X87: =G87/$B$5 -> 0.025404929 | Y87: =W87 -> 0.015470615 | Z87: =U87*(Y87-$E$9) -> 0 | AA87: =MAX(0,MIN(1,(B87-$E$4)/$B$5)) -> 1 | AB87: =Z87*AA87 -> 0 | AC87: =Z87-AB87 -> 0 | AD87: =Q87*$B$5 -> 0 | AE87: =AD87*AA87 -> 0 | AF87: =F87*(M87*((G87+$E$9*$B$5)*Q87+R87)+$B$4*(M86-M87)*Q87) -> 0 | AG87: =S87 -> 0 | AH87: =IF(E87=1,ABS(P87-D87)*10000,0) -> 5.2041704e-14
A88: 57 | B88: =A88/2 -> 28.5 | C88: =ROUNDUP(A88/2,0) -> 29 | D88: =INDEX(Curves!$E$5:$E$34,C88)/10000 -> 0.0092 | E88: =IF(C88<=$B$6,1,0) -> 0 | F88: =Curves!W62 -> 0.40235035 | G88: =Curves!X62 -> 0.012427462 | H88: =N87+D88*O87 -> 0.7579392 | I88: =F89*M87*((G89+D88*$B$5+1)-$B$4) -> 0.14571395 | J88: =M87*(F88*((G88+D88*$B$5)-$B$4)+F89*$B$4) -> 0.0028971662 | K88: =H88+F88*M87*$B$4-1 -> -0.14642499 | L88: =IF(E88=1,-2*LN((-J88+SQRT(J88^2-4*I88*K88))/(2*I88)),L87) -> 0.025091742 | M88: =M87*EXP(-L88*$B$5) -> 0.58682358 | N88: =N87+F88*(M88*G88+$B$4*(M87-M88)) -> 0.61838677 | O88: =O87+F88*M88*$B$5 -> 15.735337 | Q88: =IF(A88<=$B$9,MIN(A88,$B$10)/$B$10-MAX(0,MIN(A88-1,$B$9)-$B$7)/$B$8,0) -> 0 | R88: =IF(AND(A88>$B$7,A88<=$B$9),1/$B$8,0) -> 0 | S88: =IF(A88<=$B$10,1/$B$10,0) -> 0 | T88: =F87*M87*S88 -> 0 | U88: =F88*M88*$B$5*Q88 -> 0 | V88: =M88/M87 -> 0.9875325 | W88: =(1-V88)*(1+G88-$B$4)/(V88*$B$5) -> 0.015463672 | X88: =G88/$B$5 -> 0.024854924 | Y88: =W88 -> 0.015463672 | Z88: =U88*(Y88-$E$9) -> 0 | AA88: =MAX(0,MIN(1,(B88-$E$4)/$B$5)) -> 1 | AB88: =Z88*AA88 -> 0 | AC88: =Z88-AB88 -> 0 | AD88: =Q88*$B$5 -> 0 | AE88: =AD88*AA88 -> 0 | AF88: =F88*(M88*((G88+$E$9*$B$5)*Q88+R88)+$B$4*(M87-M88)*Q88) -> 0 | AG88: =S88 -> 0 | AH88: 0
A89: 58 | B89: =A89/2 -> 29 | C89: =ROUNDUP(A89/2,0) -> 29 | D89: =INDEX(Curves!$E$5:$E$34,C89)/10000 -> 0.0092 | E89: =IF(C89<=$B$6,1,0) -> 0 | F89: =Curves!W63 -> 0.39741153 | G89: =Curves!X63 -> 0.012427462 | L89: =L88 -> 0.025091742 | M89: =M88*EXP(-L89*$B$5) -> 0.57950736 | N89: =N88+F89*(M89*G89+$B$4*(M88-M89)) -> 0.62241187 | O89: =O88+F89*M89*$B$5 -> 15.850488 | P89: =IF(E89=1,(1-N89-F89*M89)/O89,"") | Q89: =IF(A89<=$B$9,MIN(A89,$B$10)/$B$10-MAX(0,MIN(A89-1,$B$9)-$B$7)/$B$8,0) -> 0 | R89: =IF(AND(A89>$B$7,A89<=$B$9),1/$B$8,0) -> 0 | S89: =IF(A89<=$B$10,1/$B$10,0) -> 0 | T89: =F88*M88*S89 -> 0 | U89: =F89*M89*$B$5*Q89 -> 0 | V89: =M89/M88 -> 0.9875325 | W89: =(1-V89)*(1+G89-$B$4)/(V89*$B$5) -> 0.015463672 | X89: =G89/$B$5 -> 0.024854924 | Y89: =W89 -> 0.015463672 | Z89: =U89*(Y89-$E$9) -> 0 | AA89: =MAX(0,MIN(1,(B89-$E$4)/$B$5)) -> 1 | AB89: =Z89*AA89 -> 0 | AC89: =Z89-AB89 -> 0 | AD89: =Q89*$B$5 -> 0 | AE89: =AD89*AA89 -> 0 | AF89: =F89*(M89*((G89+$E$9*$B$5)*Q89+R89)+$B$4*(M88-M89)*Q89) -> 0 | AG89: =S89 -> 0 | AH89: =IF(E89=1,ABS(P89-D89)*10000,0) -> 0
A90: 59 | B90: =A90/2 -> 29.5 | C90: =ROUNDUP(A90/2,0) -> 30 | D90: =INDEX(Curves!$E$5:$E$34,C90)/10000 -> 0.0092 | E90: =IF(C90<=$B$6,1,0) -> 0 | F90: =Curves!W64 -> 0.39264094 | G90: =Curves!X64 -> 0.012150017 | H90: =N89+D90*O89 -> 0.76823637 | I90: =F91*M89*((G91+D90*$B$5+1)-$B$4) -> 0.13864966 | J90: =M89*(F90*((G90+D90*$B$5)-$B$4)+F91*$B$4) -> 0.0027187075 | K90: =H90+F90*M89*$B$4-1 -> -0.14074831 | L90: =IF(E90=1,-2*LN((-J90+SQRT(J90^2-4*I90*K90))/(2*I90)),L89) -> 0.025091742 | M90: =M89*EXP(-L90*$B$5) -> 0.57228235 | N90: =N89+F90*(M90*G90+$B$4*(M89-M90)) -> 0.62627673 | O90: =O89+F90*M90*$B$5 -> 15.962839 | Q90: =IF(A90<=$B$9,MIN(A90,$B$10)/$B$10-MAX(0,MIN(A90-1,$B$9)-$B$7)/$B$8,0) -> 0 | R90: =IF(AND(A90>$B$7,A90<=$B$9),1/$B$8,0) -> 0 | S90: =IF(A90<=$B$10,1/$B$10,0) -> 0 | T90: =F89*M89*S90 -> 0 | U90: =F90*M90*$B$5*Q90 -> 0 | V90: =M90/M89 -> 0.9875325 | W90: =(1-V90)*(1+G90-$B$4)/(V90*$B$5) -> 0.015456666 | X90: =G90/$B$5 -> 0.024300034 | Y90: =W90 -> 0.015456666 | Z90: =U90*(Y90-$E$9) -> 0 | AA90: =MAX(0,MIN(1,(B90-$E$4)/$B$5)) -> 1 | AB90: =Z90*AA90 -> 0 | AC90: =Z90-AB90 -> 0 | AD90: =Q90*$B$5 -> 0 | AE90: =AD90*AA90 -> 0 | AF90: =F90*(M90*((G90+$E$9*$B$5)*Q90+R90)+$B$4*(M89-M90)*Q90) -> 0 | AG90: =S90 -> 0 | AH90: 0
A91: 60 | B91: =A91/2 -> 30 | C91: =ROUNDUP(A91/2,0) -> 30 | D91: =INDEX(Curves!$E$5:$E$34,C91)/10000 -> 0.0092 | E91: =IF(C91<=$B$6,1,0) -> 0 | F91: =Curves!W65 -> 0.38792761 | G91: =Curves!X65 -> 0.012150017 | L91: =L90 -> 0.025091742 | M91: =M90*EXP(-L91*$B$5) -> 0.56514742 | N91: =N90+F91*(M91*G91+$B$4*(M90-M91)) -> 0.63004759 | O91: =O90+F91*M91*$B$5 -> 16.072457 | P91: =IF(E91=1,(1-N91-F91*M91)/O91,"") | Q91: =IF(A91<=$B$9,MIN(A91,$B$10)/$B$10-MAX(0,MIN(A91-1,$B$9)-$B$7)/$B$8,0) -> 0 | R91: =IF(AND(A91>$B$7,A91<=$B$9),1/$B$8,0) -> 0 | S91: =IF(A91<=$B$10,1/$B$10,0) -> 0 | T91: =F90*M90*S91 -> 0 | U91: =F91*M91*$B$5*Q91 -> 0 | V91: =M91/M90 -> 0.9875325 | W91: =(1-V91)*(1+G91-$B$4)/(V91*$B$5) -> 0.015456666 | X91: =G91/$B$5 -> 0.024300034 | Y91: =W91 -> 0.015456666 | Z91: =U91*(Y91-$E$9) -> 0 | AA91: =MAX(0,MIN(1,(B91-$E$4)/$B$5)) -> 1 | AB91: =Z91*AA91 -> 0 | AC91: =Z91-AB91 -> 0 | AD91: =Q91*$B$5 -> 0 | AE91: =AD91*AA91 -> 0 | AF91: =F91*(M91*((G91+$E$9*$B$5)*Q91+R91)+$B$4*(M90-M91)*Q91) -> 0 | AG91: =S91 -> 0 | AH91: =IF(E91=1,ABS(P91-D91)*10000,0) -> 0

Sheet Calc_Fixed
A1: FIXED-rate loan vs bond YTM curve — calibration, loan grid and exact pricing
A2: Calculation sheet — no inputs here. Units: per 1 of notional, rates as decimals.
D3: Pricing results (per 1 notional)
A4: Recovery R | B4: =Inputs!C13 -> 0.4 | D4: WAL = Σ O·a (years) | E4: =SUM($AD$32:$AD$91) -> 12.5
A5: Accrual a (semi-annual) | B5: 0.5 | D5: Risky annuity B = Σ DF·S·a·O | E5: =SUM($U$32:$U$91) -> 8.9433309
A6: Last quoted credit tenor (years) | B6: =Curves!E38 -> 28 | D6: Bond YTM at WAL (quoted basis, linear interp.) | E6: =INDEX(Curves!$J$5:$J$34,MAX(1,MIN(29,INT(MIN(30,MAX(1,E4))))))+(INDEX(Curves!$J$5:$J$34,MAX(1,MIN(29,INT(MIN(30,MAX(1,E4)))))+1)-INDEX(Curves!$J$5:$J$34,MAX(1,MIN(29,INT(MIN(30,MAX(1,E4)))))))*(MIN(30,MAX(1,E4))-MAX(1,MIN(29,INT(MIN(30,MAX(1,E4)))))) -> 0.040965
A7: Drawdown periods D = 2x | B7: =ROUND(2*Inputs!C6,0) -> 2 | D7: Shortcut rate, semi-annual equivalent | E7: =2*((1+E6/Inputs!$C$18)^(Inputs!$C$18/2)-1) -> 0.040553846
A8: Repayment instalments = 2y | B8: =ROUND(2*Inputs!C7,0) -> 46 | D8: Adjustment X (decimal) | E8: =Inputs!C9/10000 -> 0
A9: Total periods n | B9: =B7+B8 -> 48 | D9: Loan spread/rate CHARGED = shortcut + X | E9: =E7+E8 -> 0.040553846
A10: Number of drawdowns (≥1) | B10: =MAX(B7,1) -> 2 | D10: FAIR (hazard-consistent) spread/rate = Σw·k / Σw | E10: =SUMPRODUCT($U$32:$U$91,$Y$32:$Y$91)/E5 -> 0.04135539
D11: NET wedge = fair − charged (+ = borrower saves) | E11: =E10-E9 -> 0.00080154395
D12: Exposure-weighted risk-free forward Σw·f / Σw | E12: =SUMPRODUCT($U$32:$U$91,$X$32:$X$91)/E5 -> 0.034477515
D13: PV of saving, per 1 notional = Σ w·(k − charged) | E13: =SUM($Z$32:$Z$91) -> 0.0071684728
D14: of which WAL → maturity (benefit) | E14: =SUM($AB$32:$AB$91) -> 0.012648777
D15: of which start → WAL (loss) | E15: =SUM($AC$32:$AC$91) -> -0.0054803044
D16: Principal-years after WAL | E16: =SUM($AE$32:$AE$91) -> 3
D17: Principal-years before WAL | E17: =E4-E16 -> 9.5
D18: Risky annuity after WAL | E18: =SUMPRODUCT($U$32:$U$91,$AA$32:$AA$91) -> 1.3386449
D19: Avg fair spread/rate after WAL | E19: =IF(E18>0,SUMPRODUCT($U$32:$U$91,$AA$32:$AA$91,$Y$32:$Y$91)/E18,0) -> 0.050002788
D20: Avg fair spread/rate before WAL | E20: =IF(E5-E18>0,(SUMPRODUCT($U$32:$U$91,$Y$32:$Y$91)-SUMPRODUCT($U$32:$U$91,$AA$32:$AA$91,$Y$32:$Y$91))/(E5-E18),0) -> 0.039833198
D21: CHECK: PV(drawdowns) − PV(loan at charged) — must equal E13 | E21: =SUM($T$32:$T$91)-SUM($AF$32:$AF$91) -> 0.0071684728
D22: CHECK: max bullet repricing error (bp) | E22: =MAX($AH$32:$AH$91) -> 1.2490009e-12
D23: Minimum forward hazard λ | E23: =MIN($L$32:$L$91) -> -0.0037853776
D24: CHECK: WAL via Σt·P − Σt_draw·DD | E24: =SUMPRODUCT($B$32:$B$91,$R$32:$R$91)-SUMPRODUCT($B$32:$B$91-0.5,$AG$32:$AG$91) -> 12.5
D25: Risk-free par yield at WAL (s.a.) | E25: =INDEX(Curves!$Z$6:$Z$65,MAX(1,MIN(59,INT(2*MIN(30,MAX(0.5,E4))))))+(INDEX(Curves!$Z$6:$Z$65,MAX(1,MIN(59,INT(2*MIN(30,MAX(0.5,E4)))))+1)-INDEX(Curves!$Z$6:$Z$65,MAX(1,MIN(59,INT(2*MIN(30,MAX(0.5,E4)))))))*(2*MIN(30,MAX(0.5,E4))-MAX(1,MIN(59,INT(2*MIN(30,MAX(0.5,E4)))))) -> 0.034600787
D26: Final maturity (years) | E26: =B9/2 -> 24
A30: i | B30: t | C30: bucket b | D30: Bullet quote q_b (s.a.) | E30: quoted node? | F30: DF(t) | G30: f·a | H30: K = C(i−1)+q·Ann(i−1) | I30: quad a2 | J30: quad a1 | K30: quad a0 | L30: λ_b fwd hazard | M30: S(t) | N30: C cumulative | O30: Ann cumulative | P30: Bullet reprices to (b at even i) | Q30: O outstanding in period | R30: P repayment at t | S30: DD at t(i−1) | T30: PV of drawdown | U30: w = DF·S·a·O | V30: p = S(i)/S(i−1) | W30: c = credit break-even margin | X30: f fwd rf rate | Y30: k = fair fixed rate (f + c) | Z30: PV saving = w·(k − charged) | AA30: fraction of period after WAL | AB30: PV saving after WAL | AC30: PV saving before WAL | AD30: principal-years O·a | AE30: principal-years after WAL | AF30: PV loan cashflows at charged | AG30: DD amount (for WAL check) | AH30: |repricing error| bp
A31: 0 | B31: =A31/2 -> 0 | F31: =Curves!W5 -> 1 | M31: 1 | N31: 0 | O31: 0
A32: 1 | B32: =A32/2 -> 0.5 | C32: =ROUNDUP(A32/2,0) -> 1 | D32: =INDEX(Curves!$K$5:$K$34,C32) -> 0.030093594 | E32: =IF(C32<=$B$6,1,0) -> 1 | F32: =Curves!W6 -> 0.98492605 | G32: =Curves!X6 -> 0.015304653 | H32: =N31+D32*O31 -> 0 | I32: =F33*M31*((D32*$B$5+1)-$B$4) -> 0.59557161 | J32: =M31*(F32*((D32*$B$5)-$B$4)+F33*$B$4) -> 0.0081837353 | K32: =H32+F32*M31*$B$4-1 -> -0.60602958 | L32: =IF(E32=1,-2*LN((-J32+SQRT(J32^2-4*I32*K32))/(2*I32)),0) -> -0.0037853776 | M32: =M31*EXP(-L32*$B$5) -> 1.0018945 | N32: =N31+F32*$B$4*(M31-M32) -> -0.0007463695 | O32: =O31+F32*M32*$B$5 -> 0.49339599 | Q32: =IF(A32<=$B$9,MIN(A32,$B$10)/$B$10-MAX(0,MIN(A32-1,$B$9)-$B$7)/$B$8,0) -> 0.5 | R32: =IF(AND(A32>$B$7,A32<=$B$9),1/$B$8,0) -> 0 | S32: =IF(A32<=$B$10,1/$B$10,0) -> 0.5 | T32: =F31*M31*S32 -> 0.5 | U32: =F32*M32*$B$5*Q32 -> 0.24669799 | V32: =M32/M31 -> 1.0018945 | W32: =(1-V32)*(1+G32-$B$4)/(V32*$B$5) -> -0.0023269576 | X32: =G32/$B$5 -> 0.030609306 | Y32: =X32+W32 -> 0.028282348 | Z32: =U32*(Y32-$E$9) -> -0.003027354 | AA32: =MAX(0,MIN(1,(B32-$E$4)/$B$5)) -> 0 | AB32: =Z32*AA32 -> 0 | AC32: =Z32-AB32 -> -0.003027354 | AD32: =Q32*$B$5 -> 0.25 | AE32: =AD32*AA32 -> 0 | AF32: =F32*(M32*(($E$9*$B$5)*Q32+R32)+$B$4*(M31-M32)*Q32) -> 0.0096313678 | AG32: =S32 -> 0.5 | AH32: 0
A33: 2 | B33: =A33/2 -> 1 | C33: =ROUNDUP(A33/2,0) -> 1 | D33: =INDEX(Curves!$K$5:$K$34,C33) -> 0.030093594 | E33: =IF(C33<=$B$6,1,0) -> 1 | F33: =Curves!W7 -> 0.96833543 | G33: =Curves!X7 -> 0.017133131 | L33: =L32 -> -0.0037853776 | M33: =M32*EXP(-L33*$B$5) -> 1.0037926 | N33: =N32+F33*$B$4*(M32-M33) -> -0.0014815569 | O33: =O32+F33*M33*$B$5 -> 0.97939993 | P33: =IF(E33=1,(1-N33-F33*M33)/O33,"") -> 0.030093594 | Q33: =IF(A33<=$B$9,MIN(A33,$B$10)/$B$10-MAX(0,MIN(A33-1,$B$9)-$B$7)/$B$8,0) -> 1 | R33: =IF(AND(A33>$B$7,A33<=$B$9),1/$B$8,0) -> 0 | S33: =IF(A33<=$B$10,1/$B$10,0) -> 0.5 | T33: =F32*M32*S33 -> 0.49339599 | U33: =F33*M33*$B$5*Q33 -> 0.48600395 | V33: =M33/M32 -> 1.0018945 | W33: =(1-V33)*(1+G33-$B$4)/(V33*$B$5) -> -0.0023338726 | X33: =G33/$B$5 -> 0.034266261 | Y33: =X33+W33 -> 0.031932389 | Z33: =U33*(Y33-$E$9) -> -0.0041900625 | AA33: =MAX(0,MIN(1,(B33-$E$4)/$B$5)) -> 0 | AB33: =Z33*AA33 -> 0 | AC33: =Z33-AB33 -> -0.0041900625 | AD33: =Q33*$B$5 -> 0.5 | AE33: =AD33*AA33 -> 0 | AF33: =F33*(M33*(($E$9*$B$5)*Q33+R33)+$B$4*(M32-M33)*Q33) -> 0.018974142 | AG33: =S33 -> 0.5 | AH33: =IF(E33=1,ABS(P33-D33)*10000,0) -> 1.2490009e-12
A34: 3 | B34: =A34/2 -> 1.5 | C34: =ROUNDUP(A34/2,0) -> 2 | D34: =INDEX(Curves!$K$5:$K$34,C34) -> 0.032161411 | E34: =IF(C34<=$B$6,1,0) -> 1 | F34: =Curves!W8 -> 0.95147546 | G34: =Curves!X8 -> 0.017719819 | H34: =N33+D34*O33 -> 0.030017327 | I34: =F35*M33*((D34*$B$5+1)-$B$4) -> 0.57816385 | J34: =M33*(F34*((D34*$B$5)-$B$4)+F35*$B$4) -> 0.0087067249 | K34: =H34+F34*M33*$B$4-1 -> -0.58794908 | L34: =IF(E34=1,-2*LN((-J34+SQRT(J34^2-4*I34*K34))/(2*I34)),L33) -> -0.0018497515 | M34: =M33*EXP(-L34*$B$5) -> 1.0047214 | N34: =N33+F34*$B$4*(M33-M34) -> -0.001835054 | O34: =O33+F34*M34*$B$5 -> 1.4573838 | Q34: =IF(A34<=$B$9,MIN(A34,$B$10)/$B$10-MAX(0,MIN(A34-1,$B$9)-$B$7)/$B$8,0) -> 1 | R34: =IF(AND(A34>$B$7,A34<=$B$9),1/$B$8,0) -> 0.02173913 | S34: =IF(A34<=$B$10,1/$B$10,0) -> 0 | T34: =F33*M33*S34 -> 0 | U34: =F34*M34*$B$5*Q34 -> 0.47798386 | V34: =M34/M33 -> 1.0009253 | W34: =(1-V34)*(1+G34-$B$4)/(V34*$B$5) -> -0.0011420999 | X34: =G34/$B$5 -> 0.035439638 | Y34: =X34+W34 -> 0.034297539 | Z34: =U34*(Y34-$E$9) -> -0.0029904142 | AA34: =MAX(0,MIN(1,(B34-$E$4)/$B$5)) -> 0 | AB34: =Z34*AA34 -> 0 | AC34: =Z34-AB34 -> -0.0029904142 | AD34: =Q34*$B$5 -> 0.5 | AE34: =AD34*AA34 -> 0 | AF34: =F34*(M34*(($E$9*$B$5)*Q34+R34)+$B$4*(M33-M34)*Q34) -> 0.039812494 | AG34: =S34 -> 0 | AH34: 0
A35: 4 | B35: =A35/2 -> 2 | C35: =ROUNDUP(A35/2,0) -> 2 | D35: =INDEX(Curves!$K$5:$K$34,C35) -> 0.032161411 | E35: =IF(C35<=$B$6,1,0) -> 1 | F35: =Curves!W9 -> 0.93490904 | G35: =Curves!X9 -> 0.017719819 | L35: =L34 -> -0.0018497515 | M35: =M34*EXP(-L35*$B$5) -> 1.005651 | N35: =N34+F35*$B$4*(M34-M35) -> -0.0021827176 | O35: =O34+F35*M35*$B$5 -> 1.9274799 | P35: =IF(E35=1,(1-N35-F35*M35)/O35,"") -> 0.032161411 | Q35: =IF(A35<=$B$9,MIN(A35,$B$10)/$B$10-MAX(0,MIN(A35-1,$B$9)-$B$7)/$B$8,0) -> 0.97826087 | R35: =IF(AND(A35>$B$7,A35<=$B$9),1/$B$8,0) -> 0.02173913 | S35: =IF(A35<=$B$10,1/$B$10,0) -> 0 | T35: =F34*M34*S35 -> 0 | U35: =F35*M35*$B$5*Q35 -> 0.45987664 | V35: =M35/M34 -> 1.0009253 | W35: =(1-V35)*(1+G35-$B$4)/(V35*$B$5) -> -0.0011420999 | X35: =G35/$B$5 -> 0.035439638 | Y35: =X35+W35 -> 0.034297539 | Z35: =U35*(Y35-$E$9) -> -0.0028771298 | AA35: =MAX(0,MIN(1,(B35-$E$4)/$B$5)) -> 0 | AB35: =Z35*AA35 -> 0 | AC35: =Z35-AB35 -> -0.0028771298 | AD35: =Q35*$B$5 -> 0.48913043 | AE35: =AD35*AA35 -> 0 | AF35: =F35*(M35*(($E$9*$B$5)*Q35+R35)+$B$4*(M34-M35)*Q35) -> 0.038748623 | AG35: =S35 -> 0 | AH35: =IF(E35=1,ABS(P35-D35)*10000,0) -> 6.9388939e-14
A36: 5 | B36: =A36/2 -> 2.5 | C36: =ROUNDUP(A36/2,0) -> 3 | D36: =INDEX(Curves!$K$5:$K$34,C36) -> 0.033214204 | E36: =IF(C36<=$B$6,1,0) -> 1 | F36: =Curves!W10 -> 0.91890677 | G36: =Curves!X10 -> 0.017414459 | H36: =N35+D36*O35 -> 0.061836994 | I36: =F37*M35*((D36*$B$5+1)-$B$4) -> 0.56005332 | J36: =M35*(F36*((D36*$B$5)-$B$4)+F37*$B$4) -> 0.0090197174 | K36: =H36+F36*M35*$B$4-1 -> -0.56852319 | L36: =IF(E36=1,-2*LN((-J36+SQRT(J36^2-4*I36*K36))/(2*I36)),L35) -> 0.00097441313 | M36: =M35*EXP(-L36*$B$5) -> 1.0051612 | N36: =N35+F36*$B$4*(M35-M36) -> -0.0020026705 | O36: =O35+F36*M36*$B$5 -> 2.3893046 | Q36: =IF(A36<=$B$9,MIN(A36,$B$10)/$B$10-MAX(0,MIN(A36-1,$B$9)-$B$7)/$B$8,0) -> 0.95652174 | R36: =IF(AND(A36>$B$7,A36<=$B$9),1/$B$8,0) -> 0.02173913 | S36: =IF(A36<=$B$10,1/$B$10,0) -> 0 | T36: =F35*M35*S36 -> 0 | U36: =F36*M36*$B$5*Q36 -> 0.44174538 | V36: =M36/M35 -> 0.99951291 | W36: =(1-V36)*(1+G36-$B$4)/(V36*$B$5) -> 0.00060176333 | X36: =G36/$B$5 -> 0.034828919 | Y36: =X36+W36 -> 0.035430682 | Z36: =U36*(Y36-$E$9) -> -0.0022631341 | AA36: =MAX(0,MIN(1,(B36-$E$4)/$B$5)) -> 0 | AB36: =Z36*AA36 -> 0 | AC36: =Z36-AB36 -> -0.0022631341 | AD36: =Q36*$B$5 -> 0.47826087 | AE36: =AD36*AA36 -> 0 | AF36: =F36*(M36*(($E$9*$B$5)*Q36+R36)+$B$4*(M35-M36)*Q36) -> 0.038166029 | AG36: =S36 -> 0 | AH36: 0
A37: 6 | B37: =A37/2 -> 3 | C37: =ROUNDUP(A37/2,0) -> 3 | D37: =INDEX(Curves!$K$5:$K$34,C37) -> 0.033214204 | E37: =IF(C37<=$B$6,1,0) -> 1 | F37: =Curves!W11 -> 0.90317841 | G37: =Curves!X11 -> 0.017414459 | L37: =L36 -> 0.00097441313 | M37: =M36*EXP(-L37*$B$5) -> 1.0046716 | N37: =N36+F37*$B$4*(M36-M37) -> -0.0018257913 | O37: =O36+F37*M37*$B$5 -> 2.8430035 | P37: =IF(E37=1,(1-N37-F37*M37)/O37,"") -> 0.033214204 | Q37: =IF(A37<=$B$9,MIN(A37,$B$10)/$B$10-MAX(0,MIN(A37-1,$B$9)-$B$7)/$B$8,0) -> 0.93478261 | R37: =IF(AND(A37>$B$7,A37<=$B$9),1/$B$8,0) -> 0.02173913 | S37: =IF(A37<=$B$10,1/$B$10,0) -> 0 | T37: =F36*M36*S37 -> 0 | U37: =F37*M37*$B$5*Q37 -> 0.42410979 | V37: =M37/M36 -> 0.99951291 | W37: =(1-V37)*(1+G37-$B$4)/(V37*$B$5) -> 0.00060176333 | X37: =G37/$B$5 -> 0.034828919 | Y37: =X37+W37 -> 0.035430682 | Z37: =U37*(Y37-$E$9) -> -0.0021727841 | AA37: =MAX(0,MIN(1,(B37-$E$4)/$B$5)) -> 0 | AB37: =Z37*AA37 -> 0 | AC37: =Z37-AB37 -> -0.0021727841 | AD37: =Q37*$B$5 -> 0.4673913 | AE37: =AD37*AA37 -> 0 | AF37: =F37*(M37*(($E$9*$B$5)*Q37+R37)+$B$4*(M36-M37)*Q37) -> 0.037090664 | AG37: =S37 -> 0 | AH37: =IF(E37=1,ABS(P37-D37)*10000,0) -> 6.9388939e-14
A38: 7 | B38: =A38/2 -> 3.5 | C38: =ROUNDUP(A38/2,0) -> 4 | D38: =INDEX(Curves!$K$5:$K$34,C38) -> 0.034020649 | E38: =IF(C38<=$B$6,1,0) -> 1 | F38: =Curves!W12 -> 0.88817134 | G38: =Curves!X12 -> 0.016896594 | H38: =N37+D38*O37 -> 0.094895032 | I38: =F39*M37*((D38*$B$5+1)-$B$4) -> 0.54142277 | J38: =M37*(F38*((D38*$B$5)-$B$4)+F39*$B$4) -> 0.0092479984 | K38: =H38+F38*M37*$B$4-1 -> -0.54817676 | L38: =IF(E38=1,-2*LN((-J38+SQRT(J38^2-4*I38*K38))/(2*I38)),L37) -> 0.004577804 | M38: =M37*EXP(-L38*$B$5) -> 1.0023746 | N38: =N37+F38*$B$4*(M37-M38) -> -0.0010097519 | O38: =O37+F38*M38*$B$5 -> 3.2881437 | Q38: =IF(A38<=$B$9,MIN(A38,$B$10)/$B$10-MAX(0,MIN(A38-1,$B$9)-$B$7)/$B$8,0) -> 0.91304348 | R38: =IF(AND(A38>$B$7,A38<=$B$9),1/$B$8,0) -> 0.02173913 | S38: =IF(A38<=$B$10,1/$B$10,0) -> 0 | T38: =F37*M37*S38 -> 0 | U38: =F38*M38*$B$5*Q38 -> 0.40643236 | V38: =M38/M37 -> 0.99771372 | W38: =(1-V38)*(1+G38-$B$4)/(V38*$B$5) -> 0.0028272661 | X38: =G38/$B$5 -> 0.033793189 | Y38: =X38+W38 -> 0.036620455 | Z38: =U38*(Y38-$E$9) -> -0.0015986577 | AA38: =MAX(0,MIN(1,(B38-$E$4)/$B$5)) -> 0 | AB38: =Z38*AA38 -> 0 | AC38: =Z38-AB38 -> -0.0015986577 | AD38: =Q38*$B$5 -> 0.45652174 | AE38: =AD38*AA38 -> 0 | AF38: =F38*(M38*(($E$9*$B$5)*Q38+R38)+$B$4*(M37-M38)*Q38) -> 0.036581397 | AG38: =S38 -> 0 | AH38: 0
A39: 8 | B39: =A39/2 -> 4 | C39: =ROUNDUP(A39/2,0) -> 4 | D39: =INDEX(Curves!$K$5:$K$34,C39) -> 0.034020649 | E39: =IF(C39<=$B$6,1,0) -> 1 | F39: =Curves!W13 -> 0.87341362 | G39: =Curves!X13 -> 0.016896594 | L39: =L38 -> 0.004577804 | M39: =M38*EXP(-L39*$B$5) -> 1.0000829 | N39: =N38+F39*$B$4*(M38-M39) -> -0.00020910642 | O39: =O38+F39*M39*$B$5 -> 3.7248867 | P39: =IF(E39=1,(1-N39-F39*M39)/O39,"") -> 0.034020649 | Q39: =IF(A39<=$B$9,MIN(A39,$B$10)/$B$10-MAX(0,MIN(A39-1,$B$9)-$B$7)/$B$8,0) -> 0.89130435 | R39: =IF(AND(A39>$B$7,A39<=$B$9),1/$B$8,0) -> 0.02173913 | S39: =IF(A39<=$B$10,1/$B$10,0) -> 0 | T39: =F38*M38*S39 -> 0 | U39: =F39*M39*$B$5*Q39 -> 0.38927095 | V39: =M39/M38 -> 0.99771372 | W39: =(1-V39)*(1+G39-$B$4)/(V39*$B$5) -> 0.0028272661 | X39: =G39/$B$5 -> 0.033793189 | Y39: =X39+W39 -> 0.036620455 | Z39: =U39*(Y39-$E$9) -> -0.0015311552 | AA39: =MAX(0,MIN(1,(B39-$E$4)/$B$5)) -> 0 | AB39: =Z39*AA39 -> 0 | AC39: =Z39-AB39 -> -0.0015311552 | AD39: =Q39*$B$5 -> 0.44565217 | AE39: =AD39*AA39 -> 0 | AF39: =F39*(M39*(($E$9*$B$5)*Q39+R39)+$B$4*(M38-M39)*Q39) -> 0.03548888 | AG39: =S39 -> 0 | AH39: =IF(E39=1,ABS(P39-D39)*10000,0) -> 2.0816682e-13
A40: 9 | B40: =A40/2 -> 4.5 | C40: =ROUNDUP(A40/2,0) -> 5 | D40: =INDEX(Curves!$K$5:$K$34,C40) -> 0.034915232 | E40: =IF(C40<=$B$6,1,0) -> 1 | F40: =Curves!W14 -> 0.85876771 | G40: =Curves!X14 -> 0.017054571 | H40: =N39+D40*O39 -> 0.12984618 | I40: =F41*M39*((D40*$B$5+1)-$B$4) -> 0.5214043 | J40: =M39*(F40*((D40*$B$5)-$B$4)+F41*$B$4) -> 0.0092326729 | K40: =H40+F40*M39*$B$4-1 -> -0.52661826 | L40: =IF(E40=1,-2*LN((-J40+SQRT(J40^2-4*I40*K40))/(2*I40)),L39) -> 0.0076690494 | M40: =M39*EXP(-L40*$B$5) -> 0.99625542 | N40: =N39+F40*$B$4*(M39-M40) -> 0.0011056668 | O40: =O39+F40*M40*$B$5 -> 4.1526627 | Q40: =IF(A40<=$B$9,MIN(A40,$B$10)/$B$10-MAX(0,MIN(A40-1,$B$9)-$B$7)/$B$8,0) -> 0.86956522 | R40: =IF(AND(A40>$B$7,A40<=$B$9),1/$B$8,0) -> 0.02173913 | S40: =IF(A40<=$B$10,1/$B$10,0) -> 0 | T40: =F39*M39*S40 -> 0 | U40: =F40*M40*$B$5*Q40 -> 0.37197912 | V40: =M40/M39 -> 0.99617282 | W40: =(1-V40)*(1+G40-$B$4)/(V40*$B$5) -> 0.0047413065 | X40: =G40/$B$5 -> 0.034109142 | Y40: =X40+W40 -> 0.038850448 | Z40: =U40*(Y40-$E$9) -> -0.0006336286 | AA40: =MAX(0,MIN(1,(B40-$E$4)/$B$5)) -> 0 | AB40: =Z40*AA40 -> 0 | AC40: =Z40-AB40 -> -0.0006336286 | AD40: =Q40*$B$5 -> 0.43478261 | AE40: =AD40*AA40 -> 0 | AF40: =F40*(M40*(($E$9*$B$5)*Q40+R40)+$B$4*(M39-M40)*Q40) -> 0.034827421 | AG40: =S40 -> 0 | AH40: 0
A41: 10 | B41: =A41/2 -> 5 | C41: =ROUNDUP(A41/2,0) -> 5 | D41: =INDEX(Curves!$K$5:$K$34,C41) -> 0.034915232 | E41: =IF(C41<=$B$6,1,0) -> 1 | F41: =Curves!W15 -> 0.84436739 | G41: =Curves!X15 -> 0.017054571 | L41: =L40 -> 0.0076690494 | M41: =M40*EXP(-L41*$B$5) -> 0.99244256 | N41: =N40+F41*$B$4*(M40-M41) -> 0.0023934457 | O41: =O40+F41*M41*$B$5 -> 4.5716558 | P41: =IF(E41=1,(1-N41-F41*M41)/O41,"") -> 0.034915232 | Q41: =IF(A41<=$B$9,MIN(A41,$B$10)/$B$10-MAX(0,MIN(A41-1,$B$9)-$B$7)/$B$8,0) -> 0.84782609 | R41: =IF(AND(A41>$B$7,A41<=$B$9),1/$B$8,0) -> 0.02173913 | S41: =IF(A41<=$B$10,1/$B$10,0) -> 0 | T41: =F40*M40*S41 -> 0 | U41: =F41*M41*$B$5*Q41 -> 0.35523325 | V41: =M41/M40 -> 0.99617282 | W41: =(1-V41)*(1+G41-$B$4)/(V41*$B$5) -> 0.0047413065 | X41: =G41/$B$5 -> 0.034109142 | Y41: =X41+W41 -> 0.038850448 | Z41: =U41*(Y41-$E$9) -> -0.00060510371 | AA41: =MAX(0,MIN(1,(B41-$E$4)/$B$5)) -> 0 | AB41: =Z41*AA41 -> 0 | AC41: =Z41-AB41 -> -0.00060510371 | AD41: =Q41*$B$5 -> 0.42391304 | AE41: =AD41*AA41 -> 0 | AF41: =F41*(M41*(($E$9*$B$5)*Q41+R41)+$B$4*(M40-M41)*Q41) -> 0.033714977 | AG41: =S41 -> 0 | AH41: =IF(E41=1,ABS(P41-D41)*10000,0) -> 1.3877788e-13
A42: 11 | B42: =A42/2 -> 5.5 | C42: =ROUNDUP(A42/2,0) -> 6 | D42: =INDEX(Curves!$K$5:$K$34,C42) -> 0.03565223 | E42: =IF(C42<=$B$6,1,0) -> 1 | F42: =Curves!W16 -> 0.83020854 | G42: =Curves!X16 -> 0.017054571 | H42: =N41+D42*O41 -> 0.16538317 | I42: =F43*M41*((D42*$B$5+1)-$B$4) -> 0.5005121 | J42: =M41*(F42*((D42*$B$5)-$B$4)+F43*$B$4) -> 0.0091610608 | K42: =H42+F42*M41*$B$4-1 -> -0.50504312 | L42: =IF(E42=1,-2*LN((-J42+SQRT(J42^2-4*I42*K42))/(2*I42)),L41) -> 0.0092088031 | M42: =M41*EXP(-L42*$B$5) -> 0.98788346 | N42: =N41+F42*$B$4*(M41-M42) -> 0.0039074472 | O42: =O41+F42*M42*$B$5 -> 4.9817304 | Q42: =IF(A42<=$B$9,MIN(A42,$B$10)/$B$10-MAX(0,MIN(A42-1,$B$9)-$B$7)/$B$8,0) -> 0.82608696 | R42: =IF(AND(A42>$B$7,A42<=$B$9),1/$B$8,0) -> 0.02173913 | S42: =IF(A42<=$B$10,1/$B$10,0) -> 0 | T42: =F41*M41*S42 -> 0 | U42: =F42*M42*$B$5*Q42 -> 0.33875731 | V42: =M42/M41 -> 0.99540618 | W42: =(1-V42)*(1+G42-$B$4)/(V42*$B$5) -> 0.005695436 | X42: =G42/$B$5 -> 0.034109142 | Y42: =X42+W42 -> 0.039804578 | Z42: =U42*(Y42-$E$9) -> -0.00025382028 | AA42: =MAX(0,MIN(1,(B42-$E$4)/$B$5)) -> 0 | AB42: =Z42*AA42 -> 0 | AC42: =Z42-AB42 -> -0.00025382028 | AD42: =Q42*$B$5 -> 0.41304348 | AE42: =AD42*AA42 -> 0 | AF42: =F42*(M42*(($E$9*$B$5)*Q42+R42)+$B$4*(M41-M42)*Q42) -> 0.032817941 | AG42: =S42 -> 0 | AH42: 0
A43: 12 | B43: =A43/2 -> 6 | C43: =ROUNDUP(A43/2,0) -> 6 | D43: =INDEX(Curves!$K$5:$K$34,C43) -> 0.03565223 | E43: =IF(C43<=$B$6,1,0) -> 1 | F43: =Curves!W17 -> 0.81628711 | G43: =Curves!X17 -> 0.017054571 | L43: =L42 -> 0.0092088031 | M43: =M42*EXP(-L43*$B$5) -> 0.98334531 | N43: =N42+F43*$B$4*(M42-M43) -> 0.0053892226 | O43: =O42+F43*M43*$B$5 -> 5.3830765 | P43: =IF(E43=1,(1-N43-F43*M43)/O43,"") -> 0.03565223 | Q43: =IF(A43<=$B$9,MIN(A43,$B$10)/$B$10-MAX(0,MIN(A43-1,$B$9)-$B$7)/$B$8,0) -> 0.80434783 | R43: =IF(AND(A43>$B$7,A43<=$B$9),1/$B$8,0) -> 0.02173913 | S43: =IF(A43<=$B$10,1/$B$10,0) -> 0 | T43: =F42*M42*S43 -> 0 | U43: =F43*M43*$B$5*Q43 -> 0.32282182 | V43: =M43/M42 -> 0.99540618 | W43: =(1-V43)*(1+G43-$B$4)/(V43*$B$5) -> 0.005695436 | X43: =G43/$B$5 -> 0.034109142 | Y43: =X43+W43 -> 0.039804578 | Z43: =U43*(Y43-$E$9) -> -0.00024188031 | AA43: =MAX(0,MIN(1,(B43-$E$4)/$B$5)) -> 0 | AB43: =Z43*AA43 -> 0 | AC43: =Z43-AB43 -> -0.00024188031 | AD43: =Q43*$B$5 -> 0.40217391 | AE43: =AD43*AA43 -> 0 | AF43: =F43*(M43*(($E$9*$B$5)*Q43+R43)+$B$4*(M42-M43)*Q43) -> 0.031733358 | AG43: =S43 -> 0 | AH43: =IF(E43=1,ABS(P43-D43)*10000,0) -> 3.469447e-13
A44: 13 | B44: =A44/2 -> 6.5 | C44: =ROUNDUP(A44/2,0) -> 7 | D44: =INDEX(Curves!$K$5:$K$34,C44) -> 0.036919242 | E44: =IF(C44<=$B$6,1,0) -> 1 | F44: =Curves!W18 -> 0.80259913 | G44: =Curves!X18 -> 0.017054571 | H44: =N43+D44*O43 -> 0.20412833 | I44: =F45*M43*((D44*$B$5+1)-$B$4) -> 0.47992329 | J44: =M43*(F44*((D44*$B$5)-$B$4)+F45*$B$4) -> 0.0092752017 | K44: =H44+F44*M43*$B$4-1 -> -0.48017884 | L44: =IF(E44=1,-2*LN((-J44+SQRT(J44^2-4*I44*K44))/(2*I44)),L43) -> 0.018788646 | M44: =M43*EXP(-L44*$B$5) -> 0.9741507 | N44: =N43+F44*$B$4*(M43-M44) -> 0.008341056 | O44: =O43+F44*M44*$B$5 -> 5.7740027 | Q44: =IF(A44<=$B$9,MIN(A44,$B$10)/$B$10-MAX(0,MIN(A44-1,$B$9)-$B$7)/$B$8,0) -> 0.7826087 | R44: =IF(AND(A44>$B$7,A44<=$B$9),1/$B$8,0) -> 0.02173913 | S44: =IF(A44<=$B$10,1/$B$10,0) -> 0 | T44: =F43*M43*S44 -> 0 | U44: =F44*M44*$B$5*Q44 -> 0.30594228 | V44: =M44/M43 -> 0.99064967 | W44: =(1-V44)*(1+G44-$B$4)/(V44*$B$5) -> 0.011648248 | X44: =G44/$B$5 -> 0.034109142 | Y44: =X44+W44 -> 0.045757389 | Z44: =U44*(Y44-$E$9) -> 0.0015919838 | AA44: =MAX(0,MIN(1,(B44-$E$4)/$B$5)) -> 0 | AB44: =Z44*AA44 -> 0 | AC44: =Z44-AB44 -> 0.0015919838 | AD44: =Q44*$B$5 -> 0.39130435 | AE44: =AD44*AA44 -> 0 | AF44: =F44*(M44*(($E$9*$B$5)*Q44+R44)+$B$4*(M43-M44)*Q44) -> 0.03171406 | AG44: =S44 -> 0 | AH44: 0
A45: 14 | B45: =A45/2 -> 7 | C45: =ROUNDUP(A45/2,0) -> 7 | D45: =INDEX(Curves!$K$5:$K$34,C45) -> 0.036919242 | E45: =IF(C45<=$B$6,1,0) -> 1 | F45: =Curves!W19 -> 0.78914067 | G45: =Curves!X19 -> 0.017054571 | L45: =L44 -> 0.018788646 | M45: =M44*EXP(-L45*$B$5) -> 0.96504207 | N45: =N44+F45*$B$4*(M44-M45) -> 0.011216254 | O45: =O44+F45*M45*$B$5 -> 6.1547797 | P45: =IF(E45=1,(1-N45-F45*M45)/O45,"") -> 0.036919242 | Q45: =IF(A45<=$B$9,MIN(A45,$B$10)/$B$10-MAX(0,MIN(A45-1,$B$9)-$B$7)/$B$8,0) -> 0.76086957 | R45: =IF(AND(A45>$B$7,A45<=$B$9),1/$B$8,0) -> 0.02173913 | S45: =IF(A45<=$B$10,1/$B$10,0) -> 0 | T45: =F44*M44*S45 -> 0 | U45: =F45*M45*$B$5*Q45 -> 0.28972161 | V45: =M45/M44 -> 0.99064967 | W45: =(1-V45)*(1+G45-$B$4)/(V45*$B$5) -> 0.011648248 | X45: =G45/$B$5 -> 0.034109142 | Y45: =X45+W45 -> 0.045757389 | Z45: =U45*(Y45-$E$9) -> 0.0015075789 | AA45: =MAX(0,MIN(1,(B45-$E$4)/$B$5)) -> 0 | AB45: =Z45*AA45 -> 0 | AC45: =Z45-AB45 -> 0.0015075789 | AD45: =Q45*$B$5 -> 0.38043478 | AE45: =AD45*AA45 -> 0 | AF45: =F45*(M45*(($E$9*$B$5)*Q45+R45)+$B$4*(M44-M45)*Q45) -> 0.030492496 | AG45: =S45 -> 0 | AH45: =IF(E45=1,ABS(P45-D45)*10000,0) -> 2.7755576e-13
A46: 15 | B46: =A46/2 -> 7.5 | C46: =ROUNDUP(A46/2,0) -> 8 | D46: =INDEX(Curves!$K$5:$K$34,C46) -> 0.037684961 | E46: =IF(C46<=$B$6,1,0) -> 1 | F46: =Curves!W20 -> 0.77556901 | G46: =Curves!X20 -> 0.017498978 | H46: =N45+D46*O45 -> 0.24315889 | I46: =F47*M45*((D46*$B$5+1)-$B$4) -> 0.45521108 | J46: =M45*(F46*((D46*$B$5)-$B$4)+F47*$B$4) -> 0.0089539886 | K46: =H46+F46*M45*$B$4-1 -> -0.45745843 | L46: =IF(E46=1,-2*LN((-J46+SQRT(J46^2-4*I46*K46))/(2*I46)),L45) -> 0.014696495 | M46: =M45*EXP(-L46*$B$5) -> 0.95797669 | N46: =N45+F46*$B$4*(M45-M46) -> 0.013408129 | O46: =O45+F46*M46*$B$5 -> 6.5262682 | Q46: =IF(A46<=$B$9,MIN(A46,$B$10)/$B$10-MAX(0,MIN(A46-1,$B$9)-$B$7)/$B$8,0) -> 0.73913043 | R46: =IF(AND(A46>$B$7,A46<=$B$9),1/$B$8,0) -> 0.02173913 | S46: =IF(A46<=$B$10,1/$B$10,0) -> 0 | T46: =F45*M45*S46 -> 0 | U46: =F46*M46*$B$5*Q46 -> 0.27457847 | V46: =M46/M45 -> 0.99267868 | W46: =(1-V46)*(1+G46-$B$4)/(V46*$B$5) -> 0.0091084953 | X46: =G46/$B$5 -> 0.034997956 | Y46: =X46+W46 -> 0.044106451 | Z46: =U46*(Y46-$E$9) -> 0.00097546877 | AA46: =MAX(0,MIN(1,(B46-$E$4)/$B$5)) -> 0 | AB46: =Z46*AA46 -> 0 | AC46: =Z46-AB46 -> 0.00097546877 | AD46: =Q46*$B$5 -> 0.36956522 | AE46: =AD46*AA46 -> 0 | AF46: =F46*(M46*(($E$9*$B$5)*Q46+R46)+$B$4*(M45-M46)*Q46) -> 0.028906969 | AG46: =S46 -> 0 | AH46: 0
A47: 16 | B47: =A47/2 -> 8 | C47: =ROUNDUP(A47/2,0) -> 8 | D47: =INDEX(Curves!$K$5:$K$34,C47) -> 0.037684961 | E47: =IF(C47<=$B$6,1,0) -> 1 | F47: =Curves!W21 -> 0.76223075 | G47: =Curves!X21 -> 0.017498978 | L47: =L46 -> 0.014696495 | M47: =M46*EXP(-L47*$B$5) -> 0.95096304 | N47: =N46+F47*$B$4*(M46-M47) -> 0.015546536 | O47: =O46+F47*M47*$B$5 -> 6.8886948 | P47: =IF(E47=1,(1-N47-F47*M47)/O47,"") -> 0.037684961 | Q47: =IF(A47<=$B$9,MIN(A47,$B$10)/$B$10-MAX(0,MIN(A47-1,$B$9)-$B$7)/$B$8,0) -> 0.7173913 | R47: =IF(AND(A47>$B$7,A47<=$B$9),1/$B$8,0) -> 0.02173913 | S47: =IF(A47<=$B$10,1/$B$10,0) -> 0 | T47: =F46*M46*S47 -> 0 | U47: =F47*M47*$B$5*Q47 -> 0.26000172 | V47: =M47/M46 -> 0.99267868 | W47: =(1-V47)*(1+G47-$B$4)/(V47*$B$5) -> 0.0091084953 | X47: =G47/$B$5 -> 0.034997956 | Y47: =X47+W47 -> 0.044106451 | Z47: =U47*(Y47-$E$9) -> 0.00092368333 | AA47: =MAX(0,MIN(1,(B47-$E$4)/$B$5)) -> 0 | AB47: =Z47*AA47 -> 0 | AC47: =Z47-AB47 -> 0.00092368333 | AD47: =Q47*$B$5 -> 0.35869565 | AE47: =AD47*AA47 -> 0 | AF47: =F47*(M47*(($E$9*$B$5)*Q47+R47)+$B$4*(M46-M47)*Q47) -> 0.027835824 | AG47: =S47 -> 0 | AH47: =IF(E47=1,ABS(P47-D47)*10000,0) -> 0
A48: 17 | B48: =A48/2 -> 8.5 | C48: =ROUNDUP(A48/2,0) -> 9 | D48: =INDEX(Curves!$K$5:$K$34,C48) -> 0.038509259 | E48: =IF(C48<=$B$6,1,0) -> 1 | F48: =Curves!W22 -> 0.74903791 | G48: =Curves!X22 -> 0.017613041 | H48: =N47+D48*O47 -> 0.28082507 | I48: =F49*M47*((D48*$B$5+1)-$B$4) -> 0.433465 | J48: =M47*(F48*((D48*$B$5)-$B$4)+F49*$B$4) -> 0.0087837138 | K48: =H48+F48*M47*$B$4-1 -> -0.43425198 | L48: =IF(E48=1,-2*LN((-J48+SQRT(J48^2-4*I48*K48))/(2*I48)),L47) -> 0.018431322 | M48: =M47*EXP(-L48*$B$5) -> 0.94223955 | N48: =N47+F48*$B$4*(M47-M48) -> 0.018160228 | O48: =O47+F48*M48*$B$5 -> 7.2415814 | Q48: =IF(A48<=$B$9,MIN(A48,$B$10)/$B$10-MAX(0,MIN(A48-1,$B$9)-$B$7)/$B$8,0) -> 0.69565217 | R48: =IF(AND(A48>$B$7,A48<=$B$9),1/$B$8,0) -> 0.02173913 | S48: =IF(A48<=$B$10,1/$B$10,0) -> 0 | T48: =F47*M47*S48 -> 0 | U48: =F48*M48*$B$5*Q48 -> 0.24548631 | V48: =M48/M47 -> 0.99082667 | W48: =(1-V48)*(1+G48-$B$4)/(V48*$B$5) -> 0.011436039 | X48: =G48/$B$5 -> 0.035226082 | Y48: =X48+W48 -> 0.046662121 | Z48: =U48*(Y48-$E$9) -> 0.0014994978 | AA48: =MAX(0,MIN(1,(B48-$E$4)/$B$5)) -> 0 | AB48: =Z48*AA48 -> 0 | AC48: =Z48-AB48 -> 0.0014994978 | AD48: =Q48*$B$5 -> 0.34782609 | AE48: =AD48*AA48 -> 0 | AF48: =F48*(M48*(($E$9*$B$5)*Q48+R48)+$B$4*(M47-M48)*Q48) -> 0.027116529 | AG48: =S48 -> 0 | AH48: 0
A49: 18 | B49: =A49/2 -> 9 | C49: =ROUNDUP(A49/2,0) -> 9 | D49: =INDEX(Curves!$K$5:$K$34,C49) -> 0.038509259 | E49: =IF(C49<=$B$6,1,0) -> 1 | F49: =Curves!W23 -> 0.73607342 | G49: =Curves!X23 -> 0.017613041 | L49: =L48 -> 0.018431322 | M49: =M48*EXP(-L49*$B$5) -> 0.93359607 | N49: =N48+F49*$B$4*(M48-M49) -> 0.020705119 | O49: =O48+F49*M49*$B$5 -> 7.585179 | P49: =IF(E49=1,(1-N49-F49*M49)/O49,"") -> 0.038509259 | Q49: =IF(A49<=$B$9,MIN(A49,$B$10)/$B$10-MAX(0,MIN(A49-1,$B$9)-$B$7)/$B$8,0) -> 0.67391304 | R49: =IF(AND(A49>$B$7,A49<=$B$9),1/$B$8,0) -> 0.02173913 | S49: =IF(A49<=$B$10,1/$B$10,0) -> 0 | T49: =F48*M48*S49 -> 0 | U49: =F49*M49*$B$5*Q49 -> 0.23155492 | V49: =M49/M48 -> 0.99082667 | W49: =(1-V49)*(1+G49-$B$4)/(V49*$B$5) -> 0.011436039 | X49: =G49/$B$5 -> 0.035226082 | Y49: =X49+W49 -> 0.046662121 | Z49: =U49*(Y49-$E$9) -> 0.0014144011 | AA49: =MAX(0,MIN(1,(B49-$E$4)/$B$5)) -> 0 | AB49: =Z49*AA49 -> 0 | AC49: =Z49-AB49 -> 0.0014144011 | AD49: =Q49*$B$5 -> 0.33695652 | AE49: =AD49*AA49 -> 0 | AF49: =F49*(M49*(($E$9*$B$5)*Q49+R49)+$B$4*(M48-M49)*Q49) -> 0.026044506 | AG49: =S49 -> 0 | AH49: =IF(E49=1,ABS(P49-D49)*10000,0) -> 6.9388939e-14
A50: 19 | B50: =A50/2 -> 9.5 | C50: =ROUNDUP(A50/2,0) -> 10 | D50: =INDEX(Curves!$K$5:$K$34,C50) -> 0.039038989 | E50: =IF(C50<=$B$6,1,0) -> 1 | F50: =Curves!W24 -> 0.72325054 | G50: =Curves!X24 -> 0.017729519 | H50: =N49+D50*O49 -> 0.31682284 | I50: =F51*M49*((D50*$B$5+1)-$B$4) -> 0.41102703 | J50: =M49*(F50*((D50*$B$5)-$B$4)+F51*$B$4) -> 0.0084748908 | K50: =H50+F50*M49*$B$4-1 -> -0.41308761 | L50: =IF(E50=1,-2*LN((-J50+SQRT(J50^2-4*I50*K50))/(2*I50)),L49) -> 0.015566243 | M50: =M49*EXP(-L50*$B$5) -> 0.92635799 | N50: =N49+F50*$B$4*(M49-M50) -> 0.0227991 | O50: =O49+F50*M50*$B$5 -> 7.9201735 | Q50: =IF(A50<=$B$9,MIN(A50,$B$10)/$B$10-MAX(0,MIN(A50-1,$B$9)-$B$7)/$B$8,0) -> 0.65217391 | R50: =IF(AND(A50>$B$7,A50<=$B$9),1/$B$8,0) -> 0.02173913 | S50: =IF(A50<=$B$10,1/$B$10,0) -> 0 | T50: =F49*M49*S50 -> 0 | U50: =F50*M50*$B$5*Q50 -> 0.21847464 | V50: =M50/M49 -> 0.99224709 | W50: =(1-V50)*(1+G50-$B$4)/(V50*$B$5) -> 0.0096532451 | X50: =G50/$B$5 -> 0.035459037 | Y50: =X50+W50 -> 0.045112282 | Z50: =U50*(Y50-$E$9) -> 0.00099590265 | AA50: =MAX(0,MIN(1,(B50-$E$4)/$B$5)) -> 0 | AB50: =Z50*AA50 -> 0 | AC50: =Z50-AB50 -> 0.00099590265 | AD50: =Q50*$B$5 -> 0.32608696 | AE50: =AD50*AA50 -> 0 | AF50: =F50*(M50*(($E$9*$B$5)*Q50+R50)+$B$4*(M49-M50)*Q50) -> 0.024790603 | AG50: =S50 -> 0 | AH50: 0
A51: 20 | B51: =A51/2 -> 10 | C51: =ROUNDUP(A51/2,0) -> 10 | D51: =INDEX(Curves!$K$5:$K$34,C51) -> 0.039038989 | E51: =IF(C51<=$B$6,1,0) -> 1 | F51: =Curves!W25 -> 0.71065104 | G51: =Curves!X25 -> 0.017729519 | L51: =L50 -> 0.015566243 | M51: =M50*EXP(-L51*$B$5) -> 0.91917601 | N51: =N50+F51*$B$4*(M50-M51) -> 0.02484065 | O51: =O50+F51*M51*$B$5 -> 8.2467802 | P51: =IF(E51=1,(1-N51-F51*M51)/O51,"") -> 0.039038989 | Q51: =IF(A51<=$B$9,MIN(A51,$B$10)/$B$10-MAX(0,MIN(A51-1,$B$9)-$B$7)/$B$8,0) -> 0.63043478 | R51: =IF(AND(A51>$B$7,A51<=$B$9),1/$B$8,0) -> 0.02173913 | S51: =IF(A51<=$B$10,1/$B$10,0) -> 0 | T51: =F50*M50*S51 -> 0 | U51: =F51*M51*$B$5*Q51 -> 0.20590422 | V51: =M51/M50 -> 0.99224709 | W51: =(1-V51)*(1+G51-$B$4)/(V51*$B$5) -> 0.0096532451 | X51: =G51/$B$5 -> 0.035459037 | Y51: =X51+W51 -> 0.045112282 | Z51: =U51*(Y51-$E$9) -> 0.00093860118 | AA51: =MAX(0,MIN(1,(B51-$E$4)/$B$5)) -> 0 | AB51: =Z51*AA51 -> 0 | AC51: =Z51-AB51 -> 0.00093860118 | AD51: =Q51*$B$5 -> 0.31521739 | AE51: =AD51*AA51 -> 0 | AF51: =F51*(M51*(($E$9*$B$5)*Q51+R51)+$B$4*(M50-M51)*Q51) -> 0.023837563 | AG51: =S51 -> 0 | AH51: =IF(E51=1,ABS(P51-D51)*10000,0) -> 6.9388939e-14
A52: 21 | B52: =A52/2 -> 10.5 | C52: =ROUNDUP(A52/2,0) -> 11 | D52: =INDEX(Curves!$K$5:$K$34,C52) -> 0.039558776 | E52: =IF(C52<=$B$6,1,0) -> 1 | F52: =Curves!W26 -> 0.69827814 | G52: =Curves!X26 -> 0.017719145 | H52: =N51+D52*O51 -> 0.35107318 | I52: =F53*M51*((D52*$B$5+1)-$B$4) -> 0.39087358 | J52: =M51*(F52*((D52*$B$5)-$B$4)+F53*$B$4) -> 0.00822527 | K52: =H52+F52*M51*$B$4-1 -> -0.39219061 | L52: =IF(E52=1,-2*LN((-J52+SQRT(J52^2-4*I52*K52))/(2*I52)),L51) -> 0.017643752 | M52: =M51*EXP(-L52*$B$5) -> 0.91110282 | N52: =N51+F52*$B$4*(M51-M52) -> 0.027095584 | O52: =O51+F52*M52*$B$5 -> 8.5648818 | Q52: =IF(A52<=$B$9,MIN(A52,$B$10)/$B$10-MAX(0,MIN(A52-1,$B$9)-$B$7)/$B$8,0) -> 0.60869565 | R52: =IF(AND(A52>$B$7,A52<=$B$9),1/$B$8,0) -> 0.02173913 | S52: =IF(A52<=$B$10,1/$B$10,0) -> 0 | T52: =F51*M51*S52 -> 0 | U52: =F52*M52*$B$5*Q52 -> 0.19362706 | V52: =M52/M51 -> 0.99121692 | W52: =(1-V52)*(1+G52-$B$4)/(V52*$B$5) -> 0.0109471 | X52: =G52/$B$5 -> 0.035438291 | Y52: =X52+W52 -> 0.04638539 | Z52: =U52*(Y52-$E$9) -> 0.0011291447 | AA52: =MAX(0,MIN(1,(B52-$E$4)/$B$5)) -> 0 | AB52: =Z52*AA52 -> 0 | AC52: =Z52-AB52 -> 0.0011291447 | AD52: =Q52*$B$5 -> 0.30434783 | AE52: =AD52*AA52 -> 0 | AF52: =F52*(M52*(($E$9*$B$5)*Q52+R52)+$B$4*(M51-M52)*Q52) -> 0.023055395 | AG52: =S52 -> 0 | AH52: 0
A53: 22 | B53: =A53/2 -> 11 | C53: =ROUNDUP(A53/2,0) -> 11 | D53: =INDEX(Curves!$K$5:$K$34,C53) -> 0.039558776 | E53: =IF(C53<=$B$6,1,0) -> 1 | F53: =Curves!W27 -> 0.68612067 | G53: =Curves!X27 -> 0.017719145 | L53: =L52 -> 0.017643752 | M53: =M52*EXP(-L53*$B$5) -> 0.90310053 | N53: =N52+F53*$B$4*(M52-M53) -> 0.029291798 | O53: =O52+F53*M53*$B$5 -> 8.8746997 | P53: =IF(E53=1,(1-N53-F53*M53)/O53,"") -> 0.039558776 | Q53: =IF(A53<=$B$9,MIN(A53,$B$10)/$B$10-MAX(0,MIN(A53-1,$B$9)-$B$7)/$B$8,0) -> 0.58695652 | R53: =IF(AND(A53>$B$7,A53<=$B$9),1/$B$8,0) -> 0.02173913 | S53: =IF(A53<=$B$10,1/$B$10,0) -> 0 | T53: =F52*M52*S53 -> 0 | U53: =F53*M53*$B$5*Q53 -> 0.18184968 | V53: =M53/M52 -> 0.99121692 | W53: =(1-V53)*(1+G53-$B$4)/(V53*$B$5) -> 0.0109471 | X53: =G53/$B$5 -> 0.035438291 | Y53: =X53+W53 -> 0.04638539 | Z53: =U53*(Y53-$E$9) -> 0.0010604644 | AA53: =MAX(0,MIN(1,(B53-$E$4)/$B$5)) -> 0 | AB53: =Z53*AA53 -> 0 | AC53: =Z53-AB53 -> 0.0010604644 | AD53: =Q53*$B$5 -> 0.29347826 | AE53: =AD53*AA53 -> 0 | AF53: =F53*(M53*(($E$9*$B$5)*Q53+R53)+$B$4*(M52-M53)*Q53) -> 0.022134133 | AG53: =S53 -> 0 | AH53: =IF(E53=1,ABS(P53-D53)*10000,0) -> 0
A54: 23 | B54: =A54/2 -> 11.5 | C54: =ROUNDUP(A54/2,0) -> 12 | D54: =INDEX(Curves!$K$5:$K$34,C54) -> 0.04022221 | E54: =IF(C54<=$B$6,1,0) -> 1 | F54: =Curves!W28 -> 0.67411049 | G54: =Curves!X28 -> 0.017816333 | H54: =N53+D54*O53 -> 0.38625184 | I54: =F55*M53*((D54*$B$5+1)-$B$4) -> 0.37090892 | J54: =M53*(F54*((D54*$B$5)-$B$4)+F55*$B$4) -> 0.0079808158 | K54: =H54+F54*M53*$B$4-1 -> -0.37023235 | L54: =IF(E54=1,-2*LN((-J54+SQRT(J54^2-4*I54*K54))/(2*I54)),L53) -> 0.023361921 | M54: =M53*EXP(-L54*$B$5) -> 0.89261282 | N54: =N53+F54*$B$4*(M53-M54) -> 0.032119748 | O54: =O53+F54*M54*$B$5 -> 9.1755596 | Q54: =IF(A54<=$B$9,MIN(A54,$B$10)/$B$10-MAX(0,MIN(A54-1,$B$9)-$B$7)/$B$8,0) -> 0.56521739 | R54: =IF(AND(A54>$B$7,A54<=$B$9),1/$B$8,0) -> 0.02173913 | S54: =IF(A54<=$B$10,1/$B$10,0) -> 0 | T54: =F53*M53*S54 -> 0 | U54: =F54*M54*$B$5*Q54 -> 0.17005121 | V54: =M54/M53 -> 0.988387 | W54: =(1-V54)*(1+G54-$B$4)/(V54*$B$5) -> 0.014518003 | X54: =G54/$B$5 -> 0.035632666 | Y54: =X54+W54 -> 0.050150669 | Z54: =U54*(Y54-$E$9) -> 0.0016319513 | AA54: =MAX(0,MIN(1,(B54-$E$4)/$B$5)) -> 0 | AB54: =Z54*AA54 -> 0 | AC54: =Z54-AB54 -> 0.0016319513 | AD54: =Q54*$B$5 -> 0.2826087 | AE54: =AD54*AA54 -> 0 | AF54: =F54*(M54*(($E$9*$B$5)*Q54+R54)+$B$4*(M53-M54)*Q54) -> 0.0215755 | AG54: =S54 -> 0 | AH54: 0
A55: 24 | B55: =A55/2 -> 12 | C55: =ROUNDUP(A55/2,0) -> 12 | D55: =INDEX(Curves!$K$5:$K$34,C55) -> 0.04022221 | E55: =IF(C55<=$B$6,1,0) -> 1 | F55: =Curves!W29 -> 0.66231055 | G55: =Curves!X29 -> 0.017816333 | L55: =L54 -> 0.023361921 | M55: =M54*EXP(-L55*$B$5) -> 0.88224691 | N55: =N54+F55*$B$4*(M54-M55) -> 0.03486593 | O55: =O54+F55*M55*$B$5 -> 9.4677203 | P55: =IF(E55=1,(1-N55-F55*M55)/O55,"") -> 0.04022221 | Q55: =IF(A55<=$B$9,MIN(A55,$B$10)/$B$10-MAX(0,MIN(A55-1,$B$9)-$B$7)/$B$8,0) -> 0.54347826 | R55: =IF(AND(A55>$B$7,A55<=$B$9),1/$B$8,0) -> 0.02173913 | S55: =IF(A55<=$B$10,1/$B$10,0) -> 0 | T55: =F54*M54*S55 -> 0 | U55: =F55*M55*$B$5*Q55 -> 0.158783 | V55: =M55/M54 -> 0.988387 | W55: =(1-V55)*(1+G55-$B$4)/(V55*$B$5) -> 0.014518003 | X55: =G55/$B$5 -> 0.035632666 | Y55: =X55+W55 -> 0.050150669 | Z55: =U55*(Y55-$E$9) -> 0.0015238123 | AA55: =MAX(0,MIN(1,(B55-$E$4)/$B$5)) -> 0 | AB55: =Z55*AA55 -> 0 | AC55: =Z55-AB55 -> 0.0015238123 | AD55: =Q55*$B$5 -> 0.27173913 | AE55: =AD55*AA55 -> 0 | AF55: =F55*(M55*(($E$9*$B$5)*Q55+R55)+$B$4*(M54-M55)*Q55) -> 0.020634391 | AG55: =S55 -> 0 | AH55: =IF(E55=1,ABS(P55-D55)*10000,0) -> 6.9388939e-14
A56: 25 | B56: =A56/2 -> 12.5 | C56: =ROUNDUP(A56/2,0) -> 13 | D56: =INDEX(Curves!$K$5:$K$34,C56) -> 0.040885429 | E56: =IF(C56<=$B$6,1,0) -> 1 | F56: =Curves!W30 -> 0.65065363 | G56: =Curves!X30 -> 0.017915708 | H56: =N55+D56*O55 -> 0.42195773 | I56: =F57*M55*((D56*$B$5+1)-$B$4) -> 0.34988867 | J56: =M55*(F56*((D56*$B$5)-$B$4)+F57*$B$4) -> 0.0076935676 | K56: =H56+F56*M55*$B$4-1 -> -0.34842741 | L56: =IF(E56=1,-2*LN((-J56+SQRT(J56^2-4*I56*K56))/(2*I56)),L55) -> 0.026219335 | M56: =M55*EXP(-L56*$B$5) -> 0.87075643 | N56: =N55+F56*$B$4*(M55-M56) -> 0.037856459 | O56: =O55+F56*M56*$B$5 -> 9.7510007 | Q56: =IF(A56<=$B$9,MIN(A56,$B$10)/$B$10-MAX(0,MIN(A56-1,$B$9)-$B$7)/$B$8,0) -> 0.52173913 | R56: =IF(AND(A56>$B$7,A56<=$B$9),1/$B$8,0) -> 0.02173913 | S56: =IF(A56<=$B$10,1/$B$10,0) -> 0 | T56: =F55*M55*S56 -> 0 | U56: =F56*M56*$B$5*Q56 -> 0.14779848 | V56: =M56/M55 -> 0.98697589 | W56: =(1-V56)*(1+G56-$B$4)/(V56*$B$5) -> 0.016308002 | X56: =G56/$B$5 -> 0.035831417 | Y56: =X56+W56 -> 0.052139418 | Z56: =U56*(Y56-$E$9) -> 0.0017123299 | AA56: =MAX(0,MIN(1,(B56-$E$4)/$B$5)) -> 0 | AB56: =Z56*AA56 -> 0 | AC56: =Z56-AB56 -> 0.0017123299 | AD56: =Q56*$B$5 -> 0.26086957 | AE56: =AD56*AA56 -> 0 | AF56: =F56*(M56*(($E$9*$B$5)*Q56+R56)+$B$4*(M55-M56)*Q56) -> 0.019870613 | AG56: =S56 -> 0 | AH56: 0
A57: 26 | B57: =A57/2 -> 13 | C57: =ROUNDUP(A57/2,0) -> 13 | D57: =INDEX(Curves!$K$5:$K$34,C57) -> 0.040885429 | E57: =IF(C57<=$B$6,1,0) -> 1 | F57: =Curves!W31 -> 0.63920187 | G57: =Curves!X31 -> 0.017915708 | L57: =L56 -> 0.026219335 | M57: =M56*EXP(-L57*$B$5) -> 0.8594156 | N57: =N56+F57*$B$4*(M56-M57) -> 0.04075609 | O57: =O56+F57*M57*$B$5 -> 10.025671 | P57: =IF(E57=1,(1-N57-F57*M57)/O57,"") -> 0.040885429 | Q57: =IF(A57<=$B$9,MIN(A57,$B$10)/$B$10-MAX(0,MIN(A57-1,$B$9)-$B$7)/$B$8,0) -> 0.5 | R57: =IF(AND(A57>$B$7,A57<=$B$9),1/$B$8,0) -> 0.02173913 | S57: =IF(A57<=$B$10,1/$B$10,0) -> 0 | T57: =F56*M56*S57 -> 0 | U57: =F57*M57*$B$5*Q57 -> 0.13733502 | V57: =M57/M56 -> 0.98697589 | W57: =(1-V57)*(1+G57-$B$4)/(V57*$B$5) -> 0.016308002 | X57: =G57/$B$5 -> 0.035831417 | Y57: =X57+W57 -> 0.052139418 | Z57: =U57*(Y57-$E$9) -> 0.0015911047 | AA57: =MAX(0,MIN(1,(B57-$E$4)/$B$5)) -> 1 | AB57: =Z57*AA57 -> 0.0015911047 | AC57: =Z57-AB57 -> 0 | AD57: =Q57*$B$5 -> 0.25 | AE57: =AD57*AA57 -> 0.25 | AF57: =F57*(M57*(($E$9*$B$5)*Q57+R57)+$B$4*(M56-M57)*Q57) -> 0.018961454 | AG57: =S57 -> 0 | AH57: =IF(E57=1,ABS(P57-D57)*10000,0) -> 1.3877788e-13
A58: 27 | B58: =A58/2 -> 13.5 | C58: =ROUNDUP(A58/2,0) -> 14 | D58: =INDEX(Curves!$K$5:$K$34,C58) -> 0.041548432 | E58: =IF(C58<=$B$6,1,0) -> 1 | F58: =Curves!W32 -> 0.62788896 | G58: =Curves!X32 -> 0.018017377 | H58: =N57+D58*O57 -> 0.45730699 | I58: =F59*M57*((D58*$B$5+1)-$B$4) -> 0.32905202 | J58: =M57*(F58*((D58*$B$5)-$B$4)+F59*$B$4) -> 0.0073899641 | K58: =H58+F58*M57*$B$4-1 -> -0.32684598 | L58: =IF(E58=1,-2*LN((-J58+SQRT(J58^2-4*I58*K58))/(2*I58)),L57) -> 0.029260324 | M58: =M57*EXP(-L58*$B$5) -> 0.84693374 | N58: =N57+F58*$B$4*(M57-M58) -> 0.043890979 | O58: =O57+F58*M58*$B$5 -> 10.291561 | Q58: =IF(A58<=$B$9,MIN(A58,$B$10)/$B$10-MAX(0,MIN(A58-1,$B$9)-$B$7)/$B$8,0) -> 0.47826087 | R58: =IF(AND(A58>$B$7,A58<=$B$9),1/$B$8,0) -> 0.02173913 | S58: =IF(A58<=$B$10,1/$B$10,0) -> 0 | T58: =F57*M57*S58 -> 0 | U58: =F58*M58*$B$5*Q58 -> 0.12716487 | V58: =M58/M57 -> 0.98547634 | W58: =(1-V58)*(1+G58-$B$4)/(V58*$B$5) -> 0.018216318 | X58: =G58/$B$5 -> 0.036034754 | Y58: =X58+W58 -> 0.054251071 | Z58: =U58*(Y58-$E$9) -> 0.0017418058 | AA58: =MAX(0,MIN(1,(B58-$E$4)/$B$5)) -> 1 | AB58: =Z58*AA58 -> 0.0017418058 | AC58: =Z58-AB58 -> 0 | AD58: =Q58*$B$5 -> 0.23913043 | AE58: =AD58*AA58 -> 0.23913043 | AF58: =F58*(M58*(($E$9*$B$5)*Q58+R58)+$B$4*(M57-M58)*Q58) -> 0.018216762 | AG58: =S58 -> 0 | AH58: 0
A59: 28 | B59: =A59/2 -> 14 | C59: =ROUNDUP(A59/2,0) -> 14 | D59: =INDEX(Curves!$K$5:$K$34,C59) -> 0.041548432 | E59: =IF(C59<=$B$6,1,0) -> 1 | F59: =Curves!W33 -> 0.61677627 | G59: =Curves!X33 -> 0.018017377 | L59: =L58 -> 0.029260324 | M59: =M58*EXP(-L59*$B$5) -> 0.83463316 | N59: =N58+F59*$B$4*(M58-M59) -> 0.046925661 | O59: =O58+F59*M59*$B$5 -> 10.548952 | P59: =IF(E59=1,(1-N59-F59*M59)/O59,"") -> 0.041548432 | Q59: =IF(A59<=$B$9,MIN(A59,$B$10)/$B$10-MAX(0,MIN(A59-1,$B$9)-$B$7)/$B$8,0) -> 0.45652174 | R59: =IF(AND(A59>$B$7,A59<=$B$9),1/$B$8,0) -> 0.02173913 | S59: =IF(A59<=$B$10,1/$B$10,0) -> 0 | T59: =F58*M58*S59 -> 0 | U59: =F59*M59*$B$5*Q59 -> 0.11750457 | V59: =M59/M58 -> 0.98547634 | W59: =(1-V59)*(1+G59-$B$4)/(V59*$B$5) -> 0.018216318 | X59: =G59/$B$5 -> 0.036034754 | Y59: =X59+W59 -> 0.054251071 | Z59: =U59*(Y59-$E$9) -> 0.0016094866 | AA59: =MAX(0,MIN(1,(B59-$E$4)/$B$5)) -> 1 | AB59: =Z59*AA59 -> 0.0016094866 | AC59: =Z59-AB59 -> 0 | AD59: =Q59*$B$5 -> 0.22826087 | AE59: =AD59*AA59 -> 0.22826087 | AF59: =F59*(M59*(($E$9*$B$5)*Q59+R59)+$B$4*(M58-M59)*Q59) -> 0.017341572 | AG59: =S59 -> 0 | AH59: =IF(E59=1,ABS(P59-D59)*10000,0) -> 1.3877788e-13
A60: 29 | B60: =A60/2 -> 14.5 | C60: =ROUNDUP(A60/2,0) -> 15 | D60: =INDEX(Curves!$K$5:$K$34,C60) -> 0.042116549 | E60: =IF(C60<=$B$6,1,0) -> 1 | F60: =Curves!W34 -> 0.60579833 | G60: =Curves!X34 -> 0.018121451 | H60: =N59+D60*O59 -> 0.49121111 | I60: =F61*M59*((D60*$B$5+1)-$B$4) -> 0.3084299 | J60: =M59*(F60*((D60*$B$5)-$B$4)+F61*$B$4) -> 0.0070476824 | K60: =H60+F60*M59*$B$4-1 -> -0.30654114 | L60: =IF(E60=1,-2*LN((-J60+SQRT(J60^2-4*I60*K60))/(2*I60)),L59) -> 0.029062589 | M60: =M59*EXP(-L60*$B$5) -> 0.82259256 | N60: =N59+F60*$B$4*(M59-M60) -> 0.049843333 | O60: =O59+F60*M60*$B$5 -> 10.798114 | Q60: =IF(A60<=$B$9,MIN(A60,$B$10)/$B$10-MAX(0,MIN(A60-1,$B$9)-$B$7)/$B$8,0) -> 0.43478261 | R60: =IF(AND(A60>$B$7,A60<=$B$9),1/$B$8,0) -> 0.02173913 | S60: =IF(A60<=$B$10,1/$B$10,0) -> 0 | T60: =F59*M59*S60 -> 0 | U60: =F60*M60*$B$5*Q60 -> 0.10833156 | V60: =M60/M59 -> 0.98557378 | W60: =(1-V60)*(1+G60-$B$4)/(V60*$B$5) -> 0.018095366 | X60: =G60/$B$5 -> 0.036242901 | Y60: =X60+W60 -> 0.054338267 | Z60: =U60*(Y60-$E$9) -> 0.0014932879 | AA60: =MAX(0,MIN(1,(B60-$E$4)/$B$5)) -> 1 | AB60: =Z60*AA60 -> 0.0014932879 | AC60: =Z60-AB60 -> 0 | AD60: =Q60*$B$5 -> 0.2173913 | AE60: =AD60*AA60 -> 0.2173913 | AF60: =F60*(M60*(($E$9*$B$5)*Q60+R60)+$B$4*(M59-M60)*Q60) -> 0.016494971 | AG60: =S60 -> 0 | AH60: 0
A61: 30 | B61: =A61/2 -> 15 | C61: =ROUNDUP(A61/2,0) -> 15 | D61: =INDEX(Curves!$K$5:$K$34,C61) -> 0.042116549 | E61: =IF(C61<=$B$6,1,0) -> 1 | F61: =Curves!W35 -> 0.59501578 | G61: =Curves!X35 -> 0.018121451 | L61: =L60 -> 0.029062589 | M61: =M60*EXP(-L61*$B$5) -> 0.81072565 | N61: =N60+F61*$B$4*(M60-M61) -> 0.052667731 | O61: =O60+F61*M61*$B$5 -> 11.039312 | P61: =IF(E61=1,(1-N61-F61*M61)/O61,"") -> 0.042116549 | Q61: =IF(A61<=$B$9,MIN(A61,$B$10)/$B$10-MAX(0,MIN(A61-1,$B$9)-$B$7)/$B$8,0) -> 0.41304348 | R61: =IF(AND(A61>$B$7,A61<=$B$9),1/$B$8,0) -> 0.02173913 | S61: =IF(A61<=$B$10,1/$B$10,0) -> 0 | T61: =F60*M60*S61 -> 0 | U61: =F61*M61*$B$5*Q61 -> 0.099624962 | V61: =M61/M60 -> 0.98557378 | W61: =(1-V61)*(1+G61-$B$4)/(V61*$B$5) -> 0.018095366 | X61: =G61/$B$5 -> 0.036242901 | Y61: =X61+W61 -> 0.054338267 | Z61: =U61*(Y61-$E$9) -> 0.0013732724 | AA61: =MAX(0,MIN(1,(B61-$E$4)/$B$5)) -> 1 | AB61: =Z61*AA61 -> 0.0013732724 | AC61: =Z61-AB61 -> 0 | AD61: =Q61*$B$5 -> 0.20652174 | AE61: =AD61*AA61 -> 0.20652174 | AF61: =F61*(M61*(($E$9*$B$5)*Q61+R61)+$B$4*(M60-M61)*Q61) -> 0.015693613 | AG61: =S61 -> 0 | AH61: =IF(E61=1,ABS(P61-D61)*10000,0) -> 0
A62: 31 | B62: =A62/2 -> 15.5 | C62: =ROUNDUP(A62/2,0) -> 16 | D62: =INDEX(Curves!$K$5:$K$34,C62) -> 0.042325472 | E62: =IF(C62<=$B$6,1,0) -> 1 | F62: =Curves!W36 -> 0.58531642 | G62: =Curves!X36 -> 0.016571135 | H62: =N61+D62*O61 -> 0.51991181 | I62: =F63*M61*((D62*$B$5+1)-$B$4) -> 0.28995609 | J62: =M61*(F62*((D62*$B$5)-$B$4)+F63*$B$4) -> 0.0069482412 | K62: =H62+F62*M61*$B$4-1 -> -0.29027577 | L62: =IF(E62=1,-2*LN((-J62+SQRT(J62^2-4*I62*K62))/(2*I62)),L61) -> 0.022847405 | M62: =M61*EXP(-L62*$B$5) -> 0.80151686 | N62: =N61+F62*$B$4*(M61-M62) -> 0.054823753 | O62: =O61+F62*M62*$B$5 -> 11.273882 | Q62: =IF(A62<=$B$9,MIN(A62,$B$10)/$B$10-MAX(0,MIN(A62-1,$B$9)-$B$7)/$B$8,0) -> 0.39130435 | R62: =IF(AND(A62>$B$7,A62<=$B$9),1/$B$8,0) -> 0.02173913 | S62: =IF(A62<=$B$10,1/$B$10,0) -> 0 | T62: =F61*M61*S62 -> 0 | U62: =F62*M62*$B$5*Q62 -> 0.091788453 | V62: =M62/M61 -> 0.9886413 | W62: =(1-V62)*(1+G62-$B$4)/(V62*$B$5) -> 0.014167821 | X62: =G62/$B$5 -> 0.03314227 | Y62: =X62+W62 -> 0.047310091 | Z62: =U62*(Y62-$E$9) -> 0.00062014525 | AA62: =MAX(0,MIN(1,(B62-$E$4)/$B$5)) -> 1 | AB62: =Z62*AA62 -> 0.00062014525 | AC62: =Z62-AB62 -> 0 | AD62: =Q62*$B$5 -> 0.19565217 | AE62: =AD62*AA62 -> 0.19565217 | AF62: =F62*(M62*(($E$9*$B$5)*Q62+R62)+$B$4*(M61-M62)*Q62) -> 0.014764753 | AG62: =S62 -> 0 | AH62: 0
A63: 32 | B63: =A63/2 -> 16 | C63: =ROUNDUP(A63/2,0) -> 16 | D63: =INDEX(Curves!$K$5:$K$34,C63) -> 0.042325472 | E63: =IF(C63<=$B$6,1,0) -> 1 | F63: =Curves!W37 -> 0.57577517 | G63: =Curves!X37 -> 0.016571135 | L63: =L62 -> 0.022847405 | M63: =M62*EXP(-L63*$B$5) -> 0.79241267 | N63: =N62+F63*$B$4*(M62-M63) -> 0.05692054 | O63: =O62+F63*M63*$B$5 -> 11.502008 | P63: =IF(E63=1,(1-N63-F63*M63)/O63,"") -> 0.042325472 | Q63: =IF(A63<=$B$9,MIN(A63,$B$10)/$B$10-MAX(0,MIN(A63-1,$B$9)-$B$7)/$B$8,0) -> 0.36956522 | R63: =IF(AND(A63>$B$7,A63<=$B$9),1/$B$8,0) -> 0.02173913 | S63: =IF(A63<=$B$10,1/$B$10,0) -> 0 | T63: =F62*M62*S63 -> 0 | U63: =F63*M63*$B$5*Q63 -> 0.08430735 | V63: =M63/M62 -> 0.9886413 | W63: =(1-V63)*(1+G63-$B$4)/(V63*$B$5) -> 0.014167821 | X63: =G63/$B$5 -> 0.03314227 | Y63: =X63+W63 -> 0.047310091 | Z63: =U63*(Y63-$E$9) -> 0.00056960109 | AA63: =MAX(0,MIN(1,(B63-$E$4)/$B$5)) -> 1 | AB63: =Z63*AA63 -> 0.00056960109 | AC63: =Z63-AB63 -> 0 | AD63: =Q63*$B$5 -> 0.18478261 | AE63: =AD63*AA63 -> 0.18478261 | AF63: =F63*(M63*(($E$9*$B$5)*Q63+R63)+$B$4*(M62-M63)*Q63) -> 0.014112398 | AG63: =S63 -> 0 | AH63: =IF(E63=1,ABS(P63-D63)*10000,0) -> 0
A64: 33 | B64: =A64/2 -> 16.5 | C64: =ROUNDUP(A64/2,0) -> 17 | D64: =INDEX(Curves!$K$5:$K$34,C64) -> 0.042534373 | E64: =IF(C64<=$B$6,1,0) -> 1 | F64: =Curves!W38 -> 0.56644863 | G64: =Curves!X38 -> 0.016464948 | H64: =N63+D64*O63 -> 0.54615124 | I64: =F65*M63*((D64*$B$5+1)-$B$4) -> 0.27434557 | J64: =M63*(F64*((D64*$B$5)-$B$4)+F65*$B$4) -> 0.0066377075 | K64: =H64+F64*M63*$B$4-1 -> -0.27430433 | L64: =IF(E64=1,-2*LN((-J64+SQRT(J64^2-4*I64*K64))/(2*I64)),L63) -> 0.024346253 | M64: =M63*EXP(-L64*$B$5) -> 0.78282501 | N64: =N63+F64*$B$4*(M63-M64) -> 0.059092908 | O64: =O63+F64*M64*$B$5 -> 11.723723 | Q64: =IF(A64<=$B$9,MIN(A64,$B$10)/$B$10-MAX(0,MIN(A64-1,$B$9)-$B$7)/$B$8,0) -> 0.34782609 | R64: =IF(AND(A64>$B$7,A64<=$B$9),1/$B$8,0) -> 0.02173913 | S64: =IF(A64<=$B$10,1/$B$10,0) -> 0 | T64: =F63*M63*S64 -> 0 | U64: =F64*M64*$B$5*Q64 -> 0.077118287 | V64: =M64/M63 -> 0.98790067 | W64: =(1-V64)*(1+G64-$B$4)/(V64*$B$5) -> 0.015100334 | X64: =G64/$B$5 -> 0.032929897 | Y64: =X64+W64 -> 0.048030231 | Z64: =U64*(Y64-$E$9) -> 0.00057656596 | AA64: =MAX(0,MIN(1,(B64-$E$4)/$B$5)) -> 1 | AB64: =Z64*AA64 -> 0.00057656596 | AC64: =Z64-AB64 -> 0 | AD64: =Q64*$B$5 -> 0.17391304 | AE64: =AD64*AA64 -> 0.17391304 | AF64: =F64*(M64*(($E$9*$B$5)*Q64+R64)+$B$4*(M63-M64)*Q64) -> 0.013522835 | AG64: =S64 -> 0 | AH64: 0
A65: 34 | B65: =A65/2 -> 17 | C65: =ROUNDUP(A65/2,0) -> 17 | D65: =INDEX(Curves!$K$5:$K$34,C65) -> 0.042534373 | E65: =IF(C65<=$B$6,1,0) -> 1 | F65: =Curves!W39 -> 0.55727315 | G65: =Curves!X39 -> 0.016464948 | L65: =L64 -> 0.024346253 | M65: =M64*EXP(-L65*$B$5) -> 0.77335334 | N65: =N64+F65*$B$4*(M64-M65) -> 0.061204229 | O65: =O64+F65*M65*$B$5 -> 11.939208 | P65: =IF(E65=1,(1-N65-F65*M65)/O65,"") -> 0.042534373 | Q65: =IF(A65<=$B$9,MIN(A65,$B$10)/$B$10-MAX(0,MIN(A65-1,$B$9)-$B$7)/$B$8,0) -> 0.32608696 | R65: =IF(AND(A65>$B$7,A65<=$B$9),1/$B$8,0) -> 0.02173913 | S65: =IF(A65<=$B$10,1/$B$10,0) -> 0 | T65: =F64*M64*S65 -> 0 | U65: =F65*M65*$B$5*Q65 -> 0.070266694 | V65: =M65/M64 -> 0.98790067 | W65: =(1-V65)*(1+G65-$B$4)/(V65*$B$5) -> 0.015100334 | X65: =G65/$B$5 -> 0.032929897 | Y65: =X65+W65 -> 0.048030231 | Z65: =U65*(Y65-$E$9) -> 0.00052534082 | AA65: =MAX(0,MIN(1,(B65-$E$4)/$B$5)) -> 1 | AB65: =Z65*AA65 -> 0.00052534082 | AC65: =Z65-AB65 -> 0 | AD65: =Q65*$B$5 -> 0.16304348 | AE65: =AD65*AA65 -> 0.16304348 | AF65: =F65*(M65*(($E$9*$B$5)*Q65+R65)+$B$4*(M64-M65)*Q65) -> 0.012906951 | AG65: =S65 -> 0 | AH65: =IF(E65=1,ABS(P65-D65)*10000,0) -> 0
